Workbook

Sheet Opzet
A1: Index | B1: =COLUMN() -> 2 | C1: =COLUMN() -> 3 | D1: =COLUMN() -> 4 | E1: =COLUMN() -> 5 | F1: =COLUMN() -> 6 | G1: =COLUMN() -> 7 | H1: =COLUMN() -> 8 | I1: =COLUMN() -> 9 | ... P1: =COLUMN() -> 16
A2: =ROW() -> 2 | B2: Omschrijving | C2: Opening | D2: Jaar 1 | E2: =D2 -> Jaar 1 | F2: =E2 -> Jaar 1 | G2: =F2 -> Jaar 1 | H2: =G2 -> Jaar 1 | I2: =H2 -> Jaar 1 | J2: =I2 -> Jaar 1 | K2: =J2 -> Jaar 1 | L2: =K2 -> Jaar 1 | ... P2: =O2 -> Jaar 1
A3: =ROW() -> 3 | D3: ACT/BUD/FCST | E3: ACT/BUD/FCST | F3: ACT/BUD/FCST | G3: ACT/BUD/FCST | H3: ACT/BUD/FCST | I3: ACT/BUD/FCST | J3: ACT/BUD/FCST | K3: ACT/BUD/FCST | L3: ACT/BUD/FCST | M3: ACT/BUD/FCST | N3: ACT/BUD/FCST | O3: ACT/BUD/FCST | P3: ACT/BUD/FCST
A4: =ROW() -> 4 | D4: Maand 1 | E4: Maand 2 | F4: Maand 3 | G4: Maand 4 | H4: Maand 5 | I4: Maand 6 | J4: Maand 7 | K4: Maand 8 | L4: Maand 9 | M4: Maand 10 | N4: Maand 11 | O4: Maand 12 | P4: Totaal
A5: =ROW() -> 5
A6: =ROW() -> 6
A7: =ROW() -> 7
A8: =ROW() -> 8
A9: =ROW() -> 9
A10: =ROW() -> 10
A11: =ROW() -> 11
A12: =ROW() -> 12
A13: =ROW() -> 13
A14: =ROW() -> 14
A15: =ROW() -> 15
A16: =ROW() -> 16
... A27: =ROW() -> 27

Sheet RFF
A1: Index | B1: =COLUMN() -> 2 | C1: =COLUMN() -> 3 | D1: =COLUMN() -> 4 | E1: =COLUMN() -> 5 | F1: =COLUMN() -> 6 | G1: =COLUMN() -> 7 | H1: =COLUMN() -> 8 | I1: =COLUMN() -> 9 | ... AP1: =COLUMN() -> 42
A2: =ROW() -> 2 | B2: Omschrijving | C2: Opening | D2: 2026 | E2: =D2 -> 2026 | F2: =E2 -> 2026 | G2: =F2 -> 2026 | H2: =G2 -> 2026 | I2: =H2 -> 2026 | J2: =I2 -> 2026 | K2: =J2 -> 2026 | L2: =K2 -> 2026 | ... P2: =O2 -> 2026 | Q2: 2027 | R2: =Q2 -> 2027 | S2: =R2 -> 2027 | T2: =S2 -> 2027 | U2: =T2 -> 2027 | V2: =U2 -> 2027 | W2: =V2 -> 2027 | X2: =W2 -> 2027 | Y2: =X2 -> 2027 | ... AC2: =AB2 -> 2027 | AD2: 2028 | AE2: =AD2 -> 2028 | AF2: =AE2 -> 2028 | AG2: =AF2 -> 2028 | AH2: =AG2 -> 2028 | AI2: =AH2 -> 2028 | AJ2: =AI2 -> 2028 | AK2: =AJ2 -> 2028 | AL2: =AK2 -> 2028 | ... AP2: =AO2 -> 2028
A3: =ROW() -> 3 | D3: FCST | E3: =D3 -> FCST | F3: =E3 -> FCST | G3: =F3 -> FCST | H3: =G3 -> FCST | I3: =H3 -> FCST | J3: =I3 -> FCST | K3: =J3 -> FCST | L3: =K3 -> FCST | ... P3: =O3 -> FCST | Q3: FCST | R3: =Q3 -> FCST | S3: =R3 -> FCST | T3: =S3 -> FCST | U3: =T3 -> FCST | V3: =U3 -> FCST | W3: =V3 -> FCST | X3: =W3 -> FCST | Y3: =X3 -> FCST | ... AC3: =AB3 -> FCST | AD3: FCST | AE3: =AD3 -> FCST | AF3: =AE3 -> FCST | AG3: =AF3 -> FCST | AH3: =AG3 -> FCST | AI3: =AH3 -> FCST | AJ3: =AI3 -> FCST | AK3: =AJ3 -> FCST | AL3: =AK3 -> FCST | ... AP3: =AO3 -> FCST
A4: =ROW() -> 4 | D4: 1 | E4: =D4+1 -> 2 | F4: =E4+1 -> 3 | G4: =F4+1 -> 4 | H4: =G4+1 -> 5 | I4: =H4+1 -> 6 | J4: =I4+1 -> 7 | K4: =J4+1 -> 8 | L4: =K4+1 -> 9 | ... O4: =N4+1 -> 12 | P4: Totaal | Q4: 1 | R4: =Q4+1 -> 2 | S4: =R4+1 -> 3 | T4: =S4+1 -> 4 | U4: =T4+1 -> 5 | V4: =U4+1 -> 6 | W4: =V4+1 -> 7 | X4: =W4+1 -> 8 | Y4: =X4+1 -> 9 | ... AB4: =AA4+1 -> 12 | AC4: Totaal | AD4: 1 | AE4: =AD4+1 -> 2 | AF4: =AE4+1 -> 3 | AG4: =AF4+1 -> 4 | AH4: =AG4+1 -> 5 | AI4: =AH4+1 -> 6 | AJ4: =AI4+1 -> 7 | AK4: =AJ4+1 -> 8 | AL4: =AK4+1 -> 9 | ... AO4: =AN4+1 -> 12 | AP4: Totaal
A5: =ROW() -> 5
A6: =ROW() -> 6 | B6: KPI
A7: =ROW() -> 7 | B7: Aantal klanten Foundation | D7: 0 | E7: 0 | F7: 0 | G7: 1 | H7: 1 | I7: 1 | J7: 2 | K7: 2 | L7: 2 | M7: 3 | N7: 3 | O7: 3 | P7: =AVERAGE(D7:O7) -> 1.5 | Q7: =O7+2 -> 5 | R7: =Q7 -> 5 | S7: =R7+1 -> 6 | T7: =S7 -> 6 | U7: =T7+1 -> 7 | V7: =U7 -> 7 | W7: =V7 -> 7 | X7: =W7 -> 7 | Y7: =X7+1 -> 8 | Z7: =Y7 -> 8 | AA7: =Z7 -> 8 | AB7: =AA7 -> 8 | AC7: =AVERAGE(Q7:AB7) -> 6.8333333 | AD7: =AB7+2 -> 10 | AE7: =AD7 -> 10 | AF7: =AE7+1 -> 11 | AG7: =AF7 -> 11 | AH7: =AG7+1 -> 12 | AI7: =AH7 -> 12 | AJ7: =AI7 -> 12 | AK7: =AJ7 -> 12 | AL7: =AK7+1 -> 13 | AM7: =AL7 -> 13 | AN7: =AM7 -> 13 | AO7: =AN7 -> 13 | AP7: =AVERAGE(AD7:AO7) -> 11.833333
A8: =ROW() -> 8 | B8: Aantal klanten Growth | D8: 0 | E8: 0 | F8: 0 | G8: 0 | H8: 0 | I8: 0 | J8: 1 | K8: 1 | L8: 1 | M8: 1 | N8: 1 | O8: 1 | P8: =AVERAGE(D8:O8) -> 0.5 | Q8: =O8*1 -> 1 | R8: =Q8 -> 1 | S8: =R8 -> 1 | T8: =S8+1 -> 2 | U8: =T8 -> 2 | V8: =U8 -> 2 | W8: =V8 -> 2 | X8: =W8 -> 2 | Y8: =X8 -> 2 | Z8: =Y8 -> 2 | AA8: =Z8 -> 2 | AB8: =AA8 -> 2 | AC8: =AVERAGE(Q8:AB8) -> 1.75 | AD8: =AB8+1 -> 3 | AE8: =AD8 -> 3 | AF8: =AE8 -> 3 | AG8: =AF8+1 -> 4 | AH8: =AG8 -> 4 | AI8: =AH8 -> 4 | AJ8: =AI8 -> 4 | AK8: =AJ8 -> 4 | AL8: =AK8 -> 4 | AM8: =AL8 -> 4 | AN8: =AM8 -> 4 | AO8: =AN8 -> 4 | AP8: =AVERAGE(AD8:AO8) -> 3.75
A9: =ROW() -> 9 | B9: Aantal klanten Scale | D9: 0 | E9: 0 | F9: 0 | G9: 0 | H9: 0 | I9: 0 | J9: 0 | K9: 0 | L9: 0 | M9: 0.5 | N9: 0.5 | O9: 0.5 | P9: =AVERAGE(D9:O9) -> 0.125 | Q9: =O9*2 -> 1 | R9: =Q9 -> 1 | S9: =R9 -> 1 | T9: =S9 -> 1 | U9: =T9 -> 1 | V9: =U9+0.5 -> 1.5 | W9: =V9 -> 1.5 | X9: =W9 -> 1.5 | Y9: =X9 -> 1.5 | Z9: =Y9+0.5 -> 2 | AA9: =Z9 -> 2 | AB9: =AA9 -> 2 | AC9: =AVERAGE(Q9:AB9) -> 1.4166667 | AD9: =AB9+1 -> 3 | AE9: =AD9 -> 3 | AF9: =AE9 -> 3 | AG9: =AF9 -> 3 | AH9: =AG9 -> 3 | AI9: =AH9+0.5 -> 3.5 | AJ9: =AI9 -> 3.5 | AK9: =AJ9 -> 3.5 | AL9: =AK9 -> 3.5 | AM9: =AL9+0.5 -> 4 | AN9: =AM9 -> 4 | AO9: =AN9 -> 4 | AP9: =AVERAGE(AD9:AO9) -> 3.4166667
A10: =ROW() -> 10
A11: =ROW() -> 11 | B11: Tarief klanten Foundation | D11: =Pakketten!C3 -> 6750 | E11: =D11 -> 6750 | F11: =E11 -> 6750 | G11: =F11 -> 6750 | H11: =G11 -> 6750 | I11: =H11 -> 6750 | J11: =I11 -> 6750 | K11: =J11 -> 6750 | L11: =K11 -> 6750 | ... O11: =N11 -> 6750 | P11: =AVERAGE(D11:O11) -> 6750 | Q11: =O11*1.05 -> 7087.5 | R11: =Q11 -> 7087.5 | S11: =R11 -> 7087.5 | T11: =S11 -> 7087.5 | U11: =T11 -> 7087.5 | V11: =U11 -> 7087.5 | W11: =V11 -> 7087.5 | X11: =W11 -> 7087.5 | Y11: =X11 -> 7087.5 | ... AB11: =AA11 -> 7087.5 | AC11: =AVERAGE(Q11:AB11) -> 7087.5 | AD11: =AB11*1.05 -> 7441.875 | AE11: =AD11 -> 7441.875 | AF11: =AE11 -> 7441.875 | AG11: =AF11 -> 7441.875 | AH11: =AG11 -> 7441.875 | AI11: =AH11 -> 7441.875 | AJ11: =AI11 -> 7441.875 | AK11: =AJ11 -> 7441.875 | AL11: =AK11 -> 7441.875 | ... AO11: =AN11 -> 7441.875 | AP11: =AVERAGE(AD11:AO11) -> 7441.875
A12: =ROW() -> 12 | B12: Tarief klanten Growth | D12: =Pakketten!K3 -> 17000 | E12: =D12 -> 17000 | F12: =E12 -> 17000 | G12: =F12 -> 17000 | H12: =G12 -> 17000 | I12: =H12 -> 17000 | J12: =I12 -> 17000 | K12: =J12 -> 17000 | L12: =K12 -> 17000 | ... O12: =N12 -> 17000 | P12: =AVERAGE(D12:O12) -> 17000 | Q12: =O12*1.05 -> 17850 | R12: =Q12 -> 17850 | S12: =R12 -> 17850 | T12: =S12 -> 17850 | U12: =T12 -> 17850 | V12: =U12 -> 17850 | W12: =V12 -> 17850 | X12: =W12 -> 17850 | Y12: =X12 -> 17850 | ... AB12: =AA12 -> 17850 | AC12: =AVERAGE(Q12:AB12) -> 17850 | AD12: =AB12*1.05 -> 18742.5 | AE12: =AD12 -> 18742.5 | AF12: =AE12 -> 18742.5 | AG12: =AF12 -> 18742.5 | AH12: =AG12 -> 18742.5 | AI12: =AH12 -> 18742.5 | AJ12: =AI12 -> 18742.5 | AK12: =AJ12 -> 18742.5 | AL12: =AK12 -> 18742.5 | ... AO12: =AN12 -> 18742.5 | AP12: =AVERAGE(AD12:AO12) -> 18742.5
A13: =ROW() -> 13 | B13: Tarief klanten Scale | D13: =Pakketten!S3 -> 27000 | E13: =D13 -> 27000 | F13: =E13 -> 27000 | G13: =F13 -> 27000 | H13: =G13 -> 27000 | I13: =H13 -> 27000 | J13: =I13 -> 27000 | K13: =J13 -> 27000 | L13: =K13 -> 27000 | ... O13: =N13 -> 27000 | P13: =AVERAGE(D13:O13) -> 27000 | Q13: =O13*1.05 -> 28350 | R13: =Q13 -> 28350 | S13: =R13 -> 28350 | T13: =S13 -> 28350 | U13: =T13 -> 28350 | V13: =U13 -> 28350 | W13: =V13 -> 28350 | X13: =W13 -> 28350 | Y13: =X13 -> 28350 | ... AB13: =AA13 -> 28350 | AC13: =AVERAGE(Q13:AB13) -> 28350 | AD13: =AB13*1.05 -> 29767.5 | AE13: =AD13 -> 29767.5 | AF13: =AE13 -> 29767.5 | AG13: =AF13 -> 29767.5 | AH13: =AG13 -> 29767.5 | AI13: =AH13 -> 29767.5 | AJ13: =AI13 -> 29767.5 | AK13: =AJ13 -> 29767.5 | AL13: =AK13 -> 29767.5 | ... AO13: =AN13 -> 29767.5 | AP13: =AVERAGE(AD13:AO13) -> 29767.5
A14: =ROW() -> 14
A15: =ROW() -> 15 | B15: MRR klanten Foundation | D15: =D7*D11 -> 0 | E15: =E7*E11 -> 0 | F15: =F7*F11 -> 0 | G15: =G7*G11 -> 6750 | H15: =H7*H11 -> 6750 | I15: =I7*I11 -> 6750 | J15: =J7*J11 -> 13500 | K15: =K7*K11 -> 13500 | ... O15: =O7*O11 -> 20250 | P15: =AVERAGE(D15:O15) -> 10125 | Q15: =Q7*Q11 -> 35437.5 | R15: =R7*R11 -> 35437.5 | S15: =S7*S11 -> 42525 | T15: =T7*T11 -> 42525 | U15: =U7*U11 -> 49612.5 | V15: =V7*V11 -> 49612.5 | W15: =W7*W11 -> 49612.5 | X15: =X7*X11 -> 49612.5 | ... AB15: =AB7*AB11 -> 56700 | AC15: =AVERAGE(Q15:AB15) -> 48431.25 | AD15: =AD7*AD11 -> 74418.75 | AE15: =AE7*AE11 -> 74418.75 | AF15: =AF7*AF11 -> 81860.625 | AG15: =AG7*AG11 -> 81860.625 | AH15: =AH7*AH11 -> 89302.5 | AI15: =AI7*AI11 -> 89302.5 | AJ15: =AJ7*AJ11 -> 89302.5 | AK15: =AK7*AK11 -> 89302.5 | ... AO15: =AO7*AO11 -> 96744.375 | AP15: =AVERAGE(AD15:AO15) -> 88062.188
A16: =ROW() -> 16 | B16: MRR klanten Growth | D16: =D8*D12 -> 0 | E16: =E8*E12 -> 0 | F16: =F8*F12 -> 0 | G16: =G8*G12 -> 0 | H16: =H8*H12 -> 0 | I16: =I8*I12 -> 0 | J16: =J8*J12 -> 17000 | K16: =K8*K12 -> 17000 | ... O16: =O8*O12 -> 17000 | P16: =AVERAGE(D16:O16) -> 8500 | Q16: =Q8*Q12 -> 17850 | R16: =R8*R12 -> 17850 | S16: =S8*S12 -> 17850 | T16: =T8*T12 -> 35700 | U16: =U8*U12 -> 35700 | V16: =V8*V12 -> 35700 | W16: =W8*W12 -> 35700 | X16: =X8*X12 -> 35700 | ... AB16: =AB8*AB12 -> 35700 | AC16: =AVERAGE(Q16:AB16) -> 31237.5 | AD16: =AD8*AD12 -> 56227.5 | AE16: =AE8*AE12 -> 56227.5 | AF16: =AF8*AF12 -> 56227.5 | AG16: =AG8*AG12 -> 74970 | AH16: =AH8*AH12 -> 74970 | AI16: =AI8*AI12 -> 74970 | AJ16: =AJ8*AJ12 -> 74970 | AK16: =AK8*AK12 -> 74970 | ... AO16: =AO8*AO12 -> 74970 | AP16: =AVERAGE(AD16:AO16) -> 70284.375
A17: =ROW() -> 17 | B17: MRR klanten Scale | D17: =D9*D13 -> 0 | E17: =E9*E13 -> 0 | F17: =F9*F13 -> 0 | G17: =G9*G13 -> 0 | H17: =H9*H13 -> 0 | I17: =I9*I13 -> 0 | J17: =J9*J13 -> 0 | K17: =K9*K13 -> 0 | ... O17: =O9*O13 -> 13500 | P17: =AVERAGE(D17:O17) -> 3375 | Q17: =Q9*Q13 -> 28350 | R17: =R9*R13 -> 28350 | S17: =S9*S13 -> 28350 | T17: =T9*T13 -> 28350 | U17: =U9*U13 -> 28350 | V17: =V9*V13 -> 42525 | W17: =W9*W13 -> 42525 | X17: =X9*X13 -> 42525 | ... AB17: =AB9*AB13 -> 56700 | AC17: =AVERAGE(Q17:AB17) -> 40162.5 | AD17: =AD9*AD13 -> 89302.5 | AE17: =AE9*AE13 -> 89302.5 | AF17: =AF9*AF13 -> 89302.5 | AG17: =AG9*AG13 -> 89302.5 | AH17: =AH9*AH13 -> 89302.5 | AI17: =AI9*AI13 -> 104186.25 | AJ17: =AJ9*AJ13 -> 104186.25 | AK17: =AK9*AK13 -> 104186.25 | ... AO17: =AO9*AO13 -> 119070 | AP17: =AVERAGE(AD17:AO17) -> 101705.62
A18: =ROW() -> 18
A19: =ROW() -> 19 | B19: FTEs
A20: =ROW() -> 20 | B20: - CEO (C-level) | D20: =OPEX!D17 -> 0.2 | E20: =OPEX!E17 -> 0.2 | F20: =OPEX!F17 -> 0.2 | G20: =OPEX!G17 -> 0.2 | H20: =OPEX!H17 -> 0.2 | I20: =OPEX!I17 -> 0.2 | J20: =OPEX!J17 -> 0.2 | K20: =OPEX!K17 -> 0.2 | L20: =OPEX!L17 -> 0.2 | M20: 0.6 | N20: 0.6 | O20: 0.6 | P20: =AVERAGE(D20:O20) -> 0.3 | Q20: 0.5 | R20: =Q20 -> 0.5 | S20: =R20 -> 0.5 | T20: 0.6 | U20: =T20 -> 0.6 | V20: =U20 -> 0.6 | W20: =V20 -> 0.6 | X20: =W20 -> 0.6 | Y20: 0.8 | Z20: =Y20 -> 0.8 | AA20: =Z20 -> 0.8 | AB20: =AA20 -> 0.8 | AC20: =AVERAGE(Q20:AB20) -> 0.64166667 | AD20: 1.4 | AE20: =AD20 -> 1.4 | AF20: =AE20 -> 1.4 | AG20: =AF20 -> 1.4 | AH20: =AG20 -> 1.4 | AI20: =AH20 -> 1.4 | AJ20: =AI20 -> 1.4 | AK20: =AJ20 -> 1.4 | AL20: =AK20 -> 1.4 | AM20: 1.6 | AN20: =AM20 -> 1.6 | AO20: =AN20 -> 1.6 | AP20: =AVERAGE(AD20:AO20) -> 1.45
A21: =ROW() -> 21 | B21: - CFO (C-level) | D21: =OPEX!D18 -> 0.6 | E21: =OPEX!E18 -> 0.6 | F21: =OPEX!F18 -> 0.6 | G21: =OPEX!G18 -> 0.6 | H21: =OPEX!H18 -> 0.6 | I21: =OPEX!I18 -> 0.6 | J21: =OPEX!J18 -> 0.6 | K21: =OPEX!K18 -> 0.6 | ... O21: =OPEX!O18 -> 0.6 | P21: =AVERAGE(D21:O21) -> 0.6 | Q21: 0.8 | R21: =Q21 -> 0.8 | S21: =R21 -> 0.8 | T21: 1 | U21: 1.4 | V21: =U21 -> 1.4 | W21: =V21 -> 1.4 | X21: =W21 -> 1.4 | Y21: =X21 -> 1.4 | Z21: =Y21 -> 1.4 | AA21: =Z21 -> 1.4 | AB21: =AA21 -> 1.4 | AC21: =AVERAGE(Q21:AB21) -> 1.2166667 | AD21: 2 | AE21: =AD21 -> 2 | AF21: =AE21 -> 2 | AG21: 2.2 | AH21: =AG21 -> 2.2 | AI21: =AH21 -> 2.2 | AJ21: =AI21 -> 2.2 | AK21: =AJ21 -> 2.2 | AL21: =AK21 -> 2.2 | AM21: 2.6 | AN21: =AM21 -> 2.6 | AO21: =AN21 -> 2.6 | AP21: =AVERAGE(AD21:AO21) -> 2.25
A22: =ROW() -> 22 | B22: - CMO (Senior-level) | D22: =OPEX!D19 -> 0 | E22: =OPEX!E19 -> 0 | F22: =OPEX!F19 -> 0 | G22: =OPEX!G19 -> 0 | H22: =OPEX!H19 -> 0 | I22: =OPEX!I19 -> 0 | J22: =OPEX!J19 -> 0.4 | K22: =OPEX!K19 -> 0.4 | L22: =OPEX!L19 -> 0.4 | M22: 0.6 | N22: 0.6 | O22: 0.6 | P22: =AVERAGE(D22:O22) -> 0.25 | Q22: 0.8 | R22: =Q22 -> 0.8 | S22: =R22 -> 0.8 | T22: 1 | U22: 1.2 | V22: =U22 -> 1.2 | W22: =V22 -> 1.2 | X22: =W22 -> 1.2 | Y22: =X22 -> 1.2 | Z22: 1.4 | AA22: =Z22 -> 1.4 | AB22: =AA22 -> 1.4 | AC22: =AVERAGE(Q22:AB22) -> 1.1333333 | AD22: 2 | AE22: =AD22 -> 2 | AF22: =AE22 -> 2 | AG22: 2.2 | AH22: =AG22 -> 2.2 | AI22: =AH22 -> 2.2 | AJ22: =AI22 -> 2.2 | AK22: =AJ22 -> 2.2 | AL22: =AK22 -> 2.2 | AM22: 2.6 | AN22: =AM22 -> 2.6 | AO22: =AN22 -> 2.6 | AP22: =AVERAGE(AD22:AO22) -> 2.25
A23: =ROW() -> 23 | B23: - CTO (Senior-level) | D23: =OPEX!D20 -> 0 | E23: =OPEX!E20 -> 0 | F23: =OPEX!F20 -> 0 | G23: =OPEX!G20 -> 0 | H23: =OPEX!H20 -> 0 | I23: =OPEX!I20 -> 0 | J23: =OPEX!J20 -> 0.4 | K23: =OPEX!K20 -> 0.4 | L23: =OPEX!L20 -> 0.4 | M23: 0.6 | N23: 0.6 | O23: 0.6 | P23: =AVERAGE(D23:O23) -> 0.25 | Q23: 0.8 | R23: =Q23 -> 0.8 | S23: =R23 -> 0.8 | T23: 1 | U23: 1.2 | V23: =U23 -> 1.2 | W23: =V23 -> 1.2 | X23: =W23 -> 1.2 | Y23: =X23 -> 1.2 | Z23: 1.4 | AA23: =Z23 -> 1.4 | AB23: =AA23 -> 1.4 | AC23: =AVERAGE(Q23:AB23) -> 1.1333333 | AD23: 2 | AE23: =AD23 -> 2 | AF23: =AE23 -> 2 | AG23: 2.4 | AH23: =AG23 -> 2.4 | AI23: =AH23 -> 2.4 | AJ23: =AI23 -> 2.4 | AK23: =AJ23 -> 2.4 | AL23: =AK23 -> 2.4 | AM23: 2.6 | AN23: =AM23 -> 2.6 | AO23: =AN23 -> 2.6 | AP23: =AVERAGE(AD23:AO23) -> 2.35
A24: =ROW() -> 24 | B24: - HR partner (Senior-level) | D24: =OPEX!D21 -> 0 | E24: =OPEX!E21 -> 0 | F24: =OPEX!F21 -> 0 | G24: =OPEX!G21 -> 0 | H24: =OPEX!H21 -> 0 | I24: =OPEX!I21 -> 0 | J24: =OPEX!J21 -> 0.4 | K24: =OPEX!K21 -> 0.4 | L24: =OPEX!L21 -> 0.4 | M24: 0.6 | N24: 0.6 | O24: 0.6 | P24: =AVERAGE(D24:O24) -> 0.25 | Q24: 0.8 | R24: 0.8 | S24: =R24 -> 0.8 | T24: 1.4 | U24: =T24 -> 1.4 | V24: =U24 -> 1.4 | W24: =V24 -> 1.4 | X24: =W24 -> 1.4 | Y24: =X24 -> 1.4 | Z24: =Y24 -> 1.4 | AA24: =Z24 -> 1.4 | AB24: =AA24 -> 1.4 | AC24: =AVERAGE(Q24:AB24) -> 1.25 | AD24: 2 | AE24: =AD24 -> 2 | AF24: =AE24 -> 2 | AG24: 2.4 | AH24: =AG24 -> 2.4 | AI24: =AH24 -> 2.4 | AJ24: =AI24 -> 2.4 | AK24: =AJ24 -> 2.4 | AL24: =AK24 -> 2.4 | AM24: 2.6 | AN24: =AM24 -> 2.6 | AO24: =AN24 -> 2.6 | AP24: =AVERAGE(AD24:AO24) -> 2.35
A25: =ROW() -> 25 | B25: - Finance admin (Sedior-level) | D25: =OPEX!D22 -> 0.4 | E25: =OPEX!E22 -> 0.4 | F25: =OPEX!F22 -> 0.4 | G25: =OPEX!G22 -> 0.4 | H25: =OPEX!H22 -> 0.4 | I25: =OPEX!I22 -> 0.4 | J25: 0.4 | K25: 0.4 | L25: 0.4 | M25: 0.6 | N25: =M25 -> 0.6 | O25: =N25 -> 0.6 | P25: =AVERAGE(D25:O25) -> 0.45 | Q25: 1 | R25: =Q25 -> 1 | S25: =R25 -> 1 | T25: 1.4 | U25: =T25 -> 1.4 | V25: =U25 -> 1.4 | W25: =V25 -> 1.4 | X25: =W25 -> 1.4 | Y25: =X25 -> 1.4 | Z25: =Y25 -> 1.4 | AA25: =Z25 -> 1.4 | AB25: =AA25 -> 1.4 | AC25: =AVERAGE(Q25:AB25) -> 1.3 | AD25: 2 | AE25: =AD25 -> 2 | AF25: =AE25 -> 2 | AG25: 2.4 | AH25: =AG25 -> 2.4 | AI25: =AH25 -> 2.4 | AJ25: =AI25 -> 2.4 | AK25: =AJ25 -> 2.4 | AL25: =AK25 -> 2.4 | AM25: 2.6 | AN25: =AM25 -> 2.6 | AO25: =AN25 -> 2.6 | AP25: =AVERAGE(AD25:AO25) -> 2.35
A26: =ROW() -> 26 | B26: - HR admin (Medior-level) | D26: =OPEX!D23 -> 0 | E26: =OPEX!E23 -> 0 | F26: =OPEX!F23 -> 0 | G26: =OPEX!G23 -> 0 | H26: =OPEX!H23 -> 0 | I26: =OPEX!I23 -> 0 | J26: =OPEX!J23 -> 0 | K26: =OPEX!K23 -> 0 | ... O26: =OPEX!O23 -> 0 | P26: =AVERAGE(D26:O26) -> 0 | Q26: =O26 -> 0 | R26: =Q26 -> 0 | S26: =R26 -> 0 | T26: =S26 -> 0 | U26: =T26 -> 0 | V26: =U26 -> 0 | W26: =V26 -> 0 | X26: =W26 -> 0 | Y26: =X26 -> 0 | ... AB26: =AA26 -> 0 | AC26: =AVERAGE(Q26:AB26) -> 0 | AD26: =AB26 -> 0 | AE26: =AD26 -> 0 | AF26: =AE26 -> 0 | AG26: =AF26 -> 0 | AH26: =AG26 -> 0 | AI26: =AH26 -> 0 | AJ26: =AI26 -> 0 | AK26: =AJ26 -> 0 | AL26: =AK26 -> 0 | ... AO26: =AN26 -> 0 | AP26: =AVERAGE(AD26:AO26) -> 0
A27: =ROW() -> 27 | B27: - Backoffice support (Junior-level) | D27: =OPEX!D24 -> 0 | E27: =OPEX!E24 -> 0 | F27: =OPEX!F24 -> 0 | G27: =OPEX!G24 -> 0 | H27: =OPEX!H24 -> 0 | I27: =OPEX!I24 -> 0 | J27: =OPEX!J24 -> 0.4 | K27: =OPEX!K24 -> 0.4 | ... O27: =OPEX!O24 -> 1 | P27: =AVERAGE(D27:O27) -> 0.4 | Q27: 1.6 | R27: =Q27 -> 1.6 | S27: =R27 -> 1.6 | T27: 2 | U27: 2.4 | V27: =U27 -> 2.4 | W27: =V27 -> 2.4 | X27: =W27 -> 2.4 | Y27: =X27 -> 2.4 | Z27: 3 | AA27: =Z27 -> 3 | AB27: =AA27 -> 3 | AC27: =AVERAGE(Q27:AB27) -> 2.3166667 | AD27: 4 | AE27: =AD27 -> 4 | AF27: =AE27 -> 4 | AG27: 4.4 | AH27: =AG27 -> 4.4 | AI27: =AH27 -> 4.4 | AJ27: =AI27 -> 4.4 | AK27: =AJ27 -> 4.4 | AL27: =AK27 -> 4.4 | AM27: 4.6 | AN27: =AM27 -> 4.6 | AO27: =AN27 -> 4.6 | AP27: =AVERAGE(AD27:AO27) -> 4.35
A28: =ROW() -> 28 | B28: - Data engineer (Medior-level) | D28: =OPEX!D25 -> 0 | E28: =OPEX!E25 -> 0 | F28: =OPEX!F25 -> 0 | G28: =OPEX!G25 -> 0 | H28: =OPEX!H25 -> 0 | I28: =OPEX!I25 -> 0 | J28: =OPEX!J25 -> 0.4 | K28: =OPEX!K25 -> 0.4 | ... O28: =OPEX!O25 -> 0.4 | P28: =AVERAGE(D28:O28) -> 0.2 | Q28: =O28 -> 0.4 | R28: =Q28 -> 0.4 | S28: =R28 -> 0.4 | T28: =S28 -> 0.4 | U28: =T28 -> 0.4 | V28: =U28 -> 0.4 | W28: =V28 -> 0.4 | X28: =W28 -> 0.4 | Y28: =X28 -> 0.4 | ... AB28: =AA28 -> 0.4 | AC28: =AVERAGE(Q28:AB28) -> 0.4 | AD28: =AB28 -> 0.4 | AE28: =AD28 -> 0.4 | AF28: =AE28 -> 0.4 | AG28: =AF28 -> 0.4 | AH28: =AG28 -> 0.4 | AI28: =AH28 -> 0.4 | AJ28: =AI28 -> 0.4 | AK28: =AJ28 -> 0.4 | AL28: =AK28 -> 0.4 | ... AO28: =AN28 -> 0.4 | AP28: =AVERAGE(AD28:AO28) -> 0.4
A29: =ROW() -> 29
A30: =ROW() -> 30 | B30: Werkbare dagen | D30: 21 | E30: 20 | F30: 22 | G30: 20 | H30: 19 | I30: 22 | J30: 23 | K30: 21 | L30: 22 | M30: 22 | N30: 21 | O30: 22 | Q30: 21 | R30: 20 | S30: 22 | T30: 20 | U30: 19 | V30: 22 | W30: 23 | X30: 21 | Y30: 22 | Z30: 22 | AA30: 21 | AB30: 22 | AD30: 21 | AE30: 20 | AF30: 22 | AG30: 20 | AH30: 19 | AI30: 22 | AJ30: 23 | AK30: 21 | AL30: 22 | AM30: 22 | AN30: 21 | AO30: 22
A31: =ROW() -> 31
A32: =ROW() -> 32 | B32: Norm uren klanten Foundation | D32: =Pakketten!$C$19 -> 32 | E32: =Pakketten!$C$19 -> 32 | F32: =Pakketten!$C$19 -> 32 | G32: =Pakketten!$C$19 -> 32 | H32: =Pakketten!$C$19 -> 32 | I32: =Pakketten!$C$19 -> 32 | J32: =Pakketten!$C$19 -> 32 | K32: =Pakketten!$C$19 -> 32 | ... O32: =Pakketten!$C$19 -> 32 | Q32: =Pakketten!$C$19 -> 32 | R32: =Pakketten!$C$19 -> 32 | S32: =Pakketten!$C$19 -> 32 | T32: =Pakketten!$C$19 -> 32 | U32: =Pakketten!$C$19 -> 32 | V32: =Pakketten!$C$19 -> 32 | W32: =Pakketten!$C$19 -> 32 | X32: =Pakketten!$C$19 -> 32 | ... AB32: =Pakketten!$C$19 -> 32 | AD32: =Pakketten!$C$19 -> 32 | AE32: =Pakketten!$C$19 -> 32 | AF32: =Pakketten!$C$19 -> 32 | AG32: =Pakketten!$C$19 -> 32 | AH32: =Pakketten!$C$19 -> 32 | AI32: =Pakketten!$C$19 -> 32 | AJ32: =Pakketten!$C$19 -> 32 | AK32: =Pakketten!$C$19 -> 32 | ... AO32: =Pakketten!$C$19 -> 32
A33: =ROW() -> 33 | B33: Norm uren klanten Growth | D33: =Pakketten!$K$19 -> 132 | E33: =Pakketten!$K$19 -> 132 | F33: =Pakketten!$K$19 -> 132 | G33: =Pakketten!$K$19 -> 132 | H33: =Pakketten!$K$19 -> 132 | I33: =Pakketten!$K$19 -> 132 | J33: =Pakketten!$K$19 -> 132 | K33: =Pakketten!$K$19 -> 132 | ... O33: =Pakketten!$K$19 -> 132 | Q33: =Pakketten!$K$19 -> 132 | R33: =Pakketten!$K$19 -> 132 | S33: =Pakketten!$K$19 -> 132 | T33: =Pakketten!$K$19 -> 132 | U33: =Pakketten!$K$19 -> 132 | V33: =Pakketten!$K$19 -> 132 | W33: =Pakketten!$K$19 -> 132 | X33: =Pakketten!$K$19 -> 132 | ... AB33: =Pakketten!$K$19 -> 132 | AD33: =Pakketten!$K$19 -> 132 | AE33: =Pakketten!$K$19 -> 132 | AF33: =Pakketten!$K$19 -> 132 | AG33: =Pakketten!$K$19 -> 132 | AH33: =Pakketten!$K$19 -> 132 | AI33: =Pakketten!$K$19 -> 132 | AJ33: =Pakketten!$K$19 -> 132 | AK33: =Pakketten!$K$19 -> 132 | ... AO33: =Pakketten!$K$19 -> 132
A34: =ROW() -> 34 | B34: Norm uren klanten Scale | D34: =Pakketten!$S$19 -> 208 | E34: =Pakketten!$S$19 -> 208 | F34: =Pakketten!$S$19 -> 208 | G34: =Pakketten!$S$19 -> 208 | H34: =Pakketten!$S$19 -> 208 | I34: =Pakketten!$S$19 -> 208 | J34: =Pakketten!$S$19 -> 208 | K34: =Pakketten!$S$19 -> 208 | ... O34: =Pakketten!$S$19 -> 208 | Q34: =Pakketten!$S$19 -> 208 | R34: =Pakketten!$S$19 -> 208 | S34: =Pakketten!$S$19 -> 208 | T34: =Pakketten!$S$19 -> 208 | U34: =Pakketten!$S$19 -> 208 | V34: =Pakketten!$S$19 -> 208 | W34: =Pakketten!$S$19 -> 208 | X34: =Pakketten!$S$19 -> 208 | ... AB34: =Pakketten!$S$19 -> 208 | AD34: =Pakketten!$S$19 -> 208 | AE34: =Pakketten!$S$19 -> 208 | AF34: =Pakketten!$S$19 -> 208 | AG34: =Pakketten!$S$19 -> 208 | AH34: =Pakketten!$S$19 -> 208 | AI34: =Pakketten!$S$19 -> 208 | AJ34: =Pakketten!$S$19 -> 208 | AK34: =Pakketten!$S$19 -> 208 | ... AO34: =Pakketten!$S$19 -> 208
A35: =ROW() -> 35
B36: Tarieven
A37: =ROW() -> 37 | B37: C-level tarief | D37: =Pakketten!D10 -> 91 | E37: =D37 -> 91 | F37: =E37 -> 91 | G37: =F37 -> 91 | H37: =G37 -> 91 | I37: =H37 -> 91 | J37: =I37 -> 91 | K37: =J37 -> 91 | L37: =K37 -> 91 | ... O37: =N37 -> 91 | Q37: =O37*1.03 -> 93.73 | R37: =Q37 -> 93.73 | S37: =R37 -> 93.73 | T37: =S37 -> 93.73 | U37: =T37 -> 93.73 | V37: =U37 -> 93.73 | W37: =V37 -> 93.73 | X37: =W37 -> 93.73 | Y37: =X37 -> 93.73 | ... AB37: =AA37 -> 93.73 | AD37: =AB37*1.03 -> 96.5419 | AE37: =AD37 -> 96.5419 | AF37: =AE37 -> 96.5419 | AG37: =AF37 -> 96.5419 | AH37: =AG37 -> 96.5419 | AI37: =AH37 -> 96.5419 | AJ37: =AI37 -> 96.5419 | AK37: =AJ37 -> 96.5419 | AL37: =AK37 -> 96.5419 | ... AO37: =AN37 -> 96.5419
A38: =ROW() -> 38 | B38: Senior tarief | D38: =Pakketten!D12 -> 95.157 | E38: =D38 -> 95.157 | F38: =E38 -> 95.157 | G38: =F38 -> 95.157 | H38: =G38 -> 95.157 | I38: =H38 -> 95.157 | J38: =I38 -> 95.157 | K38: =J38 -> 95.157 | L38: =K38 -> 95.157 | ... O38: =N38 -> 95.157 | Q38: =O38*1.03 -> 98.01171 | R38: =Q38 -> 98.01171 | S38: =R38 -> 98.01171 | T38: =S38 -> 98.01171 | U38: =T38 -> 98.01171 | V38: =U38 -> 98.01171 | W38: =V38 -> 98.01171 | X38: =W38 -> 98.01171 | Y38: =X38 -> 98.01171 | ... AB38: =AA38 -> 98.01171 | AD38: =AB38*1.03 -> 100.95206 | AE38: =AD38 -> 100.95206 | AF38: =AE38 -> 100.95206 | AG38: =AF38 -> 100.95206 | AH38: =AG38 -> 100.95206 | AI38: =AH38 -> 100.95206 | AJ38: =AI38 -> 100.95206 | AK38: =AJ38 -> 100.95206 | AL38: =AK38 -> 100.95206 | ... AO38: =AN38 -> 100.95206
A39: =ROW() -> 39 | B39: - HR partner (Senior-level) tarief | D39: =Pakketten!D14 -> 62.42625 | E39: =D39 -> 62.42625 | F39: =E39 -> 62.42625 | G39: =F39 -> 62.42625 | H39: =G39 -> 62.42625 | I39: =H39 -> 62.42625 | J39: =I39 -> 62.42625 | K39: =J39 -> 62.42625 | L39: =K39 -> 62.42625 | ... O39: =N39 -> 62.42625 | Q39: =O39*1.03 -> 64.299037 | R39: =Q39 -> 64.299037 | S39: =R39 -> 64.299037 | T39: =S39 -> 64.299037 | U39: =T39 -> 64.299037 | V39: =U39 -> 64.299037 | W39: =V39 -> 64.299037 | X39: =W39 -> 64.299037 | Y39: =X39 -> 64.299037 | ... AB39: =AA39 -> 64.299037 | AD39: =AB39*1.03 -> 66.228009 | AE39: =AD39 -> 66.228009 | AF39: =AE39 -> 66.228009 | AG39: =AF39 -> 66.228009 | AH39: =AG39 -> 66.228009 | AI39: =AH39 -> 66.228009 | AJ39: =AI39 -> 66.228009 | AK39: =AJ39 -> 66.228009 | AL39: =AK39 -> 66.228009 | ... AO39: =AN39 -> 66.228009
A40: =ROW() -> 40 | B40: - Finance admin (Senior-level) tarief | D40: =Pakketten!D15 -> 77.666625 | E40: =D40 -> 77.666625 | F40: =E40 -> 77.666625 | G40: =F40 -> 77.666625 | H40: =G40 -> 77.666625 | I40: =H40 -> 77.666625 | J40: =I40 -> 77.666625 | K40: =J40 -> 77.666625 | L40: =K40 -> 77.666625 | ... O40: =N40 -> 77.666625 | Q40: =O40*1.03 -> 79.996624 | R40: =Q40 -> 79.996624 | S40: =R40 -> 79.996624 | T40: =S40 -> 79.996624 | U40: =T40 -> 79.996624 | V40: =U40 -> 79.996624 | W40: =V40 -> 79.996624 | X40: =W40 -> 79.996624 | Y40: =X40 -> 79.996624 | ... AB40: =AA40 -> 79.996624 | AD40: =AB40*1.03 -> 82.396522 | AE40: =AD40 -> 82.396522 | AF40: =AE40 -> 82.396522 | AG40: =AF40 -> 82.396522 | AH40: =AG40 -> 82.396522 | AI40: =AH40 -> 82.396522 | AJ40: =AI40 -> 82.396522 | AK40: =AJ40 -> 82.396522 | AL40: =AK40 -> 82.396522 | ... AO40: =AN40 -> 82.396522
A41: =ROW() -> 41 | B41: - HR admin (Medior-level) tarief | D41: =Pakketten!D16 -> 50.391 | E41: =D41 -> 50.391 | F41: =E41 -> 50.391 | G41: =F41 -> 50.391 | H41: =G41 -> 50.391 | I41: =H41 -> 50.391 | J41: =I41 -> 50.391 | K41: =J41 -> 50.391 | L41: =K41 -> 50.391 | ... O41: =N41 -> 50.391 | Q41: =O41*1.03 -> 51.90273 | R41: =Q41 -> 51.90273 | S41: =R41 -> 51.90273 | T41: =S41 -> 51.90273 | U41: =T41 -> 51.90273 | V41: =U41 -> 51.90273 | W41: =V41 -> 51.90273 | X41: =W41 -> 51.90273 | Y41: =X41 -> 51.90273 | ... AB41: =AA41 -> 51.90273 | AD41: =AB41*1.03 -> 53.459812 | AE41: =AD41 -> 53.459812 | AF41: =AE41 -> 53.459812 | AG41: =AF41 -> 53.459812 | AH41: =AG41 -> 53.459812 | AI41: =AH41 -> 53.459812 | AJ41: =AI41 -> 53.459812 | AK41: =AJ41 -> 53.459812 | AL41: =AK41 -> 53.459812 | ... AO41: =AN41 -> 53.459812
A42: =ROW() -> 42 | B42: - Backoffice support (Junior-level) tarief | D42: =Pakketten!D17 -> 34.60575 | E42: =D42 -> 34.60575 | F42: =E42 -> 34.60575 | G42: =F42 -> 34.60575 | H42: =G42 -> 34.60575 | I42: =H42 -> 34.60575 | J42: =I42 -> 34.60575 | K42: =J42 -> 34.60575 | L42: =K42 -> 34.60575 | ... O42: =N42 -> 34.60575 | Q42: =O42*1.03 -> 35.643923 | R42: =Q42 -> 35.643923 | S42: =R42 -> 35.643923 | T42: =S42 -> 35.643923 | U42: =T42 -> 35.643923 | V42: =U42 -> 35.643923 | W42: =V42 -> 35.643923 | X42: =W42 -> 35.643923 | Y42: =X42 -> 35.643923 | ... AB42: =AA42 -> 35.643923 | AD42: =AB42*1.03 -> 36.71324 | AE42: =AD42 -> 36.71324 | AF42: =AE42 -> 36.71324 | AG42: =AF42 -> 36.71324 | AH42: =AG42 -> 36.71324 | AI42: =AH42 -> 36.71324 | AJ42: =AI42 -> 36.71324 | AK42: =AJ42 -> 36.71324 | AL42: =AK42 -> 36.71324 | ... AO42: =AN42 -> 36.71324
A43: =ROW() -> 43 | B43: - Data engineer (Medior-level) tarief | D43: =Pakketten!D18 -> 50.971125 | E43: =D43 -> 50.971125 | F43: =E43 -> 50.971125 | G43: =F43 -> 50.971125 | H43: =G43 -> 50.971125 | I43: =H43 -> 50.971125 | J43: =I43 -> 50.971125 | K43: =J43 -> 50.971125 | L43: =K43 -> 50.971125 | ... O43: =N43 -> 50.971125 | Q43: =O43*1.03 -> 52.500259 | R43: =Q43 -> 52.500259 | S43: =R43 -> 52.500259 | T43: =S43 -> 52.500259 | U43: =T43 -> 52.500259 | V43: =U43 -> 52.500259 | W43: =V43 -> 52.500259 | X43: =W43 -> 52.500259 | Y43: =X43 -> 52.500259 | ... AB43: =AA43 -> 52.500259 | AD43: =AB43*1.03 -> 54.075267 | AE43: =AD43 -> 54.075267 | AF43: =AE43 -> 54.075267 | AG43: =AF43 -> 54.075267 | AH43: =AG43 -> 54.075267 | AI43: =AH43 -> 54.075267 | AJ43: =AI43 -> 54.075267 | AK43: =AJ43 -> 54.075267 | AL43: =AK43 -> 54.075267 | ... AO43: =AN43 -> 54.075267
A44: =ROW() -> 44
A45: =ROW() -> 45 | B45: Klanturen
A46: =ROW() -> 46 | B46: - CEO (C-level) | D46: =D$7*Pakketten!$C10+D$8*Pakketten!$K10+RFF!D$9*Pakketten!$S10 -> 0 | E46: =E$7*Pakketten!$C10+E$8*Pakketten!$K10+RFF!E$9*Pakketten!$S10 -> 0 | F46: =F$7*Pakketten!$C10+F$8*Pakketten!$K10+RFF!F$9*Pakketten!$S10 -> 0 | G46: =G$7*Pakketten!$C10+G$8*Pakketten!$K10+RFF!G$9*Pakketten!$S10 -> 4 | H46: =H$7*Pakketten!$C10+H$8*Pakketten!$K10+RFF!H$9*Pakketten!$S10 -> 4 | I46: =I$7*Pakketten!$C10+I$8*Pakketten!$K10+RFF!I$9*Pakketten!$S10 -> 4 | J46: =J$7*Pakketten!$C10+J$8*Pakketten!$K10+RFF!J$9*Pakketten!$S10 -> 16 | K46: =K$7*Pakketten!$C10+K$8*Pakketten!$K10+RFF!K$9*Pakketten!$S10 -> 16 | ... O46: =O$7*Pakketten!$C10+O$8*Pakketten!$K10+RFF!O$9*Pakketten!$S10 -> 28 | P46: =SUM(D46:O46) -> 144 | Q46: =Q$7*Pakketten!$C10+Q$8*Pakketten!$K10+RFF!Q$9*Pakketten!$S10 -> 44 | R46: =R$7*Pakketten!$C10+R$8*Pakketten!$K10+RFF!R$9*Pakketten!$S10 -> 44 | S46: =S$7*Pakketten!$C10+S$8*Pakketten!$K10+RFF!S$9*Pakketten!$S10 -> 48 | T46: =T$7*Pakketten!$C10+T$8*Pakketten!$K10+RFF!T$9*Pakketten!$S10 -> 56 | U46: =U$7*Pakketten!$C10+U$8*Pakketten!$K10+RFF!U$9*Pakketten!$S10 -> 60 | V46: =V$7*Pakketten!$C10+V$8*Pakketten!$K10+RFF!V$9*Pakketten!$S10 -> 68 | W46: =W$7*Pakketten!$C10+W$8*Pakketten!$K10+RFF!W$9*Pakketten!$S10 -> 68 | X46: =X$7*Pakketten!$C10+X$8*Pakketten!$K10+RFF!X$9*Pakketten!$S10 -> 68 | ... AB46: =AB$7*Pakketten!$C10+AB$8*Pakketten!$K10+RFF!AB$9*Pakketten!$S10 -> 80 | AC46: =SUM(Q46:AB46) -> 768 | AD46: =AD$7*Pakketten!$C10+AD$8*Pakketten!$K10+RFF!AD$9*Pakketten!$S10 -> 112 | AE46: =AE$7*Pakketten!$C10+AE$8*Pakketten!$K10+RFF!AE$9*Pakketten!$S10 -> 112 | AF46: =AF$7*Pakketten!$C10+AF$8*Pakketten!$K10+RFF!AF$9*Pakketten!$S10 -> 116 | AG46: =AG$7*Pakketten!$C10+AG$8*Pakketten!$K10+RFF!AG$9*Pakketten!$S10 -> 124 | AH46: =AH$7*Pakketten!$C10+AH$8*Pakketten!$K10+RFF!AH$9*Pakketten!$S10 -> 128 | AI46: =AI$7*Pakketten!$C10+AI$8*Pakketten!$K10+RFF!AI$9*Pakketten!$S10 -> 136 | AJ46: =AJ$7*Pakketten!$C10+AJ$8*Pakketten!$K10+RFF!AJ$9*Pakketten!$S10 -> 136 | AK46: =AK$7*Pakketten!$C10+AK$8*Pakketten!$K10+RFF!AK$9*Pakketten!$S10 -> 136 | ... AO46: =AO$7*Pakketten!$C10+AO$8*Pakketten!$K10+RFF!AO$9*Pakketten!$S10 -> 148 | AP46: =SUM(AD46:AO46) -> 1584
A47: =ROW() -> 47 | B47: - CFO (C-level) | D47: =D$7*Pakketten!$C11+D$8*Pakketten!$K11+RFF!D$9*Pakketten!$S11 -> 0 | E47: =E$7*Pakketten!$C11+E$8*Pakketten!$K11+RFF!E$9*Pakketten!$S11 -> 0 | F47: =F$7*Pakketten!$C11+F$8*Pakketten!$K11+RFF!F$9*Pakketten!$S11 -> 0 | G47: =G$7*Pakketten!$C11+G$8*Pakketten!$K11+RFF!G$9*Pakketten!$S11 -> 8 | H47: =H$7*Pakketten!$C11+H$8*Pakketten!$K11+RFF!H$9*Pakketten!$S11 -> 8 | I47: =I$7*Pakketten!$C11+I$8*Pakketten!$K11+RFF!I$9*Pakketten!$S11 -> 8 | J47: =J$7*Pakketten!$C11+J$8*Pakketten!$K11+RFF!J$9*Pakketten!$S11 -> 32 | K47: =K$7*Pakketten!$C11+K$8*Pakketten!$K11+RFF!K$9*Pakketten!$S11 -> 32 | ... O47: =O$7*Pakketten!$C11+O$8*Pakketten!$K11+RFF!O$9*Pakketten!$S11 -> 56 | P47: =SUM(D47:O47) -> 288 | Q47: =Q$7*Pakketten!$C11+Q$8*Pakketten!$K11+RFF!Q$9*Pakketten!$S11 -> 88 | R47: =R$7*Pakketten!$C11+R$8*Pakketten!$K11+RFF!R$9*Pakketten!$S11 -> 88 | S47: =S$7*Pakketten!$C11+S$8*Pakketten!$K11+RFF!S$9*Pakketten!$S11 -> 96 | T47: =T$7*Pakketten!$C11+T$8*Pakketten!$K11+RFF!T$9*Pakketten!$S11 -> 112 | U47: =U$7*Pakketten!$C11+U$8*Pakketten!$K11+RFF!U$9*Pakketten!$S11 -> 120 | V47: =V$7*Pakketten!$C11+V$8*Pakketten!$K11+RFF!V$9*Pakketten!$S11 -> 136 | W47: =W$7*Pakketten!$C11+W$8*Pakketten!$K11+RFF!W$9*Pakketten!$S11 -> 136 | X47: =X$7*Pakketten!$C11+X$8*Pakketten!$K11+RFF!X$9*Pakketten!$S11 -> 136 | ... AB47: =AB$7*Pakketten!$C11+AB$8*Pakketten!$K11+RFF!AB$9*Pakketten!$S11 -> 160 | AC47: =SUM(Q47:AB47) -> 1536 | AD47: =AD$7*Pakketten!$C11+AD$8*Pakketten!$K11+RFF!AD$9*Pakketten!$S11 -> 224 | AE47: =AE$7*Pakketten!$C11+AE$8*Pakketten!$K11+RFF!AE$9*Pakketten!$S11 -> 224 | AF47: =AF$7*Pakketten!$C11+AF$8*Pakketten!$K11+RFF!AF$9*Pakketten!$S11 -> 232 | AG47: =AG$7*Pakketten!$C11+AG$8*Pakketten!$K11+RFF!AG$9*Pakketten!$S11 -> 248 | AH47: =AH$7*Pakketten!$C11+AH$8*Pakketten!$K11+RFF!AH$9*Pakketten!$S11 -> 256 | AI47: =AI$7*Pakketten!$C11+AI$8*Pakketten!$K11+RFF!AI$9*Pakketten!$S11 -> 272 | AJ47: =AJ$7*Pakketten!$C11+AJ$8*Pakketten!$K11+RFF!AJ$9*Pakketten!$S11 -> 272 | AK47: =AK$7*Pakketten!$C11+AK$8*Pakketten!$K11+RFF!AK$9*Pakketten!$S11 -> 272 | ... AO47: =AO$7*Pakketten!$C11+AO$8*Pakketten!$K11+RFF!AO$9*Pakketten!$S11 -> 296 | AP47: =SUM(AD47:AO47) -> 3168
A48: =ROW() -> 48 | B48: - CMO (Senior-level) | D48: =D$7*Pakketten!$C12+D$8*Pakketten!$K12+RFF!D$9*Pakketten!$S12 -> 0 | E48: =E$7*Pakketten!$C12+E$8*Pakketten!$K12+RFF!E$9*Pakketten!$S12 -> 0 | F48: =F$7*Pakketten!$C12+F$8*Pakketten!$K12+RFF!F$9*Pakketten!$S12 -> 0 | G48: =G$7*Pakketten!$C12+G$8*Pakketten!$K12+RFF!G$9*Pakketten!$S12 -> 6 | H48: =H$7*Pakketten!$C12+H$8*Pakketten!$K12+RFF!H$9*Pakketten!$S12 -> 6 | I48: =I$7*Pakketten!$C12+I$8*Pakketten!$K12+RFF!I$9*Pakketten!$S12 -> 6 | J48: =J$7*Pakketten!$C12+J$8*Pakketten!$K12+RFF!J$9*Pakketten!$S12 -> 36 | K48: =K$7*Pakketten!$C12+K$8*Pakketten!$K12+RFF!K$9*Pakketten!$S12 -> 36 | ... O48: =O$7*Pakketten!$C12+O$8*Pakketten!$K12+RFF!O$9*Pakketten!$S12 -> 60 | P48: =SUM(D48:O48) -> 306 | Q48: =Q$7*Pakketten!$C12+Q$8*Pakketten!$K12+RFF!Q$9*Pakketten!$S12 -> 90 | R48: =R$7*Pakketten!$C12+R$8*Pakketten!$K12+RFF!R$9*Pakketten!$S12 -> 90 | S48: =S$7*Pakketten!$C12+S$8*Pakketten!$K12+RFF!S$9*Pakketten!$S12 -> 96 | T48: =T$7*Pakketten!$C12+T$8*Pakketten!$K12+RFF!T$9*Pakketten!$S12 -> 120 | U48: =U$7*Pakketten!$C12+U$8*Pakketten!$K12+RFF!U$9*Pakketten!$S12 -> 126 | V48: =V$7*Pakketten!$C12+V$8*Pakketten!$K12+RFF!V$9*Pakketten!$S12 -> 144 | W48: =W$7*Pakketten!$C12+W$8*Pakketten!$K12+RFF!W$9*Pakketten!$S12 -> 144 | X48: =X$7*Pakketten!$C12+X$8*Pakketten!$K12+RFF!X$9*Pakketten!$S12 -> 144 | ... AB48: =AB$7*Pakketten!$C12+AB$8*Pakketten!$K12+RFF!AB$9*Pakketten!$S12 -> 168 | AC48: =SUM(Q48:AB48) -> 1608 | AD48: =AD$7*Pakketten!$C12+AD$8*Pakketten!$K12+RFF!AD$9*Pakketten!$S12 -> 240 | AE48: =AE$7*Pakketten!$C12+AE$8*Pakketten!$K12+RFF!AE$9*Pakketten!$S12 -> 240 | AF48: =AF$7*Pakketten!$C12+AF$8*Pakketten!$K12+RFF!AF$9*Pakketten!$S12 -> 246 | AG48: =AG$7*Pakketten!$C12+AG$8*Pakketten!$K12+RFF!AG$9*Pakketten!$S12 -> 270 | AH48: =AH$7*Pakketten!$C12+AH$8*Pakketten!$K12+RFF!AH$9*Pakketten!$S12 -> 276 | AI48: =AI$7*Pakketten!$C12+AI$8*Pakketten!$K12+RFF!AI$9*Pakketten!$S12 -> 294 | AJ48: =AJ$7*Pakketten!$C12+AJ$8*Pakketten!$K12+RFF!AJ$9*Pakketten!$S12 -> 294 | AK48: =AK$7*Pakketten!$C12+AK$8*Pakketten!$K12+RFF!AK$9*Pakketten!$S12 -> 294 | ... AO48: =AO$7*Pakketten!$C12+AO$8*Pakketten!$K12+RFF!AO$9*Pakketten!$S12 -> 318 | AP48: =SUM(AD48:AO48) -> 3408
A49: =ROW() -> 49 | B49: - CTO (Senior-level) | D49: =D$7*Pakketten!$C13+D$8*Pakketten!$K13+RFF!D$9*Pakketten!$S13 -> 0 | E49: =E$7*Pakketten!$C13+E$8*Pakketten!$K13+RFF!E$9*Pakketten!$S13 -> 0 | F49: =F$7*Pakketten!$C13+F$8*Pakketten!$K13+RFF!F$9*Pakketten!$S13 -> 0 | G49: =G$7*Pakketten!$C13+G$8*Pakketten!$K13+RFF!G$9*Pakketten!$S13 -> 6 | H49: =H$7*Pakketten!$C13+H$8*Pakketten!$K13+RFF!H$9*Pakketten!$S13 -> 6 | I49: =I$7*Pakketten!$C13+I$8*Pakketten!$K13+RFF!I$9*Pakketten!$S13 -> 6 | J49: =J$7*Pakketten!$C13+J$8*Pakketten!$K13+RFF!J$9*Pakketten!$S13 -> 36 | K49: =K$7*Pakketten!$C13+K$8*Pakketten!$K13+RFF!K$9*Pakketten!$S13 -> 36 | ... O49: =O$7*Pakketten!$C13+O$8*Pakketten!$K13+RFF!O$9*Pakketten!$S13 -> 60 | P49: =SUM(D49:O49) -> 306 | Q49: =Q$7*Pakketten!$C13+Q$8*Pakketten!$K13+RFF!Q$9*Pakketten!$S13 -> 90 | R49: =R$7*Pakketten!$C13+R$8*Pakketten!$K13+RFF!R$9*Pakketten!$S13 -> 90 | S49: =S$7*Pakketten!$C13+S$8*Pakketten!$K13+RFF!S$9*Pakketten!$S13 -> 96 | T49: =T$7*Pakketten!$C13+T$8*Pakketten!$K13+RFF!T$9*Pakketten!$S13 -> 120 | U49: =U$7*Pakketten!$C13+U$8*Pakketten!$K13+RFF!U$9*Pakketten!$S13 -> 126 | V49: =V$7*Pakketten!$C13+V$8*Pakketten!$K13+RFF!V$9*Pakketten!$S13 -> 144 | W49: =W$7*Pakketten!$C13+W$8*Pakketten!$K13+RFF!W$9*Pakketten!$S13 -> 144 | X49: =X$7*Pakketten!$C13+X$8*Pakketten!$K13+RFF!X$9*Pakketten!$S13 -> 144 | ... AB49: =AB$7*Pakketten!$C13+AB$8*Pakketten!$K13+RFF!AB$9*Pakketten!$S13 -> 168 | AC49: =SUM(Q49:AB49) -> 1608 | AD49: =AD$7*Pakketten!$C13+AD$8*Pakketten!$K13+RFF!AD$9*Pakketten!$S13 -> 240 | AE49: =AE$7*Pakketten!$C13+AE$8*Pakketten!$K13+RFF!AE$9*Pakketten!$S13 -> 240 | AF49: =AF$7*Pakketten!$C13+AF$8*Pakketten!$K13+RFF!AF$9*Pakketten!$S13 -> 246 | AG49: =AG$7*Pakketten!$C13+AG$8*Pakketten!$K13+RFF!AG$9*Pakketten!$S13 -> 270 | AH49: =AH$7*Pakketten!$C13+AH$8*Pakketten!$K13+RFF!AH$9*Pakketten!$S13 -> 276 | AI49: =AI$7*Pakketten!$C13+AI$8*Pakketten!$K13+RFF!AI$9*Pakketten!$S13 -> 294 | AJ49: =AJ$7*Pakketten!$C13+AJ$8*Pakketten!$K13+RFF!AJ$9*Pakketten!$S13 -> 294 | AK49: =AK$7*Pakketten!$C13+AK$8*Pakketten!$K13+RFF!AK$9*Pakketten!$S13 -> 294 | ... AO49: =AO$7*Pakketten!$C13+AO$8*Pakketten!$K13+RFF!AO$9*Pakketten!$S13 -> 318 | AP49: =SUM(AD49:AO49) -> 3408
A50: =ROW() -> 50 | B50: - HR partner (Senior-level) | D50: =D$7*Pakketten!$C14+D$8*Pakketten!$K14+RFF!D$9*Pakketten!$S14 -> 0 | E50: =E$7*Pakketten!$C14+E$8*Pakketten!$K14+RFF!E$9*Pakketten!$S14 -> 0 | F50: =F$7*Pakketten!$C14+F$8*Pakketten!$K14+RFF!F$9*Pakketten!$S14 -> 0 | G50: =G$7*Pakketten!$C14+G$8*Pakketten!$K14+RFF!G$9*Pakketten!$S14 -> 8 | H50: =H$7*Pakketten!$C14+H$8*Pakketten!$K14+RFF!H$9*Pakketten!$S14 -> 8 | I50: =I$7*Pakketten!$C14+I$8*Pakketten!$K14+RFF!I$9*Pakketten!$S14 -> 8 | J50: =J$7*Pakketten!$C14+J$8*Pakketten!$K14+RFF!J$9*Pakketten!$S14 -> 40 | K50: =K$7*Pakketten!$C14+K$8*Pakketten!$K14+RFF!K$9*Pakketten!$S14 -> 40 | ... O50: =O$7*Pakketten!$C14+O$8*Pakketten!$K14+RFF!O$9*Pakketten!$S14 -> 66 | P50: =SUM(D50:O50) -> 342 | Q50: =Q$7*Pakketten!$C14+Q$8*Pakketten!$K14+RFF!Q$9*Pakketten!$S14 -> 100 | R50: =R$7*Pakketten!$C14+R$8*Pakketten!$K14+RFF!R$9*Pakketten!$S14 -> 100 | S50: =S$7*Pakketten!$C14+S$8*Pakketten!$K14+RFF!S$9*Pakketten!$S14 -> 108 | T50: =T$7*Pakketten!$C14+T$8*Pakketten!$K14+RFF!T$9*Pakketten!$S14 -> 132 | U50: =U$7*Pakketten!$C14+U$8*Pakketten!$K14+RFF!U$9*Pakketten!$S14 -> 140 | V50: =V$7*Pakketten!$C14+V$8*Pakketten!$K14+RFF!V$9*Pakketten!$S14 -> 158 | W50: =W$7*Pakketten!$C14+W$8*Pakketten!$K14+RFF!W$9*Pakketten!$S14 -> 158 | X50: =X$7*Pakketten!$C14+X$8*Pakketten!$K14+RFF!X$9*Pakketten!$S14 -> 158 | ... AB50: =AB$7*Pakketten!$C14+AB$8*Pakketten!$K14+RFF!AB$9*Pakketten!$S14 -> 184 | AC50: =SUM(Q50:AB50) -> 1772 | AD50: =AD$7*Pakketten!$C14+AD$8*Pakketten!$K14+RFF!AD$9*Pakketten!$S14 -> 260 | AE50: =AE$7*Pakketten!$C14+AE$8*Pakketten!$K14+RFF!AE$9*Pakketten!$S14 -> 260 | AF50: =AF$7*Pakketten!$C14+AF$8*Pakketten!$K14+RFF!AF$9*Pakketten!$S14 -> 268 | AG50: =AG$7*Pakketten!$C14+AG$8*Pakketten!$K14+RFF!AG$9*Pakketten!$S14 -> 292 | AH50: =AH$7*Pakketten!$C14+AH$8*Pakketten!$K14+RFF!AH$9*Pakketten!$S14 -> 300 | AI50: =AI$7*Pakketten!$C14+AI$8*Pakketten!$K14+RFF!AI$9*Pakketten!$S14 -> 318 | AJ50: =AJ$7*Pakketten!$C14+AJ$8*Pakketten!$K14+RFF!AJ$9*Pakketten!$S14 -> 318 | AK50: =AK$7*Pakketten!$C14+AK$8*Pakketten!$K14+RFF!AK$9*Pakketten!$S14 -> 318 | ... AO50: =AO$7*Pakketten!$C14+AO$8*Pakketten!$K14+RFF!AO$9*Pakketten!$S14 -> 344 | AP50: =SUM(AD50:AO50) -> 3692
A51: =ROW() -> 51 | B51: - Finance admin (Senior-level) | D51: =D$7*Pakketten!$C15+D$8*Pakketten!$K15+RFF!D$9*Pakketten!$S15 -> 0 | E51: =E$7*Pakketten!$C15+E$8*Pakketten!$K15+RFF!E$9*Pakketten!$S15 -> 0 | F51: =F$7*Pakketten!$C15+F$8*Pakketten!$K15+RFF!F$9*Pakketten!$S15 -> 0 | G51: =G$7*Pakketten!$C15+G$8*Pakketten!$K15+RFF!G$9*Pakketten!$S15 -> 12 | H51: =H$7*Pakketten!$C15+H$8*Pakketten!$K15+RFF!H$9*Pakketten!$S15 -> 12 | I51: =I$7*Pakketten!$C15+I$8*Pakketten!$K15+RFF!I$9*Pakketten!$S15 -> 12 | J51: =J$7*Pakketten!$C15+J$8*Pakketten!$K15+RFF!J$9*Pakketten!$S15 -> 42 | K51: =K$7*Pakketten!$C15+K$8*Pakketten!$K15+RFF!K$9*Pakketten!$S15 -> 42 | ... O51: =O$7*Pakketten!$C15+O$8*Pakketten!$K15+RFF!O$9*Pakketten!$S15 -> 66 | P51: =SUM(D51:O51) -> 360 | Q51: =Q$7*Pakketten!$C15+Q$8*Pakketten!$K15+RFF!Q$9*Pakketten!$S15 -> 102 | R51: =R$7*Pakketten!$C15+R$8*Pakketten!$K15+RFF!R$9*Pakketten!$S15 -> 102 | S51: =S$7*Pakketten!$C15+S$8*Pakketten!$K15+RFF!S$9*Pakketten!$S15 -> 114 | T51: =T$7*Pakketten!$C15+T$8*Pakketten!$K15+RFF!T$9*Pakketten!$S15 -> 132 | U51: =U$7*Pakketten!$C15+U$8*Pakketten!$K15+RFF!U$9*Pakketten!$S15 -> 144 | V51: =V$7*Pakketten!$C15+V$8*Pakketten!$K15+RFF!V$9*Pakketten!$S15 -> 156 | W51: =W$7*Pakketten!$C15+W$8*Pakketten!$K15+RFF!W$9*Pakketten!$S15 -> 156 | X51: =X$7*Pakketten!$C15+X$8*Pakketten!$K15+RFF!X$9*Pakketten!$S15 -> 156 | ... AB51: =AB$7*Pakketten!$C15+AB$8*Pakketten!$K15+RFF!AB$9*Pakketten!$S15 -> 180 | AC51: =SUM(Q51:AB51) -> 1770 | AD51: =AD$7*Pakketten!$C15+AD$8*Pakketten!$K15+RFF!AD$9*Pakketten!$S15 -> 246 | AE51: =AE$7*Pakketten!$C15+AE$8*Pakketten!$K15+RFF!AE$9*Pakketten!$S15 -> 246 | AF51: =AF$7*Pakketten!$C15+AF$8*Pakketten!$K15+RFF!AF$9*Pakketten!$S15 -> 258 | AG51: =AG$7*Pakketten!$C15+AG$8*Pakketten!$K15+RFF!AG$9*Pakketten!$S15 -> 276 | AH51: =AH$7*Pakketten!$C15+AH$8*Pakketten!$K15+RFF!AH$9*Pakketten!$S15 -> 288 | AI51: =AI$7*Pakketten!$C15+AI$8*Pakketten!$K15+RFF!AI$9*Pakketten!$S15 -> 300 | AJ51: =AJ$7*Pakketten!$C15+AJ$8*Pakketten!$K15+RFF!AJ$9*Pakketten!$S15 -> 300 | AK51: =AK$7*Pakketten!$C15+AK$8*Pakketten!$K15+RFF!AK$9*Pakketten!$S15 -> 300 | ... AO51: =AO$7*Pakketten!$C15+AO$8*Pakketten!$K15+RFF!AO$9*Pakketten!$S15 -> 324 | AP51: =SUM(AD51:AO51) -> 3498
A52: =ROW() -> 52 | B52: - HR admin (Medior-level) | D52: =D$7*Pakketten!$C16+D$8*Pakketten!$K16+RFF!D$9*Pakketten!$S16 -> 0 | E52: =E$7*Pakketten!$C16+E$8*Pakketten!$K16+RFF!E$9*Pakketten!$S16 -> 0 | F52: =F$7*Pakketten!$C16+F$8*Pakketten!$K16+RFF!F$9*Pakketten!$S16 -> 0 | G52: =G$7*Pakketten!$C16+G$8*Pakketten!$K16+RFF!G$9*Pakketten!$S16 -> 0 | H52: =H$7*Pakketten!$C16+H$8*Pakketten!$K16+RFF!H$9*Pakketten!$S16 -> 0 | I52: =I$7*Pakketten!$C16+I$8*Pakketten!$K16+RFF!I$9*Pakketten!$S16 -> 0 | J52: =J$7*Pakketten!$C16+J$8*Pakketten!$K16+RFF!J$9*Pakketten!$S16 -> 8 | K52: =K$7*Pakketten!$C16+K$8*Pakketten!$K16+RFF!K$9*Pakketten!$S16 -> 8 | ... O52: =O$7*Pakketten!$C16+O$8*Pakketten!$K16+RFF!O$9*Pakketten!$S16 -> 16 | P52: =SUM(D52:O52) -> 72 | Q52: =Q$7*Pakketten!$C16+Q$8*Pakketten!$K16+RFF!Q$9*Pakketten!$S16 -> 24 | R52: =R$7*Pakketten!$C16+R$8*Pakketten!$K16+RFF!R$9*Pakketten!$S16 -> 24 | S52: =S$7*Pakketten!$C16+S$8*Pakketten!$K16+RFF!S$9*Pakketten!$S16 -> 24 | T52: =T$7*Pakketten!$C16+T$8*Pakketten!$K16+RFF!T$9*Pakketten!$S16 -> 32 | U52: =U$7*Pakketten!$C16+U$8*Pakketten!$K16+RFF!U$9*Pakketten!$S16 -> 32 | V52: =V$7*Pakketten!$C16+V$8*Pakketten!$K16+RFF!V$9*Pakketten!$S16 -> 40 | W52: =W$7*Pakketten!$C16+W$8*Pakketten!$K16+RFF!W$9*Pakketten!$S16 -> 40 | X52: =X$7*Pakketten!$C16+X$8*Pakketten!$K16+RFF!X$9*Pakketten!$S16 -> 40 | ... AB52: =AB$7*Pakketten!$C16+AB$8*Pakketten!$K16+RFF!AB$9*Pakketten!$S16 -> 48 | AC52: =SUM(Q52:AB52) -> 440 | AD52: =AD$7*Pakketten!$C16+AD$8*Pakketten!$K16+RFF!AD$9*Pakketten!$S16 -> 72 | AE52: =AE$7*Pakketten!$C16+AE$8*Pakketten!$K16+RFF!AE$9*Pakketten!$S16 -> 72 | AF52: =AF$7*Pakketten!$C16+AF$8*Pakketten!$K16+RFF!AF$9*Pakketten!$S16 -> 72 | AG52: =AG$7*Pakketten!$C16+AG$8*Pakketten!$K16+RFF!AG$9*Pakketten!$S16 -> 80 | AH52: =AH$7*Pakketten!$C16+AH$8*Pakketten!$K16+RFF!AH$9*Pakketten!$S16 -> 80 | AI52: =AI$7*Pakketten!$C16+AI$8*Pakketten!$K16+RFF!AI$9*Pakketten!$S16 -> 88 | AJ52: =AJ$7*Pakketten!$C16+AJ$8*Pakketten!$K16+RFF!AJ$9*Pakketten!$S16 -> 88 | AK52: =AK$7*Pakketten!$C16+AK$8*Pakketten!$K16+RFF!AK$9*Pakketten!$S16 -> 88 | ... AO52: =AO$7*Pakketten!$C16+AO$8*Pakketten!$K16+RFF!AO$9*Pakketten!$S16 -> 96 | AP52: =SUM(AD52:AO52) -> 1016
A53: =ROW() -> 53 | B53: - Backoffice support (Junior-level) | D53: =D$7*Pakketten!$C17+D$8*Pakketten!$K17+RFF!D$9*Pakketten!$S17 -> 0 | E53: =E$7*Pakketten!$C17+E$8*Pakketten!$K17+RFF!E$9*Pakketten!$S17 -> 0 | F53: =F$7*Pakketten!$C17+F$8*Pakketten!$K17+RFF!F$9*Pakketten!$S17 -> 0 | G53: =G$7*Pakketten!$C17+G$8*Pakketten!$K17+RFF!G$9*Pakketten!$S17 -> 20 | H53: =H$7*Pakketten!$C17+H$8*Pakketten!$K17+RFF!H$9*Pakketten!$S17 -> 20 | I53: =I$7*Pakketten!$C17+I$8*Pakketten!$K17+RFF!I$9*Pakketten!$S17 -> 20 | J53: =J$7*Pakketten!$C17+J$8*Pakketten!$K17+RFF!J$9*Pakketten!$S17 -> 70 | K53: =K$7*Pakketten!$C17+K$8*Pakketten!$K17+RFF!K$9*Pakketten!$S17 -> 70 | ... O53: =O$7*Pakketten!$C17+O$8*Pakketten!$K17+RFF!O$9*Pakketten!$S17 -> 120 | P53: =SUM(D53:O53) -> 630 | Q53: =Q$7*Pakketten!$C17+Q$8*Pakketten!$K17+RFF!Q$9*Pakketten!$S17 -> 190 | R53: =R$7*Pakketten!$C17+R$8*Pakketten!$K17+RFF!R$9*Pakketten!$S17 -> 190 | S53: =S$7*Pakketten!$C17+S$8*Pakketten!$K17+RFF!S$9*Pakketten!$S17 -> 210 | T53: =T$7*Pakketten!$C17+T$8*Pakketten!$K17+RFF!T$9*Pakketten!$S17 -> 240 | U53: =U$7*Pakketten!$C17+U$8*Pakketten!$K17+RFF!U$9*Pakketten!$S17 -> 260 | V53: =V$7*Pakketten!$C17+V$8*Pakketten!$K17+RFF!V$9*Pakketten!$S17 -> 290 | W53: =W$7*Pakketten!$C17+W$8*Pakketten!$K17+RFF!W$9*Pakketten!$S17 -> 290 | X53: =X$7*Pakketten!$C17+X$8*Pakketten!$K17+RFF!X$9*Pakketten!$S17 -> 290 | ... AB53: =AB$7*Pakketten!$C17+AB$8*Pakketten!$K17+RFF!AB$9*Pakketten!$S17 -> 340 | AC53: =SUM(Q53:AB53) -> 3290 | AD53: =AD$7*Pakketten!$C17+AD$8*Pakketten!$K17+RFF!AD$9*Pakketten!$S17 -> 470 | AE53: =AE$7*Pakketten!$C17+AE$8*Pakketten!$K17+RFF!AE$9*Pakketten!$S17 -> 470 | AF53: =AF$7*Pakketten!$C17+AF$8*Pakketten!$K17+RFF!AF$9*Pakketten!$S17 -> 490 | AG53: =AG$7*Pakketten!$C17+AG$8*Pakketten!$K17+RFF!AG$9*Pakketten!$S17 -> 520 | AH53: =AH$7*Pakketten!$C17+AH$8*Pakketten!$K17+RFF!AH$9*Pakketten!$S17 -> 540 | AI53: =AI$7*Pakketten!$C17+AI$8*Pakketten!$K17+RFF!AI$9*Pakketten!$S17 -> 570 | AJ53: =AJ$7*Pakketten!$C17+AJ$8*Pakketten!$K17+RFF!AJ$9*Pakketten!$S17 -> 570 | AK53: =AK$7*Pakketten!$C17+AK$8*Pakketten!$K17+RFF!AK$9*Pakketten!$S17 -> 570 | ... AO53: =AO$7*Pakketten!$C17+AO$8*Pakketten!$K17+RFF!AO$9*Pakketten!$S17 -> 620 | AP53: =SUM(AD53:AO53) -> 6650
A54: =ROW() -> 54 | B54: - Data engineer (Medior-level) | D54: =D$7*Pakketten!$C18+D$8*Pakketten!$K18+RFF!D$9*Pakketten!$S18 -> 0 | E54: =E$7*Pakketten!$C18+E$8*Pakketten!$K18+RFF!E$9*Pakketten!$S18 -> 0 | F54: =F$7*Pakketten!$C18+F$8*Pakketten!$K18+RFF!F$9*Pakketten!$S18 -> 0 | G54: =G$7*Pakketten!$C18+G$8*Pakketten!$K18+RFF!G$9*Pakketten!$S18 -> 0 | H54: =H$7*Pakketten!$C18+H$8*Pakketten!$K18+RFF!H$9*Pakketten!$S18 -> 0 | I54: =I$7*Pakketten!$C18+I$8*Pakketten!$K18+RFF!I$9*Pakketten!$S18 -> 0 | J54: =J$7*Pakketten!$C18+J$8*Pakketten!$K18+RFF!J$9*Pakketten!$S18 -> 4 | K54: =K$7*Pakketten!$C18+K$8*Pakketten!$K18+RFF!K$9*Pakketten!$S18 -> 4 | ... O54: =O$7*Pakketten!$C18+O$8*Pakketten!$K18+RFF!O$9*Pakketten!$S18 -> 8 | P54: =SUM(D54:O54) -> 36 | Q54: =Q$7*Pakketten!$C18+Q$8*Pakketten!$K18+RFF!Q$9*Pakketten!$S18 -> 12 | R54: =R$7*Pakketten!$C18+R$8*Pakketten!$K18+RFF!R$9*Pakketten!$S18 -> 12 | S54: =S$7*Pakketten!$C18+S$8*Pakketten!$K18+RFF!S$9*Pakketten!$S18 -> 12 | T54: =T$7*Pakketten!$C18+T$8*Pakketten!$K18+RFF!T$9*Pakketten!$S18 -> 16 | U54: =U$7*Pakketten!$C18+U$8*Pakketten!$K18+RFF!U$9*Pakketten!$S18 -> 16 | V54: =V$7*Pakketten!$C18+V$8*Pakketten!$K18+RFF!V$9*Pakketten!$S18 -> 20 | W54: =W$7*Pakketten!$C18+W$8*Pakketten!$K18+RFF!W$9*Pakketten!$S18 -> 20 | X54: =X$7*Pakketten!$C18+X$8*Pakketten!$K18+RFF!X$9*Pakketten!$S18 -> 20 | ... AB54: =AB$7*Pakketten!$C18+AB$8*Pakketten!$K18+RFF!AB$9*Pakketten!$S18 -> 24 | AC54: =SUM(Q54:AB54) -> 220 | AD54: =AD$7*Pakketten!$C18+AD$8*Pakketten!$K18+RFF!AD$9*Pakketten!$S18 -> 36 | AE54: =AE$7*Pakketten!$C18+AE$8*Pakketten!$K18+RFF!AE$9*Pakketten!$S18 -> 36 | AF54: =AF$7*Pakketten!$C18+AF$8*Pakketten!$K18+RFF!AF$9*Pakketten!$S18 -> 36 | AG54: =AG$7*Pakketten!$C18+AG$8*Pakketten!$K18+RFF!AG$9*Pakketten!$S18 -> 40 | AH54: =AH$7*Pakketten!$C18+AH$8*Pakketten!$K18+RFF!AH$9*Pakketten!$S18 -> 40 | AI54: =AI$7*Pakketten!$C18+AI$8*Pakketten!$K18+RFF!AI$9*Pakketten!$S18 -> 44 | AJ54: =AJ$7*Pakketten!$C18+AJ$8*Pakketten!$K18+RFF!AJ$9*Pakketten!$S18 -> 44 | AK54: =AK$7*Pakketten!$C18+AK$8*Pakketten!$K18+RFF!AK$9*Pakketten!$S18 -> 44 | ... AO54: =AO$7*Pakketten!$C18+AO$8*Pakketten!$K18+RFF!AO$9*Pakketten!$S18 -> 48 | AP54: =SUM(AD54:AO54) -> 508
A55: =ROW() -> 55 | D55: =D$7*Pakketten!$C19+D$8*Pakketten!$K19+RFF!D$9*Pakketten!$S19 -> 0 | E55: =E$7*Pakketten!$C19+E$8*Pakketten!$K19+RFF!E$9*Pakketten!$S19 -> 0 | F55: =F$7*Pakketten!$C19+F$8*Pakketten!$K19+RFF!F$9*Pakketten!$S19 -> 0 | G55: =G$7*Pakketten!$C19+G$8*Pakketten!$K19+RFF!G$9*Pakketten!$S19 -> 32 | H55: =H$7*Pakketten!$C19+H$8*Pakketten!$K19+RFF!H$9*Pakketten!$S19 -> 32 | I55: =I$7*Pakketten!$C19+I$8*Pakketten!$K19+RFF!I$9*Pakketten!$S19 -> 32 | J55: =J$7*Pakketten!$C19+J$8*Pakketten!$K19+RFF!J$9*Pakketten!$S19 -> 196 | K55: =K$7*Pakketten!$C19+K$8*Pakketten!$K19+RFF!K$9*Pakketten!$S19 -> 196 | ... O55: =O$7*Pakketten!$C19+O$8*Pakketten!$K19+RFF!O$9*Pakketten!$S19 -> 332 | P55: =SUM(D55:O55) -> 1680 | Q55: =Q$7*Pakketten!$C19+Q$8*Pakketten!$K19+RFF!Q$9*Pakketten!$S19 -> 500 | R55: =R$7*Pakketten!$C19+R$8*Pakketten!$K19+RFF!R$9*Pakketten!$S19 -> 500 | S55: =S$7*Pakketten!$C19+S$8*Pakketten!$K19+RFF!S$9*Pakketten!$S19 -> 532 | T55: =T$7*Pakketten!$C19+T$8*Pakketten!$K19+RFF!T$9*Pakketten!$S19 -> 664 | U55: =U$7*Pakketten!$C19+U$8*Pakketten!$K19+RFF!U$9*Pakketten!$S19 -> 696 | V55: =V$7*Pakketten!$C19+V$8*Pakketten!$K19+RFF!V$9*Pakketten!$S19 -> 800 | W55: =W$7*Pakketten!$C19+W$8*Pakketten!$K19+RFF!W$9*Pakketten!$S19 -> 800 | X55: =X$7*Pakketten!$C19+X$8*Pakketten!$K19+RFF!X$9*Pakketten!$S19 -> 800 | ... AB55: =AB$7*Pakketten!$C19+AB$8*Pakketten!$K19+RFF!AB$9*Pakketten!$S19 -> 936 | AC55: =SUM(Q55:AB55) -> 8932 | AD55: =AD$7*Pakketten!$C19+AD$8*Pakketten!$K19+RFF!AD$9*Pakketten!$S19 -> 1340 | AE55: =AE$7*Pakketten!$C19+AE$8*Pakketten!$K19+RFF!AE$9*Pakketten!$S19 -> 1340 | AF55: =AF$7*Pakketten!$C19+AF$8*Pakketten!$K19+RFF!AF$9*Pakketten!$S19 -> 1372 | AG55: =AG$7*Pakketten!$C19+AG$8*Pakketten!$K19+RFF!AG$9*Pakketten!$S19 -> 1504 | AH55: =AH$7*Pakketten!$C19+AH$8*Pakketten!$K19+RFF!AH$9*Pakketten!$S19 -> 1536 | AI55: =AI$7*Pakketten!$C19+AI$8*Pakketten!$K19+RFF!AI$9*Pakketten!$S19 -> 1640 | AJ55: =AJ$7*Pakketten!$C19+AJ$8*Pakketten!$K19+RFF!AJ$9*Pakketten!$S19 -> 1640 | AK55: =AK$7*Pakketten!$C19+AK$8*Pakketten!$K19+RFF!AK$9*Pakketten!$S19 -> 1640 | ... AO55: =AO$7*Pakketten!$C19+AO$8*Pakketten!$K19+RFF!AO$9*Pakketten!$S19 -> 1776 | AP55: =SUM(AD55:AO55) -> 19012
A56: =ROW() -> 56
A57: =ROW() -> 57 | B57: Productiviteit (op basis van ca 1600 uur)
A58: =ROW() -> 58 | B58: - CEO (C-level) | D58: =IFERROR(D46/(D20*D$30*8*0.6),0) -> 0 | E58: =IFERROR(E46/(E20*E$30*8*0.6),0) -> 0 | F58: =IFERROR(F46/(F20*F$30*8*0.6),0) -> 0 | G58: =IFERROR(G46/(G20*G$30*8*0.6),0) -> 0.20833333 | H58: =IFERROR(H46/(H20*H$30*8*0.6),0) -> 0.21929825 | I58: =IFERROR(I46/(I20*I$30*8*0.6),0) -> 0.18939394 | J58: =IFERROR(J46/(J20*J$30*8*0.6),0) -> 0.72463768 | K58: =IFERROR(K46/(K20*K$30*8*0.6),0) -> 0.79365079 | ... O58: =IFERROR(O46/(O20*O$30*8*0.6),0) -> 0.44191919 | Q58: =IFERROR(Q46/(Q20*Q$30*8*0.6),0) -> 0.87301587 | R58: =IFERROR(R46/(R20*R$30*8*0.6),0) -> 0.91666667 | S58: =IFERROR(S46/(S20*S$30*8*0.6),0) -> 0.90909091 | T58: =IFERROR(T46/(T20*T$30*8*0.6),0) -> 0.97222222 | U58: =IFERROR(U46/(U20*U$30*8*0.6),0) -> 1.0964912 | V58: =IFERROR(V46/(V20*V$30*8*0.6),0) -> 1.0732323 | W58: =IFERROR(W46/(W20*W$30*8*0.6),0) -> 1.02657 | X58: =IFERROR(X46/(X20*X$30*8*0.6),0) -> 1.1243386 | ... AB58: =IFERROR(AB46/(AB20*AB$30*8*0.6),0) -> 0.9469697 | AD58: =IFERROR(AD46/(AD20*AD$30*8*0.6),0) -> 0.79365079 | AE58: =IFERROR(AE46/(AE20*AE$30*8*0.6),0) -> 0.83333333 | AF58: =IFERROR(AF46/(AF20*AF$30*8*0.6),0) -> 0.78463203 | AG58: =IFERROR(AG46/(AG20*AG$30*8*0.6),0) -> 0.92261905 | AH58: =IFERROR(AH46/(AH20*AH$30*8*0.6),0) -> 1.0025063 | AI58: =IFERROR(AI46/(AI20*AI$30*8*0.6),0) -> 0.91991342 | AJ58: =IFERROR(AJ46/(AJ20*AJ$30*8*0.6),0) -> 0.87991718 | AK58: =IFERROR(AK46/(AK20*AK$30*8*0.6),0) -> 0.96371882 | ... AO58: =IFERROR(AO46/(AO20*AO$30*8*0.6),0) -> 0.87594697
A59: =ROW() -> 59 | B59: - CFO (C-level) | D59: =IFERROR(D47/(D21*D$30*8*0.7),0) -> 0 | E59: =IFERROR(E47/(E21*E$30*8*0.7),0) -> 0 | F59: =IFERROR(F47/(F21*F$30*8*0.7),0) -> 0 | G59: =IFERROR(G47/(G21*G$30*8*0.7),0) -> 0.11904762 | H59: =IFERROR(H47/(H21*H$30*8*0.7),0) -> 0.12531328 | I59: =IFERROR(I47/(I21*I$30*8*0.7),0) -> 0.10822511 | J59: =IFERROR(J47/(J21*J$30*8*0.7),0) -> 0.41407867 | K59: =IFERROR(K47/(K21*K$30*8*0.7),0) -> 0.45351474 | ... O59: =IFERROR(O47/(O21*O$30*8*0.7),0) -> 0.75757576 | Q59: =IFERROR(Q47/(Q21*Q$30*8*0.7),0) -> 0.93537415 | R59: =IFERROR(R47/(R21*R$30*8*0.7),0) -> 0.98214286 | S59: =IFERROR(S47/(S21*S$30*8*0.7),0) -> 0.97402597 | T59: =IFERROR(T47/(T21*T$30*8*0.7),0) -> 1 | U59: =IFERROR(U47/(U21*U$30*8*0.7),0) -> 0.80558539 | V59: =IFERROR(V47/(V21*V$30*8*0.7),0) -> 0.78849722 | W59: =IFERROR(W47/(W21*W$30*8*0.7),0) -> 0.75421473 | X59: =IFERROR(X47/(X21*X$30*8*0.7),0) -> 0.8260447 | ... AB59: =IFERROR(AB47/(AB21*AB$30*8*0.7),0) -> 0.92764378 | AD59: =IFERROR(AD47/(AD21*AD$30*8*0.7),0) -> 0.95238095 | AE59: =IFERROR(AE47/(AE21*AE$30*8*0.7),0) -> 1 | AF59: =IFERROR(AF47/(AF21*AF$30*8*0.7),0) -> 0.94155844 | AG59: =IFERROR(AG47/(AG21*AG$30*8*0.7),0) -> 1.0064935 | AH59: =IFERROR(AH47/(AH21*AH$30*8*0.7),0) -> 1.0936432 | AI59: =IFERROR(AI47/(AI21*AI$30*8*0.7),0) -> 1.0035419 | AJ59: =IFERROR(AJ47/(AJ21*AJ$30*8*0.7),0) -> 0.95990966 | AK59: =IFERROR(AK47/(AK21*AK$30*8*0.7),0) -> 1.0513296 | ... AO59: =IFERROR(AO47/(AO21*AO$30*8*0.7),0) -> 0.92407592
A60: =ROW() -> 60 | B60: - CMO (Senior-level) | D60: =IFERROR(D48/(D22*D$30*8*0.78),0) -> 0 | E60: =IFERROR(E48/(E22*E$30*8*0.78),0) -> 0 | F60: =IFERROR(F48/(F22*F$30*8*0.78),0) -> 0 | G60: =IFERROR(G48/(G22*G$30*8*0.78),0) -> 0 | H60: =IFERROR(H48/(H22*H$30*8*0.78),0) -> 0 | I60: =IFERROR(I48/(I22*I$30*8*0.78),0) -> 0 | J60: =IFERROR(J48/(J22*J$30*8*0.78),0) -> 0.6270903 | K60: =IFERROR(K48/(K22*K$30*8*0.78),0) -> 0.68681319 | ... O60: =IFERROR(O48/(O22*O$30*8*0.78),0) -> 0.72843823 | Q60: =IFERROR(Q48/(Q22*Q$30*8*0.78),0) -> 0.85851648 | R60: =IFERROR(R48/(R22*R$30*8*0.78),0) -> 0.90144231 | S60: =IFERROR(S48/(S22*S$30*8*0.78),0) -> 0.87412587 | T60: =IFERROR(T48/(T22*T$30*8*0.78),0) -> 0.96153846 | U60: =IFERROR(U48/(U22*U$30*8*0.78),0) -> 0.88562753 | V60: =IFERROR(V48/(V22*V$30*8*0.78),0) -> 0.87412587 | W60: =IFERROR(W48/(W22*W$30*8*0.78),0) -> 0.8361204 | X60: =IFERROR(X48/(X22*X$30*8*0.78),0) -> 0.91575092 | ... AB60: =IFERROR(AB48/(AB22*AB$30*8*0.78),0) -> 0.87412587 | AD60: =IFERROR(AD48/(AD22*AD$30*8*0.78),0) -> 0.91575092 | AE60: =IFERROR(AE48/(AE22*AE$30*8*0.78),0) -> 0.96153846 | AF60: =IFERROR(AF48/(AF22*AF$30*8*0.78),0) -> 0.89597902 | AG60: =IFERROR(AG48/(AG22*AG$30*8*0.78),0) -> 0.98339161 | AH60: =IFERROR(AH48/(AH22*AH$30*8*0.78),0) -> 1.0581524 | AI60: =IFERROR(AI48/(AI22*AI$30*8*0.78),0) -> 0.97345836 | AJ60: =IFERROR(AJ48/(AJ22*AJ$30*8*0.78),0) -> 0.93113408 | AK60: =IFERROR(AK48/(AK22*AK$30*8*0.78),0) -> 1.0198135 | ... AO60: =IFERROR(AO48/(AO22*AO$30*8*0.78),0) -> 0.89093599
A61: =ROW() -> 61 | B61: - CTO (Senior-level) | D61: =IFERROR(D49/(D23*D$30*8*0.78),0) -> 0 | E61: =IFERROR(E49/(E23*E$30*8*0.78),0) -> 0 | F61: =IFERROR(F49/(F23*F$30*8*0.78),0) -> 0 | G61: =IFERROR(G49/(G23*G$30*8*0.78),0) -> 0 | H61: =IFERROR(H49/(H23*H$30*8*0.78),0) -> 0 | I61: =IFERROR(I49/(I23*I$30*8*0.78),0) -> 0 | J61: =IFERROR(J49/(J23*J$30*8*0.78),0) -> 0.6270903 | K61: =IFERROR(K49/(K23*K$30*8*0.78),0) -> 0.68681319 | ... O61: =IFERROR(O49/(O23*O$30*8*0.78),0) -> 0.72843823 | Q61: =IFERROR(Q49/(Q23*Q$30*8*0.78),0) -> 0.85851648 | R61: =IFERROR(R49/(R23*R$30*8*0.78),0) -> 0.90144231 | S61: =IFERROR(S49/(S23*S$30*8*0.78),0) -> 0.87412587 | T61: =IFERROR(T49/(T23*T$30*8*0.78),0) -> 0.96153846 | U61: =IFERROR(U49/(U23*U$30*8*0.78),0) -> 0.88562753 | V61: =IFERROR(V49/(V23*V$30*8*0.78),0) -> 0.87412587 | W61: =IFERROR(W49/(W23*W$30*8*0.78),0) -> 0.8361204 | X61: =IFERROR(X49/(X23*X$30*8*0.78),0) -> 0.91575092 | ... AB61: =IFERROR(AB49/(AB23*AB$30*8*0.78),0) -> 0.87412587 | AD61: =IFERROR(AD49/(AD23*AD$30*8*0.78),0) -> 0.91575092 | AE61: =IFERROR(AE49/(AE23*AE$30*8*0.78),0) -> 0.96153846 | AF61: =IFERROR(AF49/(AF23*AF$30*8*0.78),0) -> 0.89597902 | AG61: =IFERROR(AG49/(AG23*AG$30*8*0.78),0) -> 0.90144231 | AH61: =IFERROR(AH49/(AH23*AH$30*8*0.78),0) -> 0.96997301 | AI61: =IFERROR(AI49/(AI23*AI$30*8*0.78),0) -> 0.89233683 | AJ61: =IFERROR(AJ49/(AJ23*AJ$30*8*0.78),0) -> 0.85353958 | AK61: =IFERROR(AK49/(AK23*AK$30*8*0.78),0) -> 0.93482906 | ... AO61: =IFERROR(AO49/(AO23*AO$30*8*0.78),0) -> 0.89093599
A62: =ROW() -> 62 | B62: - HR partner (Senior-level) | D62: =IFERROR(D50/(D24*D$30*8*0.78),0) -> 0 | E62: =IFERROR(E50/(E24*E$30*8*0.78),0) -> 0 | F62: =IFERROR(F50/(F24*F$30*8*0.78),0) -> 0 | G62: =IFERROR(G50/(G24*G$30*8*0.78),0) -> 0 | H62: =IFERROR(H50/(H24*H$30*8*0.78),0) -> 0 | I62: =IFERROR(I50/(I24*I$30*8*0.78),0) -> 0 | J62: =IFERROR(J50/(J24*J$30*8*0.78),0) -> 0.696767 | K62: =IFERROR(K50/(K24*K$30*8*0.78),0) -> 0.76312576 | ... O62: =IFERROR(O50/(O24*O$30*8*0.78),0) -> 0.80128205 | Q62: =IFERROR(Q50/(Q24*Q$30*8*0.78),0) -> 0.9539072 | R62: =IFERROR(R50/(R24*R$30*8*0.78),0) -> 1.0016026 | S62: =IFERROR(S50/(S24*S$30*8*0.78),0) -> 0.98339161 | T62: =IFERROR(T50/(T24*T$30*8*0.78),0) -> 0.75549451 | U62: =IFERROR(U50/(U24*U$30*8*0.78),0) -> 0.84345479 | V62: =IFERROR(V50/(V24*V$30*8*0.78),0) -> 0.82209457 | W62: =IFERROR(W50/(W24*W$30*8*0.78),0) -> 0.78635133 | X62: =IFERROR(X50/(X24*X$30*8*0.78),0) -> 0.86124193 | ... AB62: =IFERROR(AB50/(AB24*AB$30*8*0.78),0) -> 0.95737596 | AD62: =IFERROR(AD50/(AD24*AD$30*8*0.78),0) -> 0.99206349 | AE62: =IFERROR(AE50/(AE24*AE$30*8*0.78),0) -> 1.0416667 | AF62: =IFERROR(AF50/(AF24*AF$30*8*0.78),0) -> 0.97610723 | AG62: =IFERROR(AG50/(AG24*AG$30*8*0.78),0) -> 0.97489316 | AH62: =IFERROR(AH50/(AH24*AH$30*8*0.78),0) -> 1.0543185 | AI62: =IFERROR(AI50/(AI24*AI$30*8*0.78),0) -> 0.96518065 | AJ62: =IFERROR(AJ50/(AJ24*AJ$30*8*0.78),0) -> 0.92321628 | AK62: =IFERROR(AK50/(AK24*AK$30*8*0.78),0) -> 1.0111416 | ... AO62: =IFERROR(AO50/(AO24*AO$30*8*0.78),0) -> 0.96377981
A63: =ROW() -> 63 | B63: - Finance admin (Senior-level) | D63: =IFERROR(D51/(D25*D$30*8*0.78),0) -> 0 | E63: =IFERROR(E51/(E25*E$30*8*0.78),0) -> 0 | F63: =IFERROR(F51/(F25*F$30*8*0.78),0) -> 0 | G63: =IFERROR(G51/(G25*G$30*8*0.78),0) -> 0.24038462 | H63: =IFERROR(H51/(H25*H$30*8*0.78),0) -> 0.25303644 | I63: =IFERROR(I51/(I25*I$30*8*0.78),0) -> 0.21853147 | J63: =IFERROR(J51/(J25*J$30*8*0.78),0) -> 0.73160535 | K63: =IFERROR(K51/(K25*K$30*8*0.78),0) -> 0.80128205 | ... O63: =IFERROR(O51/(O25*O$30*8*0.78),0) -> 0.80128205 | Q63: =IFERROR(Q51/(Q25*Q$30*8*0.78),0) -> 0.77838828 | R63: =IFERROR(R51/(R25*R$30*8*0.78),0) -> 0.81730769 | S63: =IFERROR(S51/(S25*S$30*8*0.78),0) -> 0.83041958 | T63: =IFERROR(T51/(T25*T$30*8*0.78),0) -> 0.75549451 | U63: =IFERROR(U51/(U25*U$30*8*0.78),0) -> 0.8675535 | V63: =IFERROR(V51/(V25*V$30*8*0.78),0) -> 0.81168831 | W63: =IFERROR(W51/(W25*W$30*8*0.78),0) -> 0.77639752 | X63: =IFERROR(X51/(X25*X$30*8*0.78),0) -> 0.85034014 | ... AB63: =IFERROR(AB51/(AB25*AB$30*8*0.78),0) -> 0.93656344 | AD63: =IFERROR(AD51/(AD25*AD$30*8*0.78),0) -> 0.93864469 | AE63: =IFERROR(AE51/(AE25*AE$30*8*0.78),0) -> 0.98557692 | AF63: =IFERROR(AF51/(AF25*AF$30*8*0.78),0) -> 0.93968531 | AG63: =IFERROR(AG51/(AG25*AG$30*8*0.78),0) -> 0.92147436 | AH63: =IFERROR(AH51/(AH25*AH$30*8*0.78),0) -> 1.0121457 | AI63: =IFERROR(AI51/(AI25*AI$30*8*0.78),0) -> 0.91054779 | AJ63: =IFERROR(AJ51/(AJ25*AJ$30*8*0.78),0) -> 0.87095875 | AK63: =IFERROR(AK51/(AK25*AK$30*8*0.78),0) -> 0.9539072 | ... AO63: =IFERROR(AO51/(AO25*AO$30*8*0.78),0) -> 0.9077461
A64: =ROW() -> 64 | B64: - HR admin (Medior-level) | D64: =IFERROR(D52/(D26*D$30*8*0.78),0) -> 0 | E64: =IFERROR(E52/(E26*E$30*8*0.78),0) -> 0 | F64: =IFERROR(F52/(F26*F$30*8*0.78),0) -> 0 | G64: =IFERROR(G52/(G26*G$30*8*0.78),0) -> 0 | H64: =IFERROR(H52/(H26*H$30*8*0.78),0) -> 0 | I64: =IFERROR(I52/(I26*I$30*8*0.78),0) -> 0 | J64: =IFERROR(J52/(J26*J$30*8*0.78),0) -> 0 | K64: =IFERROR(K52/(K26*K$30*8*0.78),0) -> 0 | ... O64: =IFERROR(O52/(O26*O$30*8*0.78),0) -> 0 | Q64: =IFERROR(Q52/(Q26*Q$30*8*0.78),0) -> 0 | R64: =IFERROR(R52/(R26*R$30*8*0.78),0) -> 0 | S64: =IFERROR(S52/(S26*S$30*8*0.78),0) -> 0 | T64: =IFERROR(T52/(T26*T$30*8*0.78),0) -> 0 | U64: =IFERROR(U52/(U26*U$30*8*0.78),0) -> 0 | V64: =IFERROR(V52/(V26*V$30*8*0.78),0) -> 0 | W64: =IFERROR(W52/(W26*W$30*8*0.78),0) -> 0 | X64: =IFERROR(X52/(X26*X$30*8*0.78),0) -> 0 | ... AB64: =IFERROR(AB52/(AB26*AB$30*8*0.78),0) -> 0 | AD64: =IFERROR(AD52/(AD26*AD$30*8*0.78),0) -> 0 | AE64: =IFERROR(AE52/(AE26*AE$30*8*0.78),0) -> 0 | AF64: =IFERROR(AF52/(AF26*AF$30*8*0.78),0) -> 0 | AG64: =IFERROR(AG52/(AG26*AG$30*8*0.78),0) -> 0 | AH64: =IFERROR(AH52/(AH26*AH$30*8*0.78),0) -> 0 | AI64: =IFERROR(AI52/(AI26*AI$30*8*0.78),0) -> 0 | AJ64: =IFERROR(AJ52/(AJ26*AJ$30*8*0.78),0) -> 0 | AK64: =IFERROR(AK52/(AK26*AK$30*8*0.78),0) -> 0 | ... AO64: =IFERROR(AO52/(AO26*AO$30*8*0.78),0) -> 0
A65: =ROW() -> 65 | B65: - Backoffice support (Junior-level) | D65: =IFERROR(D53/(D27*D$30*8*0.78),0) -> 0 | E65: =IFERROR(E53/(E27*E$30*8*0.78),0) -> 0 | F65: =IFERROR(F53/(F27*F$30*8*0.78),0) -> 0 | G65: =IFERROR(G53/(G27*G$30*8*0.78),0) -> 0 | H65: =IFERROR(H53/(H27*H$30*8*0.78),0) -> 0 | I65: =IFERROR(I53/(I27*I$30*8*0.78),0) -> 0 | J65: =IFERROR(J53/(J27*J$30*8*0.78),0) -> 1.2193423 | K65: =IFERROR(K53/(K27*K$30*8*0.78),0) -> 1.3354701 | ... O65: =IFERROR(O53/(O27*O$30*8*0.78),0) -> 0.87412587 | Q65: =IFERROR(Q53/(Q27*Q$30*8*0.78),0) -> 0.90621184 | R65: =IFERROR(R53/(R27*R$30*8*0.78),0) -> 0.95152244 | S65: =IFERROR(S53/(S27*S$30*8*0.78),0) -> 0.95607517 | T65: =IFERROR(T53/(T27*T$30*8*0.78),0) -> 0.96153846 | U65: =IFERROR(U53/(U27*U$30*8*0.78),0) -> 0.91374269 | V65: =IFERROR(V53/(V27*V$30*8*0.78),0) -> 0.88019619 | W65: =IFERROR(W53/(W27*W$30*8*0.78),0) -> 0.84192679 | X65: =IFERROR(X53/(X27*X$30*8*0.78),0) -> 0.9221103 | ... AB65: =IFERROR(AB53/(AB27*AB$30*8*0.78),0) -> 0.82556333 | AD65: =IFERROR(AD53/(AD27*AD$30*8*0.78),0) -> 0.89667277 | AE65: =IFERROR(AE53/(AE27*AE$30*8*0.78),0) -> 0.94150641 | AF65: =IFERROR(AF53/(AF27*AF$30*8*0.78),0) -> 0.89233683 | AG65: =IFERROR(AG53/(AG27*AG$30*8*0.78),0) -> 0.9469697 | AH65: =IFERROR(AH53/(AH27*AH$30*8*0.78),0) -> 1.0351491 | AI65: =IFERROR(AI53/(AI27*AI$30*8*0.78),0) -> 0.94365861 | AJ65: =IFERROR(AJ53/(AJ27*AJ$30*8*0.78),0) -> 0.90262998 | AK65: =IFERROR(AK53/(AK27*AK$30*8*0.78),0) -> 0.98859474 | ... AO65: =IFERROR(AO53/(AO27*AO$30*8*0.78),0) -> 0.98180805
A66: =ROW() -> 66 | B66: - Data engineer (Medior-level) | D66: =IFERROR(D54/(D28*D$30*8*0.78),0) -> 0 | E66: =IFERROR(E54/(E28*E$30*8*0.78),0) -> 0 | F66: =IFERROR(F54/(F28*F$30*8*0.78),0) -> 0 | G66: =IFERROR(G54/(G28*G$30*8*0.78),0) -> 0 | H66: =IFERROR(H54/(H28*H$30*8*0.78),0) -> 0 | I66: =IFERROR(I54/(I28*I$30*8*0.78),0) -> 0 | J66: =IFERROR(J54/(J28*J$30*8*0.78),0) -> 0.0696767 | K66: =IFERROR(K54/(K28*K$30*8*0.78),0) -> 0.076312576 | ... O66: =IFERROR(O54/(O28*O$30*8*0.78),0) -> 0.14568765 | Q66: =IFERROR(Q54/(Q28*Q$30*8*0.78),0) -> 0.22893773 | R66: =IFERROR(R54/(R28*R$30*8*0.78),0) -> 0.24038462 | S66: =IFERROR(S54/(S28*S$30*8*0.78),0) -> 0.21853147 | T66: =IFERROR(T54/(T28*T$30*8*0.78),0) -> 0.32051282 | U66: =IFERROR(U54/(U28*U$30*8*0.78),0) -> 0.33738192 | V66: =IFERROR(V54/(V28*V$30*8*0.78),0) -> 0.36421911 | W66: =IFERROR(W54/(W28*W$30*8*0.78),0) -> 0.3483835 | X66: =IFERROR(X54/(X28*X$30*8*0.78),0) -> 0.38156288 | ... AB66: =IFERROR(AB54/(AB28*AB$30*8*0.78),0) -> 0.43706294 | AD66: =IFERROR(AD54/(AD28*AD$30*8*0.78),0) -> 0.68681319 | AE66: =IFERROR(AE54/(AE28*AE$30*8*0.78),0) -> 0.72115385 | AF66: =IFERROR(AF54/(AF28*AF$30*8*0.78),0) -> 0.65559441 | AG66: =IFERROR(AG54/(AG28*AG$30*8*0.78),0) -> 0.80128205 | AH66: =IFERROR(AH54/(AH28*AH$30*8*0.78),0) -> 0.84345479 | AI66: =IFERROR(AI54/(AI28*AI$30*8*0.78),0) -> 0.80128205 | AJ66: =IFERROR(AJ54/(AJ28*AJ$30*8*0.78),0) -> 0.7664437 | AK66: =IFERROR(AK54/(AK28*AK$30*8*0.78),0) -> 0.83943834 | ... AO66: =IFERROR(AO54/(AO28*AO$30*8*0.78),0) -> 0.87412587
A67: =ROW() -> 67 | D67: =D55/(D30*8*SUM(D20:D28)) -> 0 | E67: =E55/(E30*8*SUM(E20:E28)) -> 0 | F67: =F55/(F30*8*SUM(F20:F28)) -> 0 | G67: =G55/(G30*8*SUM(G20:G28)) -> 0.16666667 | H67: =H55/(H30*8*SUM(H20:H28)) -> 0.1754386 | I67: =I55/(I30*8*SUM(I20:I28)) -> 0.15151515 | J67: =J55/(J30*8*SUM(J20:J28)) -> 0.33288043 | K67: =K55/(K30*8*SUM(K20:K28)) -> 0.36458333 | ... O67: =O55/(O30*8*SUM(O20:O28)) -> 0.37727273 | Q67: =Q55/(Q30*8*SUM(Q20:Q28)) -> 0.44420753 | R67: =R55/(R30*8*SUM(R20:R28)) -> 0.46641791 | S67: =S55/(S30*8*SUM(S20:S28)) -> 0.45115332 | T67: =T55/(T30*8*SUM(T20:T28)) -> 0.47159091 | U67: =U55/(U30*8*SUM(U20:U28)) -> 0.45789474 | V67: =V55/(V30*8*SUM(V20:V28)) -> 0.45454545 | W67: =W55/(W30*8*SUM(W20:W28)) -> 0.43478261 | X67: =X55/(X30*8*SUM(X20:X28)) -> 0.47619048 | ... AB67: =AB55/(AB30*8*SUM(AB20:AB28)) -> 0.47483766 | AD67: =AD55/(AD30*8*SUM(AD20:AD28)) -> 0.50482218 | AE67: =AE55/(AE30*8*SUM(AE20:AE28)) -> 0.53006329 | AF67: =AF55/(AF30*8*SUM(AF20:AF28)) -> 0.4933832 | AG67: =AG55/(AG30*8*SUM(AG20:AG28)) -> 0.52808989 | AH67: =AH55/(AH30*8*SUM(AH20:AH28)) -> 0.56771141 | AI67: =AI55/(AI30*8*SUM(AI20:AI28)) -> 0.52349336 | AJ67: =AJ55/(AJ30*8*SUM(AJ20:AJ28)) -> 0.50073278 | AK67: =AK55/(AK30*8*SUM(AK20:AK28)) -> 0.54842162 | ... AO67: =AO55/(AO30*8*SUM(AO20:AO28)) -> 0.5148423
A68: =ROW() -> 68
A69: =ROW() -> 69
A70: =ROW() -> 70
A71: =ROW() -> 71 | B71: Winst en verlies
A72: =ROW() -> 72
A73: =ROW() -> 73 | B73: Omzet Foundation | D73: =D15 -> 0 | E73: =E15 -> 0 | F73: =F15 -> 0 | G73: =G15 -> 6750 | H73: =H15 -> 6750 | I73: =I15 -> 6750 | J73: =J15 -> 13500 | K73: =K15 -> 13500 | ... O73: =O15 -> 20250 | P73: =SUM(D73:O73) -> 121500 | Q73: =Q15 -> 35437.5 | R73: =R15 -> 35437.5 | S73: =S15 -> 42525 | T73: =T15 -> 42525 | U73: =U15 -> 49612.5 | V73: =V15 -> 49612.5 | W73: =W15 -> 49612.5 | X73: =X15 -> 49612.5 | ... AB73: =AB15 -> 56700 | AC73: =SUM(Q73:AB73) -> 581175 | AD73: =AD15 -> 74418.75 | AE73: =AE15 -> 74418.75 | AF73: =AF15 -> 81860.625 | AG73: =AG15 -> 81860.625 | AH73: =AH15 -> 89302.5 | AI73: =AI15 -> 89302.5 | AJ73: =AJ15 -> 89302.5 | AK73: =AK15 -> 89302.5 | ... AO73: =AO15 -> 96744.375 | AP73: =SUM(AD73:AO73) -> 1056746.2
A74: =ROW() -> 74 | B74: Omzet Growth | D74: =D16 -> 0 | E74: =E16 -> 0 | F74: =F16 -> 0 | G74: =G16 -> 0 | H74: =H16 -> 0 | I74: =I16 -> 0 | J74: =J16 -> 17000 | K74: =K16 -> 17000 | ... O74: =O16 -> 17000 | P74: =SUM(D74:O74) -> 102000 | Q74: =Q16 -> 17850 | R74: =R16 -> 17850 | S74: =S16 -> 17850 | T74: =T16 -> 35700 | U74: =U16 -> 35700 | V74: =V16 -> 35700 | W74: =W16 -> 35700 | X74: =X16 -> 35700 | ... AB74: =AB16 -> 35700 | AC74: =SUM(Q74:AB74) -> 374850 | AD74: =AD16 -> 56227.5 | AE74: =AE16 -> 56227.5 | AF74: =AF16 -> 56227.5 | AG74: =AG16 -> 74970 | AH74: =AH16 -> 74970 | AI74: =AI16 -> 74970 | AJ74: =AJ16 -> 74970 | AK74: =AK16 -> 74970 | ... AO74: =AO16 -> 74970 | AP74: =SUM(AD74:AO74) -> 843412.5
A75: =ROW() -> 75 | B75: Omzet Scale | D75: =D17 -> 0 | E75: =E17 -> 0 | F75: =F17 -> 0 | G75: =G17 -> 0 | H75: =H17 -> 0 | I75: =I17 -> 0 | J75: =J17 -> 0 | K75: =K17 -> 0 | ... O75: =O17 -> 13500 | P75: =SUM(D75:O75) -> 40500 | Q75: =Q17 -> 28350 | R75: =R17 -> 28350 | S75: =S17 -> 28350 | T75: =T17 -> 28350 | U75: =U17 -> 28350 | V75: =V17 -> 42525 | W75: =W17 -> 42525 | X75: =X17 -> 42525 | ... AB75: =AB17 -> 56700 | AC75: =SUM(Q75:AB75) -> 481950 | AD75: =AD17 -> 89302.5 | AE75: =AE17 -> 89302.5 | AF75: =AF17 -> 89302.5 | AG75: =AG17 -> 89302.5 | AH75: =AH17 -> 89302.5 | AI75: =AI17 -> 104186.25 | AJ75: =AJ17 -> 104186.25 | AK75: =AK17 -> 104186.25 | ... AO75: =AO17 -> 119070 | AP75: =SUM(AD75:AO75) -> 1220467.5
A76: =ROW() -> 76 | B76: Omzet opstartfee | D76: =E7*1000+E8*15000+E9*25000 -> 0 | E76: =F7-E7*1000+F8-E8*15000+F9-E9*25000 -> 0 | F76: =(G7-F7)*10000+(G8-F8)*15000+(G9-F9)*25000 -> 10000 | G76: =(H7-G7)*10000+(H8-G8)*15000+(H9-G9)*25000 -> 0 | H76: =(I7-H7)*10000+(I8-H8)*15000+(I9-H9)*25000 -> 0 | I76: =(J7-I7)*10000+(J8-I8)*15000+(J9-I9)*25000 -> 25000 | J76: =(K7-J7)*10000+(K8-J8)*15000+(K9-J9)*25000 -> 0 | K76: =(L7-K7)*10000+(L8-K8)*15000+(L9-K9)*25000 -> 0 | L76: =(M7-L7)*10000+(M8-L8)*15000+(M9-L9)*25000 -> 22500 | M76: =(N7-M7)*10000+(N8-M8)*15000+(N9-M9)*25000 -> 0 | N76: =(O7-N7)*10000+(O8-N8)*15000+(O9-N9)*25000 -> 0 | O76: =(Q7-O7)*10000+(Q8-O8)*15000+(Q9-O9)*25000 -> 32500 | P76: =SUM(D76:O76) -> 90000 | Q76: =(R7-Q7)*10000+(R8-Q8)*15000+(R9-Q9)*25000 -> 0 | R76: =(S7-R7)*10000+(S8-R8)*15000+(S9-R9)*25000 -> 10000 | S76: =(T7-S7)*10000+(T8-S8)*15000+(T9-S9)*25000 -> 15000 | T76: =(U7-T7)*10000+(U8-T8)*15000+(U9-T9)*25000 -> 10000 | U76: =(V7-U7)*10000+(V8-U8)*15000+(V9-U9)*25000 -> 12500 | V76: =(W7-V7)*10000+(W8-V8)*15000+(W9-V9)*25000 -> 0 | W76: =(X7-W7)*10000+(X8-W8)*15000+(X9-W9)*25000 -> 0 | X76: =(Y7-X7)*10000+(Y8-X8)*15000+(Y9-X9)*25000 -> 10000 | ... AA76: =(AB7-AA7)*10000+(AB8-AA8)*15000+(AB9-AA9)*25000 -> 0 | AB76: =(AD7-AB7)*10000+(AD8-AB8)*15000+(AD9-AB9)*25000 -> 60000 | AC76: =SUM(Q76:AB76) -> 130000 | AD76: =(AE7-AD7)*10000+(AE8-AD8)*15000+(AE9-AD9)*25000 -> 0 | AE76: =(AF7-AE7)*10000+(AF8-AE8)*15000+(AF9-AE9)*25000 -> 10000 | AF76: =(AG7-AF7)*10000+(AG8-AF8)*15000+(AG9-AF9)*25000 -> 15000 | AG76: =(AH7-AG7)*10000+(AH8-AG8)*15000+(AH9-AG9)*25000 -> 10000 | AH76: =(AI7-AH7)*10000+(AI8-AH8)*15000+(AI9-AH9)*25000 -> 12500 | AI76: =(AJ7-AI7)*10000+(AJ8-AI8)*15000+(AJ9-AI9)*25000 -> 0 | AJ76: =(AK7-AJ7)*10000+(AK8-AJ8)*15000+(AK9-AJ9)*25000 -> 0 | AK76: =(AL7-AK7)*10000+(AL8-AK8)*15000+(AL9-AK9)*25000 -> 10000 | ... AN76: =(AO7-AN7)*10000+(AO8-AN8)*15000+(AO9-AN9)*25000 -> 0 | AO76: 0 | AP76: =SUM(AD76:AO76) -> 70000
A77: =ROW() -> 77 | B77: Omzet Projecten | D77: 20000 | E77: 20000 | F77: 20000 | G77: 15000 | H77: 15000 | I77: 2500 | J77: 2500 | K77: 2500 | L77: 2500 | M77: 2500 | N77: 2500 | O77: 2500 | P77: =SUM(D77:O77) -> 107500 | Q77: 5000 | R77: 5000 | S77: 5000 | T77: 5000 | U77: 5000 | V77: 5000 | W77: 5000 | X77: 5000 | Y77: 5000 | Z77: 5000 | AA77: 5000 | AB77: 5000 | AC77: =SUM(Q77:AB77) -> 60000 | AD77: 10000 | AE77: 10000 | AF77: 10000 | AG77: 10000 | AH77: 10000 | AI77: 10000 | AJ77: 10000 | AK77: 10000 | AL77: 10000 | AM77: 10000 | AN77: 10000 | AO77: 10000 | AP77: =SUM(AD77:AO77) -> 120000
A78: =ROW() -> 78 | B78: Omzet Exitfee
A79: =ROW() -> 79 | B79: Totaal omzet | C79: =SUM(C73:C76) -> 0 | D79: =SUM(D73:D77) -> 20000 | E79: =SUM(E73:E77) -> 20000 | F79: =SUM(F73:F77) -> 30000 | G79: =SUM(G73:G77) -> 21750 | H79: =SUM(H73:H77) -> 21750 | I79: =SUM(I73:I77) -> 34250 | J79: =SUM(J73:J77) -> 33000 | K79: =SUM(K73:K77) -> 33000 | ... O79: =SUM(O73:O77) -> 85750 | P79: =SUM(D79:O79) -> 461500 | Q79: =SUM(Q73:Q77) -> 86637.5 | R79: =SUM(R73:R77) -> 96637.5 | S79: =SUM(S73:S77) -> 108725 | T79: =SUM(T73:T77) -> 121575 | U79: =SUM(U73:U77) -> 131162.5 | V79: =SUM(V73:V77) -> 132837.5 | W79: =SUM(W73:W77) -> 132837.5 | X79: =SUM(X73:X77) -> 142837.5 | ... AB79: =SUM(AB73:AB77) -> 214100 | AC79: =SUM(Q79:AB79) -> 1627975 | AD79: =SUM(AD73:AD77) -> 229948.75 | AE79: =SUM(AE73:AE77) -> 239948.75 | AF79: =SUM(AF73:AF77) -> 252390.62 | AG79: =SUM(AG73:AG77) -> 266133.12 | AH79: =SUM(AH73:AH77) -> 276075 | AI79: =SUM(AI73:AI77) -> 278458.75 | AJ79: =SUM(AJ73:AJ77) -> 278458.75 | AK79: =SUM(AK73:AK77) -> 288458.75 | ... AO79: =SUM(AO73:AO77) -> 300784.38 | AP79: =SUM(AD79:AO79) -> 3310626.2
A80: =ROW() -> 80
A81: =ROW() -> 81 | B81: Kostprijs AFAS licenties | D81: =D7*10*30+D8*30+D9*100 -> 0 | E81: =E7*10*30+E8*30+E9*100 -> 0 | F81: =F7*10*30+F8*30+F9*100 -> 0 | G81: =G7*10*30+G8*30+G9*100 -> 300 | H81: =H7*10*30+H8*30+H9*100 -> 300 | I81: =I7*10*30+I8*30+I9*100 -> 300 | J81: =J7*10*30+J8*30+J9*100 -> 630 | K81: =K7*10*30+K8*30+K9*100 -> 630 | ... O81: =O7*10*30+O8*30+O9*100 -> 980 | P81: =SUM(D81:O81) -> 5730 | Q81: =Q7*10*30+Q8*30+Q9*100 -> 1630 | R81: =R7*10*30+R8*30+R9*100 -> 1630 | S81: =S7*10*30+S8*30+S9*100 -> 1930 | T81: =T7*10*30+T8*30+T9*100 -> 1960 | U81: =U7*10*30+U8*30+U9*100 -> 2260 | V81: =V7*10*30+V8*30+V9*100 -> 2310 | W81: =W7*10*30+W8*30+W9*100 -> 2310 | X81: =X7*10*30+X8*30+X9*100 -> 2310 | ... AB81: =AB7*10*30+AB8*30+AB9*100 -> 2660 | AC81: =SUM(Q81:AB81) -> 26930 | AD81: =AD7*10*30+AD8*30+AD9*100 -> 3390 | AE81: =AE7*10*30+AE8*30+AE9*100 -> 3390 | AF81: =AF7*10*30+AF8*30+AF9*100 -> 3690 | AG81: =AG7*10*30+AG8*30+AG9*100 -> 3720 | AH81: =AH7*10*30+AH8*30+AH9*100 -> 4020 | AI81: =AI7*10*30+AI8*30+AI9*100 -> 4070 | AJ81: =AJ7*10*30+AJ8*30+AJ9*100 -> 4070 | AK81: =AK7*10*30+AK8*30+AK9*100 -> 4070 | ... AO81: =AO7*10*30+AO8*30+AO9*100 -> 4420 | AP81: =SUM(AD81:AO81) -> 48050
A82: =ROW() -> 82 | B82: Kostprijs Hubspot licenties | D82: =D7*2*100+D8*6*100+D9*12*100 -> 0 | E82: =E7*2*100+E8*6*100+E9*12*100 -> 0 | F82: =F7*2*100+F8*6*100+F9*12*100 -> 0 | G82: =G7*2*100+G8*6*100+G9*12*100 -> 200 | H82: =H7*2*100+H8*6*100+H9*12*100 -> 200 | I82: =I7*2*100+I8*6*100+I9*12*100 -> 200 | J82: =J7*2*100+J8*6*100+J9*12*100 -> 1000 | K82: =K7*2*100+K8*6*100+K9*12*100 -> 1000 | ... O82: =O7*2*100+O8*6*100+O9*12*100 -> 1800 | P82: =SUM(D82:O82) -> 9000 | Q82: =Q7*2*100+Q8*6*100+Q9*12*100 -> 2800 | R82: =R7*2*100+R8*6*100+R9*12*100 -> 2800 | S82: =S7*2*100+S8*6*100+S9*12*100 -> 3000 | T82: =T7*2*100+T8*6*100+T9*12*100 -> 3600 | U82: =U7*2*100+U8*6*100+U9*12*100 -> 3800 | V82: =V7*2*100+V8*6*100+V9*12*100 -> 4400 | W82: =W7*2*100+W8*6*100+W9*12*100 -> 4400 | X82: =X7*2*100+X8*6*100+X9*12*100 -> 4400 | ... AB82: =AB7*2*100+AB8*6*100+AB9*12*100 -> 5200 | AC82: =SUM(Q82:AB82) -> 49400 | AD82: =AD7*2*100+AD8*6*100+AD9*12*100 -> 7400 | AE82: =AE7*2*100+AE8*6*100+AE9*12*100 -> 7400 | AF82: =AF7*2*100+AF8*6*100+AF9*12*100 -> 7600 | AG82: =AG7*2*100+AG8*6*100+AG9*12*100 -> 8200 | AH82: =AH7*2*100+AH8*6*100+AH9*12*100 -> 8400 | AI82: =AI7*2*100+AI8*6*100+AI9*12*100 -> 9000 | AJ82: =AJ7*2*100+AJ8*6*100+AJ9*12*100 -> 9000 | AK82: =AK7*2*100+AK8*6*100+AK9*12*100 -> 9000 | ... AO82: =AO7*2*100+AO8*6*100+AO9*12*100 -> 9800 | AP82: =SUM(AD82:AO82) -> 104600
A83: =ROW() -> 83 | B83: Totaal kostprijs | C83: =SUM(C81:C82) -> 0 | D83: =SUM(D81:D82) -> 0 | E83: =SUM(E81:E82) -> 0 | F83: =SUM(F81:F82) -> 0 | G83: =SUM(G81:G82) -> 500 | H83: =SUM(H81:H82) -> 500 | I83: =SUM(I81:I82) -> 500 | J83: =SUM(J81:J82) -> 1630 | ... O83: =SUM(O81:O82) -> 2780 | P83: =SUM(D83:O83) -> 14730 | Q83: =SUM(Q81:Q82) -> 4430 | R83: =SUM(R81:R82) -> 4430 | S83: =SUM(S81:S82) -> 4930 | T83: =SUM(T81:T82) -> 5560 | U83: =SUM(U81:U82) -> 6060 | V83: =SUM(V81:V82) -> 6710 | W83: =SUM(W81:W82) -> 6710 | X83: =SUM(X81:X82) -> 6710 | ... AB83: =SUM(AB81:AB82) -> 7860 | AC83: =SUM(Q83:AB83) -> 76330 | AD83: =SUM(AD81:AD82) -> 10790 | AE83: =SUM(AE81:AE82) -> 10790 | AF83: =SUM(AF81:AF82) -> 11290 | AG83: =SUM(AG81:AG82) -> 11920 | AH83: =SUM(AH81:AH82) -> 12420 | AI83: =SUM(AI81:AI82) -> 13070 | AJ83: =SUM(AJ81:AJ82) -> 13070 | AK83: =SUM(AK81:AK82) -> 13070 | ... AO83: =SUM(AO81:AO82) -> 14220 | AP83: =SUM(AD83:AO83) -> 152650
A84: =ROW() -> 84
A85: =ROW() -> 85 | B85: Personeelskosten
A86: =ROW() -> 86 | B86: =OPEX!B29 -> Brutosalarissen | D86: =OPEX!D29 -> 2600 | E86: =OPEX!E29 -> 2600 | F86: =OPEX!F29 -> 2600 | G86: =OPEX!G29 -> 2600 | H86: =OPEX!H29 -> 2600 | I86: =OPEX!I29 -> 2600 | J86: =OPEX!J29 -> 20500 | K86: =OPEX!K29 -> 20500 | ... O86: =OPEX!O29 -> 22300 | P86: =SUM(D86:O86) -> 145800 | Q86: =OPEX!Q29 -> 30797 | R86: =OPEX!R29 -> 30797 | S86: =OPEX!S29 -> 30797 | T86: =OPEX!T29 -> 41097 | U86: =OPEX!U29 -> 45629 | V86: =OPEX!V29 -> 45629 | W86: =OPEX!W29 -> 45629 | X86: =OPEX!X29 -> 45629 | ... AB86: =OPEX!AB29 -> 50779 | AC86: =SUM(Q86:AB86) -> 513970 | AD86: =OPEX!AD29 -> 70864 | AE86: =OPEX!AE29 -> 70864 | AF86: =OPEX!AF29 -> 70864 | AG86: =OPEX!AG29 -> 81782 | AH86: =OPEX!AH29 -> 81782 | AI86: =OPEX!AI29 -> 81782 | AJ86: =OPEX!AJ29 -> 81782 | AK86: =OPEX!AK29 -> 81782 | ... AO86: =OPEX!AO29 -> 89713 | AP86: =SUM(AD86:AO86) -> 972423
A87: =ROW() -> 87 | B87: =OPEX!B30 -> Vakantiegeld | D87: =OPEX!D30 -> 208 | E87: =OPEX!E30 -> 208 | F87: =OPEX!F30 -> 208 | G87: =OPEX!G30 -> 208 | H87: =OPEX!H30 -> 208 | I87: =OPEX!I30 -> 208 | J87: =OPEX!J30 -> 1640 | K87: =OPEX!K30 -> 1640 | ... O87: =OPEX!O30 -> 1784 | P87: =SUM(D87:O87) -> 11664 | Q87: =OPEX!Q30 -> 2463.76 | R87: =OPEX!R30 -> 2463.76 | S87: =OPEX!S30 -> 2463.76 | T87: =OPEX!T30 -> 3287.76 | U87: =OPEX!U30 -> 3650.32 | V87: =OPEX!V30 -> 3650.32 | W87: =OPEX!W30 -> 3650.32 | X87: =OPEX!X30 -> 3650.32 | ... AB87: =OPEX!AB30 -> 4062.32 | AC87: =SUM(Q87:AB87) -> 41117.6 | AD87: =OPEX!AD30 -> 5669.12 | AE87: =OPEX!AE30 -> 5669.12 | AF87: =OPEX!AF30 -> 5669.12 | AG87: =OPEX!AG30 -> 6542.56 | AH87: =OPEX!AH30 -> 6542.56 | AI87: =OPEX!AI30 -> 6542.56 | AJ87: =OPEX!AJ30 -> 6542.56 | AK87: =OPEX!AK30 -> 6542.56 | ... AO87: =OPEX!AO30 -> 7177.04 | AP87: =SUM(AD87:AO87) -> 77793.84
A88: =ROW() -> 88 | B88: =OPEX!B31 -> Bonussen | D88: =OPEX!D31 -> 883.33333 | E88: =OPEX!E31 -> 883.33333 | F88: =OPEX!F31 -> 883.33333 | G88: =OPEX!G31 -> 883.33333 | H88: =OPEX!H31 -> 883.33333 | I88: =OPEX!I31 -> 883.33333 | J88: =OPEX!J31 -> 2375 | K88: =OPEX!K31 -> 2375 | ... O88: =OPEX!O31 -> 2525 | P88: =SUM(D88:O88) -> 20150 | Q88: =OPEX!Q31 -> 3682.25 | R88: =OPEX!R31 -> 3682.25 | S88: =OPEX!S31 -> 3682.25 | T88: =OPEX!T31 -> 4798.0833 | U88: =OPEX!U31 -> 5519.0833 | V88: =OPEX!V31 -> 5519.0833 | W88: =OPEX!W31 -> 5519.0833 | X88: =OPEX!X31 -> 5519.0833 | ... AB88: =OPEX!AB31 -> 6119.9167 | AC88: =SUM(Q88:AB88) -> 61971.667 | AD88: =OPEX!AD31 -> 8823.6667 | AE88: =OPEX!AE31 -> 8823.6667 | AF88: =OPEX!AF31 -> 8823.6667 | AG88: =OPEX!AG31 -> 9905.1667 | AH88: =OPEX!AH31 -> 9905.1667 | AI88: =OPEX!AI31 -> 9905.1667 | AJ88: =OPEX!AJ31 -> 9905.1667 | AK88: =OPEX!AK31 -> 9905.1667 | ... AO88: =OPEX!AO31 -> 11081.083 | AP88: =SUM(AD88:AO88) -> 119145.25
A89: =ROW() -> 89 | B89: =OPEX!B32 -> Pensioen | D89: =OPEX!D32 -> 208 | E89: =OPEX!E32 -> 208 | F89: =OPEX!F32 -> 208 | G89: =OPEX!G32 -> 208 | H89: =OPEX!H32 -> 208 | I89: =OPEX!I32 -> 208 | J89: =OPEX!J32 -> 1640 | K89: =OPEX!K32 -> 1640 | ... O89: =OPEX!O32 -> 1784 | P89: =SUM(D89:O89) -> 11664 | Q89: =OPEX!Q32 -> 2463.76 | R89: =OPEX!R32 -> 2463.76 | S89: =OPEX!S32 -> 2463.76 | T89: =OPEX!T32 -> 3287.76 | U89: =OPEX!U32 -> 3650.32 | V89: =OPEX!V32 -> 3650.32 | W89: =OPEX!W32 -> 3650.32 | X89: =OPEX!X32 -> 3650.32 | ... AB89: =OPEX!AB32 -> 4062.32 | AC89: =SUM(Q89:AB89) -> 41117.6 | AD89: =OPEX!AD32 -> 5669.12 | AE89: =OPEX!AE32 -> 5669.12 | AF89: =OPEX!AF32 -> 5669.12 | AG89: =OPEX!AG32 -> 6542.56 | AH89: =OPEX!AH32 -> 6542.56 | AI89: =OPEX!AI32 -> 6542.56 | AJ89: =OPEX!AJ32 -> 6542.56 | AK89: =OPEX!AK32 -> 6542.56 | ... AO89: =OPEX!AO32 -> 7177.04 | AP89: =SUM(AD89:AO89) -> 77793.84
A90: =ROW() -> 90 | B90: =OPEX!B33 -> Soc. Lasten | D90: =OPEX!D33 -> 549.55333 | E90: =OPEX!E33 -> 549.55333 | F90: =OPEX!F33 -> 549.55333 | G90: =OPEX!G33 -> 549.55333 | H90: =OPEX!H33 -> 549.55333 | I90: =OPEX!I33 -> 549.55333 | J90: =OPEX!J33 -> 4333.0167 | K90: =OPEX!K33 -> 4333.0167 | ... O90: =OPEX!O33 -> 4713.4767 | P90: =SUM(D90:O90) -> 30817.26 | Q90: =OPEX!Q33 -> 6509.4592 | R90: =OPEX!R33 -> 6509.4592 | S90: =OPEX!S33 -> 6509.4592 | T90: =OPEX!T33 -> 8686.5359 | U90: =OPEX!U33 -> 9644.4496 | V90: =OPEX!V33 -> 9644.4496 | W90: =OPEX!W33 -> 9644.4496 | X90: =OPEX!X33 -> 9644.4496 | ... AB90: =OPEX!AB33 -> 10732.988 | AC90: =SUM(Q90:AB90) -> 108636.13 | AD90: =OPEX!AD33 -> 14978.287 | AE90: =OPEX!AE33 -> 14978.287 | AF90: =OPEX!AF33 -> 14978.287 | AG90: =OPEX!AG33 -> 17285.989 | AH90: =OPEX!AH33 -> 17285.989 | AI90: =OPEX!AI33 -> 17285.989 | AJ90: =OPEX!AJ33 -> 17285.989 | AK90: =OPEX!AK33 -> 17285.989 | ... AO90: =OPEX!AO33 -> 18962.338 | AP90: =SUM(AD90:AO90) -> 205537.81
A91: =ROW() -> 91 | B91: =OPEX!B34 -> Vergoedingen | D91: =OPEX!D34 -> 100 | E91: =OPEX!E34 -> 100 | F91: =OPEX!F34 -> 100 | G91: =OPEX!G34 -> 100 | H91: =OPEX!H34 -> 100 | I91: =OPEX!I34 -> 100 | J91: =OPEX!J34 -> 250 | K91: =OPEX!K34 -> 250 | ... O91: =OPEX!O34 -> 280 | P91: =SUM(D91:O91) -> 2220 | Q91: =OPEX!Q34 -> 400 | R91: =OPEX!R34 -> 400 | S91: =OPEX!S34 -> 400 | T91: =OPEX!T34 -> 520 | U91: =OPEX!U34 -> 600 | V91: =OPEX!V34 -> 600 | W91: =OPEX!W34 -> 600 | X91: =OPEX!X34 -> 600 | ... AB91: =OPEX!AB34 -> 670 | AC91: =SUM(Q91:AB91) -> 6750 | AD91: =OPEX!AD34 -> 960 | AE91: =OPEX!AE34 -> 960 | AF91: =OPEX!AF34 -> 960 | AG91: =OPEX!AG34 -> 1070 | AH91: =OPEX!AH34 -> 1070 | AI91: =OPEX!AI34 -> 1070 | AJ91: =OPEX!AJ34 -> 1070 | AK91: =OPEX!AK34 -> 1070 | ... AO91: =OPEX!AO34 -> 1190 | AP91: =SUM(AD91:AO91) -> 12870
A92: =ROW() -> 92 | B92: =OPEX!B35 -> Overige personeelskosten (3%) | D92: =OPEX!D35 -> 84.24 | E92: =OPEX!E35 -> 84.24 | F92: =OPEX!F35 -> 84.24 | G92: =OPEX!G35 -> 84.24 | H92: =OPEX!H35 -> 84.24 | I92: =OPEX!I35 -> 84.24 | J92: =OPEX!J35 -> 664.2 | K92: =OPEX!K35 -> 664.2 | ... O92: =OPEX!O35 -> 722.52 | P92: =SUM(D92:O92) -> 4723.92 | Q92: =OPEX!Q35 -> 997.8228 | R92: =OPEX!R35 -> 997.8228 | S92: =OPEX!S35 -> 997.8228 | T92: =OPEX!T35 -> 1331.5428 | U92: =OPEX!U35 -> 1478.3796 | V92: =OPEX!V35 -> 1478.3796 | W92: =OPEX!W35 -> 1478.3796 | X92: =OPEX!X35 -> 1478.3796 | ... AB92: =OPEX!AB35 -> 1645.2396 | AC92: =SUM(Q92:AB92) -> 16652.628 | AD92: =OPEX!AD35 -> 2295.9936 | AE92: =OPEX!AE35 -> 2295.9936 | AF92: =OPEX!AF35 -> 2295.9936 | AG92: =OPEX!AG35 -> 2649.7368 | AH92: =OPEX!AH35 -> 2649.7368 | AI92: =OPEX!AI35 -> 2649.7368 | AJ92: =OPEX!AJ35 -> 2649.7368 | AK92: =OPEX!AK35 -> 2649.7368 | ... AO92: =OPEX!AO35 -> 2906.7012 | AP92: =SUM(AD92:AO92) -> 31506.505
A93: =ROW() -> 93 | B93: =OPEX!B36 -> Autokosten | D93: =OPEX!D36 -> 1080 | E93: =OPEX!E36 -> 1080 | F93: =OPEX!F36 -> 1080 | G93: =OPEX!G36 -> 1080 | H93: =OPEX!H36 -> 1080 | I93: =OPEX!I36 -> 1080 | J93: =OPEX!J36 -> 2960 | K93: =OPEX!K36 -> 2960 | ... O93: =OPEX!O36 -> 3080 | P93: =SUM(D93:O93) -> 24720 | Q93: =OPEX!Q36 -> 4440 | R93: =OPEX!R36 -> 4440 | S93: =OPEX!S36 -> 4440 | T93: =OPEX!T36 -> 5950 | U93: =OPEX!U36 -> 6770 | V93: =OPEX!V36 -> 6770 | W93: =OPEX!W36 -> 6770 | X93: =OPEX!X36 -> 6770 | ... AB93: =OPEX!AB36 -> 7430 | AC93: =SUM(Q93:AB93) -> 75610 | AD93: =OPEX!AD36 -> 10780 | AE93: =OPEX!AE36 -> 10780 | AF93: =OPEX!AF36 -> 10780 | AG93: =OPEX!AG36 -> 12190 | AH93: =OPEX!AH36 -> 12190 | AI93: =OPEX!AI36 -> 12190 | AJ93: =OPEX!AJ36 -> 12190 | AK93: =OPEX!AK36 -> 12190 | ... AO93: =OPEX!AO36 -> 13650 | AP93: =SUM(AD93:AO93) -> 146430
A94: =ROW() -> 94 | B94: =OPEX!B37 -> Brandstof | D94: =OPEX!D37 -> 220 | E94: =OPEX!E37 -> 220 | F94: =OPEX!F37 -> 220 | G94: =OPEX!G37 -> 220 | H94: =OPEX!H37 -> 220 | I94: =OPEX!I37 -> 220 | J94: =OPEX!J37 -> 550 | K94: =OPEX!K37 -> 550 | ... O94: =OPEX!O37 -> 550 | P94: =SUM(D94:O94) -> 4620 | Q94: =OPEX!Q37 -> 770 | R94: =OPEX!R37 -> 770 | S94: =OPEX!S37 -> 770 | T94: =OPEX!T37 -> 1040 | U94: =OPEX!U37 -> 1180 | V94: =OPEX!V37 -> 1180 | W94: =OPEX!W37 -> 1180 | X94: =OPEX!X37 -> 1180 | ... AB94: =OPEX!AB37 -> 1280 | AC94: =SUM(Q94:AB94) -> 13130 | AD94: =OPEX!AD37 -> 1880 | AE94: =OPEX!AE37 -> 1880 | AF94: =OPEX!AF37 -> 1880 | AG94: =OPEX!AG37 -> 2130 | AH94: =OPEX!AH37 -> 2130 | AI94: =OPEX!AI37 -> 2130 | AJ94: =OPEX!AJ37 -> 2130 | AK94: =OPEX!AK37 -> 2130 | ... AO94: =OPEX!AO37 -> 2400 | AP94: =SUM(AD94:AO94) -> 25620
A95: =ROW() -> 95 | B95: =OPEX!B38 -> Managementfee | D95: =OPEX!D38 -> 8000 | E95: =OPEX!E38 -> 8000 | F95: =OPEX!F38 -> 8000 | G95: =OPEX!G38 -> 8000 | H95: =OPEX!H38 -> 8000 | I95: =OPEX!I38 -> 8000 | J95: =OPEX!J38 -> 8000 | K95: =OPEX!K38 -> 8000 | ... O95: =OPEX!O38 -> 8000 | P95: =SUM(D95:O95) -> 96000 | Q95: =OPEX!Q38 -> 13000 | R95: =OPEX!R38 -> 13000 | S95: =OPEX!S38 -> 13000 | T95: =OPEX!T38 -> 16000 | U95: =OPEX!U38 -> 20000 | V95: =OPEX!V38 -> 20000 | W95: =OPEX!W38 -> 20000 | X95: =OPEX!X38 -> 20000 | ... AB95: =OPEX!AB38 -> 22000 | AC95: =SUM(Q95:AB95) -> 223000 | AD95: =OPEX!AD38 -> 34000 | AE95: =OPEX!AE38 -> 34000 | AF95: =OPEX!AF38 -> 34000 | AG95: =OPEX!AG38 -> 36000 | AH95: =OPEX!AH38 -> 36000 | AI95: =OPEX!AI38 -> 36000 | AJ95: =OPEX!AJ38 -> 36000 | AK95: =OPEX!AK38 -> 36000 | ... AO95: =OPEX!AO38 -> 42000 | AP95: =SUM(AD95:AO95) -> 444000
A96: =ROW() -> 96 | B96: Totaal personeelskosten | C96: =SUM(C86:C95) -> 0 | D96: =SUM(D86:D95) -> 13933.127 | E96: =SUM(E86:E95) -> 13933.127 | F96: =SUM(F86:F95) -> 13933.127 | G96: =SUM(G86:G95) -> 13933.127 | H96: =SUM(H86:H95) -> 13933.127 | I96: =SUM(I86:I95) -> 13933.127 | J96: =SUM(J86:J95) -> 42912.217 | ... O96: =SUM(O86:O95) -> 45738.997 | P96: =SUM(D96:O96) -> 352379.18 | Q96: =SUM(Q86:Q95) -> 65524.052 | R96: =SUM(R86:R95) -> 65524.052 | S96: =SUM(S86:S95) -> 65524.052 | T96: =SUM(T86:T95) -> 85998.682 | U96: =SUM(U86:U95) -> 98121.553 | V96: =SUM(V86:V95) -> 98121.553 | W96: =SUM(W86:W95) -> 98121.553 | X96: =SUM(X86:X95) -> 98121.553 | ... AB96: =SUM(AB86:AB95) -> 108781.78 | AC96: =SUM(Q96:AB96) -> 1101955.6 | AD96: =SUM(AD86:AD95) -> 155920.19 | AE96: =SUM(AE86:AE95) -> 155920.19 | AF96: =SUM(AF86:AF95) -> 155920.19 | AG96: =SUM(AG86:AG95) -> 176098.01 | AH96: =SUM(AH86:AH95) -> 176098.01 | AI96: =SUM(AI86:AI95) -> 176098.01 | AJ96: =SUM(AJ86:AJ95) -> 176098.01 | AK96: =SUM(AK86:AK95) -> 176098.01 | ... AO96: =SUM(AO86:AO95) -> 196257.2 | AP96: =SUM(AD96:AO96) -> 2113120.2
A97: =ROW() -> 97
A98: =ROW() -> 98 | B98: Overige bedrijfskosten
A99: =ROW() -> 99 | B99: =OPEX!B41 -> Huisvesting | D99: =OPEX!D41 -> 2200 | E99: =OPEX!E41 -> 2200 | F99: =OPEX!F41 -> 2200 | G99: =OPEX!G41 -> 2200 | H99: =OPEX!H41 -> 2200 | I99: =OPEX!I41 -> 2200 | J99: =OPEX!J41 -> 3850 | K99: =OPEX!K41 -> 3850 | ... O99: =OPEX!O41 -> 3850 | P99: =SUM(D99:O99) -> 36300 | Q99: =OPEX!Q41 -> 3965.5 | R99: =OPEX!R41 -> 3965.5 | S99: =OPEX!S41 -> 3965.5 | T99: =OPEX!T41 -> 3965.5 | U99: =OPEX!U41 -> 3965.5 | V99: =OPEX!V41 -> 7700 | W99: =OPEX!W41 -> 7700 | X99: =OPEX!X41 -> 7700 | ... AB99: =OPEX!AB41 -> 7700 | AC99: =SUM(Q99:AB99) -> 73727.5 | AD99: =OPEX!AD41 -> 11231 | AE99: =OPEX!AE41 -> 11231 | AF99: =OPEX!AF41 -> 11231 | AG99: =OPEX!AG41 -> 11231 | AH99: =OPEX!AH41 -> 11231 | AI99: =OPEX!AI41 -> 11231 | AJ99: =OPEX!AJ41 -> 11231 | AK99: =OPEX!AK41 -> 11231 | ... AO99: =OPEX!AO41 -> 11231 | AP99: =SUM(AD99:AO99) -> 134772
A100: =ROW() -> 100 | B100: =OPEX!B45 -> Algemene kosten | C100: 15000 | D100: =OPEX!D45 -> 1475 | E100: =OPEX!E45 -> 1475 | F100: =OPEX!F45 -> 1475 | G100: =OPEX!G45 -> 1475 | H100: =OPEX!H45 -> 1475 | I100: =OPEX!I45 -> 1475 | J100: =OPEX!J45 -> 1475 | K100: =OPEX!K45 -> 1475 | ... O100: =OPEX!O45 -> 1475 | P100: =SUM(D100:O100) -> 17700 | Q100: =OPEX!Q45 -> 3038.5 | R100: =OPEX!R45 -> 3038.5 | S100: =OPEX!S45 -> 3038.5 | T100: =OPEX!T45 -> 3038.5 | U100: =OPEX!U45 -> 3038.5 | V100: =OPEX!V45 -> 3038.5 | W100: =OPEX!W45 -> 3038.5 | X100: =OPEX!X45 -> 3038.5 | ... AB100: =OPEX!AB45 -> 3038.5 | AC100: =SUM(Q100:AB100) -> 36462 | AD100: =OPEX!AD45 -> 6259.31 | AE100: =OPEX!AE45 -> 6259.31 | AF100: =OPEX!AF45 -> 6259.31 | AG100: =OPEX!AG45 -> 6259.31 | AH100: =OPEX!AH45 -> 6259.31 | AI100: =OPEX!AI45 -> 6259.31 | AJ100: =OPEX!AJ45 -> 6259.31 | AK100: =OPEX!AK45 -> 6259.31 | ... AO100: =OPEX!AO45 -> 6259.31 | AP100: =SUM(AD100:AO100) -> 75111.72
...

Sheet Propositie
B2: Propositie: | C2: Fractional C-Suite + Execution Platform voor purpose-gedreven startups en scale-ups.
B4: Veel founders groeien snel maar missen een sterke finance en operations backbone.
B5: Wij bouwen en runnen je volledige backoffice, finance, HR en commerciële infrastructuur, zodat jij je volledig kunt focussen op groei.
B6: Niet als consultant
B7: Niet als interim
B8: Maar als strategisch operator-partner, van strategie tot executeren
B11: Wanneer ondernemers starten en snel groeien ontstaan uitdagingen:
B13: Finance structuur (strakke processen en administratie)
B14: Cashflow controle
B15: HR structuur
B16: Sales structuur
B17: Organisatiestructuur
B18: Governance
... B38: 2: Operating infrastructure
B39: Finance stack: | F39: Commercial stack: | J39: Operations stack: | N39: HR stack:
B40: AFAS | F40: Hubspot CRM | J40: KPI dashboards | N40: AFAS
B41: Forecasting & Budgetting | F41: sales funnel | J41: interne processen | N41: hiring
B42: Management reporting | F42: marketing funnel | N42: payroll
B43: Finance & business control | N43: HR management
B44: Risk management
B45: Controle framework
B47: 3: Execution & Ownership
B49: We bouwen vanuit de klantstrategie de backbone van de onderneming en laten dit meegroeien met de levensfase van de onderneming
B50: Maar dat is niet alles
B51: We runnen finance, HR, en brengen structuur aan in sales, marketing en operations. Sturen bij waar nodig en zijn actief betrokken als c-level partners.
B54: Waardepropositie vanuit de klant
B56: ✔ Volledige controle over hun cashflow
B57: ✔ Professionele finance structuur
B58: ✔ Schaalbare operationele backbone
B59: ✔ Sales en marketing structuur
B60: ✔ Strategische C-level begeleiding
... B67: rust + controle + versnelling

Sheet Ideale klant
B2: Ideale klantprofiel
B4: 0-100 medewerkers
B5: 0-20m omzet
B6: geen volledig c-level team
B7: founder-led, skin in the game
B8: funding of bootstrap met runway
B9: sterke groeiambitie
B10: onder de rivieren
B11: seed (0-1 jaar)
B12: early (1-2 jaar)
B13: product-market fit (2-5 jaar)
B14: scale up (5-10 jaar)
... B25: agencies

Sheet Pakketten
B2: Foundation | J2: Growth | R2: Scale
B3: Prijs | C3: 6750 | J3: Prijs | K3: 17000 | R3: Prijs | S3: 27000
B4: Startups 2-10 FTE | C4: 0 - 3m bruto-omzet | J4: Startups 10-30 FTE | K4: 1 - 8m bruto-omzet | R4: Startups 30-100 FTE | S4: 6 - 25m bruto-omzet
B5: Typologie bedrijven: Dienstverlening (zonder goederenbeweging), Urencapaciteit, Productiebedrijven, Handelsbedrijven | J5: Typologie bedrijven: Dienstverlening (zonder goederenbeweging), Urencapaciteit, Productiebedrijven, Handelsbedrijven | R5: Typologie bedrijven: Dienstverlening (zonder goederenbeweging), Urencapaciteit, Productiebedrijven, Handelsbedrijven
B6: Voorbeeld: Projectorganisaties, Consultancy, Advies, Software, MSP, Productie, Energie | J6: Voorbeeld: Projectorganisaties, Consultancy, Advies, Software, MSP, Productie, Energie | R6: Voorbeeld: Projectorganisaties, Consultancy, Advies, Software, MSP, Productie, Energie
B8: Maandelijkse inzet | C8: Uren | D8: Tarief KP | E8: Kosten | G8: blendded rate | J8: Maandelijkse inzet | K8: Uren | L8: Tarief KP | M8: Kosten | O8: blendded rate | R8: Maandelijkse inzet | S8: Uren | T8: Tarief KP | U8: Kosten | W8: blendded rate
B10: - CEO (C-level) | C10: 4 | D10: =VLOOKUP($B10,OPEX!$B$2:$Q$12,16,FALSE) -> 91 | E10: =C10*D10 -> 364 | J10: - CEO (C-level) | K10: =C10*2 -> 8 | L10: =VLOOKUP($J10,OPEX!$B$2:$Q$12,16,FALSE) -> 91 | M10: =K10*L10 -> 728 | R10: - CEO (C-level) | S10: =K10*2 -> 16 | T10: =VLOOKUP($R10,OPEX!$B$2:$Q$12,16,FALSE) -> 91 | U10: =S10*T10 -> 1456
B11: - CFO (C-level) | C11: 8 | D11: =VLOOKUP($B11,OPEX!$B$2:$Q$12,16,FALSE) -> 91 | E11: =C11*D11 -> 728 | J11: - CFO (C-level) | K11: =C11*2 -> 16 | L11: =VLOOKUP($J11,OPEX!$B$2:$Q$12,16,FALSE) -> 91 | M11: =K11*L11 -> 1456 | R11: - CFO (C-level) | S11: =K11*2 -> 32 | T11: =VLOOKUP($R11,OPEX!$B$2:$Q$12,16,FALSE) -> 91 | U11: =S11*T11 -> 2912
B12: - CMO (Senior-level) | C12: 6 | D12: =VLOOKUP($B12,OPEX!$B$2:$Q$12,16,FALSE) -> 95.157 | E12: =C12*D12 -> 570.942 | J12: - CMO (Senior-level) | K12: =C12*4 -> 24 | L12: =VLOOKUP($J12,OPEX!$B$2:$Q$12,16,FALSE) -> 95.157 | M12: =K12*L12 -> 2283.768 | R12: - CMO (Senior-level) | S12: =K12*1.5 -> 36 | T12: =VLOOKUP($R12,OPEX!$B$2:$Q$12,16,FALSE) -> 95.157 | U12: =S12*T12 -> 3425.652
B13: - CTO (Senior-level) | C13: 6 | D13: =VLOOKUP($B13,OPEX!$B$2:$Q$12,16,FALSE) -> 95.157 | E13: =C13*D13 -> 570.942 | J13: - CTO (Senior-level) | K13: =C13*4 -> 24 | L13: =VLOOKUP($J13,OPEX!$B$2:$Q$12,16,FALSE) -> 95.157 | M13: =K13*L13 -> 2283.768 | R13: - CTO (Senior-level) | S13: =K13*1.5 -> 36 | T13: =VLOOKUP($R13,OPEX!$B$2:$Q$12,16,FALSE) -> 95.157 | U13: =S13*T13 -> 3425.652
B14: - HR partner (Senior-level) | C14: 8 | D14: =VLOOKUP($B14,OPEX!$B$2:$Q$12,16,FALSE) -> 62.42625 | E14: =C14*D14 -> 499.41 | J14: - HR partner (Senior-level) | K14: =C14*3 -> 24 | L14: =VLOOKUP($J14,OPEX!$B$2:$Q$12,16,FALSE) -> 62.42625 | M14: =K14*L14 -> 1498.23 | R14: - HR partner (Senior-level) | S14: =K14*1.5 -> 36 | T14: =VLOOKUP($R14,OPEX!$B$2:$Q$12,16,FALSE) -> 62.42625 | U14: =S14*T14 -> 2247.345
B15: - Finance admin (Sedior-level) | C15: 12 | D15: =VLOOKUP($B15,OPEX!$B$2:$Q$12,16,FALSE) -> 77.666625 | E15: =C15*D15 -> 931.9995 | J15: - Finance admin (Sedior-level) | K15: =C15*1.5 -> 18 | L15: =VLOOKUP($J15,OPEX!$B$2:$Q$12,16,FALSE) -> 77.666625 | M15: =K15*L15 -> 1397.9992 | R15: - Finance admin (Sedior-level) | S15: 24 | T15: =VLOOKUP($R15,OPEX!$B$2:$Q$12,16,FALSE) -> 77.666625 | U15: =S15*T15 -> 1863.999
B16: - HR admin (Medior-level) | C16: 0 | D16: =VLOOKUP($B16,OPEX!$B$2:$Q$12,16,FALSE) -> 50.391 | E16: =C16*D16 -> 0 | J16: - HR admin (Medior-level) | K16: 8 | L16: =VLOOKUP($J16,OPEX!$B$2:$Q$12,16,FALSE) -> 50.391 | M16: =K16*L16 -> 403.128 | R16: - HR admin (Medior-level) | S16: =K16*2 -> 16 | T16: =VLOOKUP($R16,OPEX!$B$2:$Q$12,16,FALSE) -> 50.391 | U16: =S16*T16 -> 806.256
B17: - Backoffice support (Junior-level) | C17: 20 | D17: =VLOOKUP($B17,OPEX!$B$2:$Q$12,16,FALSE) -> 34.60575 | E17: =C17*D17 -> 692.115 | J17: - Backoffice support (Junior-level) | K17: =C17*1.5 -> 30 | L17: =VLOOKUP($J17,OPEX!$B$2:$Q$12,16,FALSE) -> 34.60575 | M17: =K17*L17 -> 1038.1725 | R17: - Backoffice support (Junior-level) | S17: =K17*2 -> 60 | T17: =VLOOKUP($R17,OPEX!$B$2:$Q$12,16,FALSE) -> 34.60575 | U17: =S17*T17 -> 2076.345
B18: - Data engineer (Medior-level) | C18: 0 | D18: =VLOOKUP($B18,OPEX!$B$2:$Q$12,16,FALSE) -> 50.971125 | E18: =C18*D18 -> 0 | J18: - Data engineer (Medior-level) | K18: 4 | L18: =VLOOKUP($J18,OPEX!$B$2:$Q$12,16,FALSE) -> 50.971125 | M18: =K18*L18 -> 203.8845 | R18: - Data engineer (Medior-level) | S18: 8 | T18: =VLOOKUP($R18,OPEX!$B$2:$Q$12,16,FALSE) -> 50.971125
C19: =SUM(C12:C16) -> 32 | E19: =SUM(E10:E18) -> 4357.4085 | G19: =E19/C19 -> 136.16902 | K19: =SUM(K12:K18) -> 132 | M19: =SUM(M10:M18) -> 11292.95 | O19: =M19/K19 -> 85.552653 | S19: =SUM(S12:S17) -> 208 | U19: =SUM(U10:U18) -> 18213.249 | W19: =U19/S19 -> 87.563697
B21: Software | J21: Software | R21: Software
B22: AFAS | C22: 1 | D22: 300 | E22: =C22*D22 -> 300 | J22: AFAS | K22: 1 | L22: 300 | M22: =K22*L22 -> 300 | R22: AFAS | S22: 1 | T22: 300 | U22: =S22*T22 -> 300
B23: AFAS licenties | C23: 10 | D23: 30 | E23: =C23*D23 -> 300 | J23: AFAS licenties | K23: 30 | L23: 30 | M23: =K23*L23 -> 900 | R23: AFAS licenties | S23: 75 | T23: 30 | U23: =S23*T23 -> 2250
B24: Hubspot | C24: 1 | D24: 350 | E24: =C24*D24 -> 350 | J24: Hubspot | K24: 2 | L24: 350 | M24: =K24*L24 -> 700 | R24: Hubspot | S24: 2 | T24: 350 | U24: =S24*T24 -> 700
E25: =SUM(E22:E24) -> 950 | M25: =SUM(M22:M24) -> 1900 | U25: =SUM(U22:U24) -> 3250
B27: Totaal | E27: =E19+E25 -> 5307.4085 | J27: Totaal | M27: =M19+M25 -> 13192.95 | R27: Totaal | U27: =U19+U25 -> 21463.249
B28: Overhead (25%) | D28: 0.25 | E28: =D28*E27 -> 1326.8521 | J28: Overhead (25%) | L28: 0.25 | M28: =L28*M27 -> 3298.2376 | R28: Overhead (25%) | T28: 0.25 | U28: =T28*U27 -> 5365.8122
B30: Totaal inclusief overhead | E30: =E27+E28 -> 6634.2606 | J30: Totaal inclusief overhead | M30: =M27+M28 -> 16491.188 | R30: Totaal inclusief overhead | U30: =U27+U28 -> 26829.061
B32: Marge | E32: =C3-E30 -> 115.73938 | J32: Marge | M32: =K3-M30 -> 508.81219 | R32: Marge | U32: =S3-U30 -> 170.93875
B33: Marge% | E33: =E32/C3 -> 0.017146574 | J33: Marge% | M33: =M32/K3 -> 0.029930129 | R33: Marge% | U33: =U32/S3 -> 0.0063310648
B36: Add-ons | J36: Add-ons | R36: Add-ons
B37: - API koppelingen | J37: - API koppelingen | R37: - API koppelingen
B38: - MS stack | J38: - MS stack | R38: - MS stack
B39: - DaaS | J39: - DaaS | R39: - DaaS
B40: - Data platform en dashboarding | J40: - Data platform en dashboarding | R40: - Data platform en dashboarding
B41: - IT beheer | J41: - IT beheer | R41: - IT beheer
B45: Deliverables | J45: Deliverables | R45: Deliverables
B46: - Modern en altijd up-to-date ingerichte backbone, IT omgeving en administratie gebaseerd op AFAS & Hubspot | J46: - Modern en altijd up-to-date ingerichte backbone, IT omgeving en administratie gebaseerd op AFAS & Hubspot | R46: - Modern en altijd up-to-date ingerichte backbone, IT omgeving en administratie gebaseerd op AFAS & Hubspot
B47: - Professionele, effectief en efficiente processen voor finance, HR, sales en eventueel met marketing, payroll, projecten + ordermanagement | J47: - Professionele, effectief en efficiente processen voor finance, HR, sales en eventueel met marketing, payroll, projecten + ordermanagement | R47: - Professionele, effectief en efficiente processen voor finance, HR, sales en eventueel met marketing, payroll, projecten + ordermanagement
B48: - Financiele administratie optioneel salarisadministratie, projectadministratie, voorraadadministratie | J48: - Dashboarding en KPIs | R48: - Dashboarding en KPIs
B49: - Maandafsluiting en rapportage | J49: - Financiele administratie optioneel salarisadministratie, projectadministratie, voorraadadministratie | R49: - Financiele administratie optioneel salarisadministratie, projectadministratie, voorraadadministratie
B50: - Forecast & Budget inclusief cash forecast | J50: - Maandafsluiting en rapportages | R50: - Maandafsluiting en rapportages
... B55: - AV sessies (max 4x per jaar) | J55: - On- en offboarding medewerkers | R55: - On- en offboarding medewerkers
J56: - AV sessies (max 4x per jaar) | R56: - AV sessies (max 4x per jaar)
B59: Aanvullende diensten op projectbasis of uitbesteden aan partners (voorbeelden)
B60: - Transformation en change trajecten
B61: - M&A en corporate finance trajecten
B62: - Accountantswerkzaamheden (samenstel jaarrekening en VPB). Wordt uitbesteed aan externe accountant.
B63: - Controle werkzaamheden accountancy
B64: - Certificering trajecten
B65: - IT en werkplekbeheer. Kan worden uitbesteed aan partner
B66: - Vlootschouw en arbeidsvoorwaarden benchmark
B67: - Fulltime interim
B68: - Sales & Marketing strategie
B69: - Branding
B72: Opstartfee
... B75: - Data migratie optioneel

Sheet OPEX
N1: =2080 -> 2080 | O1: 1600
B2: Personeelskosten | C2: FTE | D2: Management fee | E2: Brutosalaris | F2: Vakantiegeld | G2: Bonus | H2: Pensioen | I2: Soc. Lasten | J2: Auto, vergoeding | K2: Brandstof | L2: Overige onkosten | M2: Totaal | N2: Uren per maand | O2: Werkbare declarabele uren per maand | P2: Uurloon | Q2: Uurloon werkbaar
B4: - CEO (C-level) | C4: 1 | D4: 10000 | G4: =D4/12 -> 833.33333 | J4: 1000 | K4: 200 | L4: 100 | M4: =SUM(D4:L4) -> 12133.333 | N4: =N$1/12 -> 173.33333 | O4: =O$1/12 -> 133.33333 | P4: =M4/N4 -> 70 | Q4: =M4/O4 -> 91
B5: - CFO (C-level) | C5: 1 | D5: 10000 | G5: =D5/12 -> 833.33333 | J5: 1000 | K5: 200 | L5: 100 | M5: =SUM(D5:L5) -> 12133.333 | N5: =N$1/12 -> 173.33333 | O5: =O$1/12 -> 133.33333 | P5: =M5/N5 -> 70 | Q5: =M5/O5 -> 91
B6: - CMO (Senior-level) | C6: 1 | E6: 8000 | F6: =E6*0.08 -> 640 | G6: =E6*1/12 -> 666.66667 | H6: =0.08*E6 -> 640 | I6: =0.17*SUM(E6:H6) -> 1690.9333 | J6: 850 | K6: 150 | L6: 50 | M6: =SUM(D6:L6) -> 12687.6 | N6: =N$1/12 -> 173.33333 | O6: =O$1/12 -> 133.33333 | P6: =M6/N6 -> 73.197692 | Q6: =M6/O6 -> 95.157
B7: - CTO (Senior-level) | C7: 1 | E7: 8000 | F7: =E7*0.08 -> 640 | G7: =E7*1/12 -> 666.66667 | H7: =0.08*E7 -> 640 | I7: =0.17*SUM(E7:H7) -> 1690.9333 | J7: 850 | K7: 150 | L7: 50 | M7: =SUM(D7:L7) -> 12687.6 | N7: =N$1/12 -> 173.33333 | O7: =O$1/12 -> 133.33333 | P7: =M7/N7 -> 73.197692 | Q7: =M7/O7 -> 95.157
B8: - HR partner (Senior-level) | C8: 1 | E8: 5000 | F8: =E8*0.08 -> 400 | G8: =E8*1/12 -> 416.66667 | H8: =0.08*E8 -> 400 | I8: =0.17*SUM(E8:H8) -> 1056.8333 | J8: 850 | K8: 150 | L8: 50 | M8: =SUM(D8:L8) -> 8323.5 | N8: =N$1/12 -> 173.33333 | O8: =O$1/12 -> 133.33333 | P8: =M8/N8 -> 48.020192 | Q8: =M8/O8 -> 62.42625
B9: - Finance admin (Sedior-level) | C9: 1 | E9: 6500 | F9: =E9*0.08 -> 520 | G9: =E9*1/12 -> 541.66667 | H9: =0.08*E9 -> 520 | I9: =0.17*SUM(E9:H9) -> 1373.8833 | J9: 700 | K9: 150 | L9: 50 | M9: =SUM(D9:L9) -> 10355.55 | N9: =N$1/12 -> 173.33333 | O9: =O$1/12 -> 133.33333 | P9: =M9/N9 -> 59.743558 | Q9: =M9/O9 -> 77.666625
B10: - HR admin (Medior-level) | C10: 1 | E10: 4000 | F10: =E10*0.08 -> 320 | G10: =E10*1/12 -> 333.33333 | H10: =0.08*E10 -> 320 | I10: =0.17*SUM(E10:H10) -> 845.46667 | J10: 700 | K10: 150 | L10: 50 | M10: =SUM(D10:L10) -> 6718.8 | N10: =N$1/12 -> 173.33333 | O10: =O$1/12 -> 133.33333 | P10: =M10/N10 -> 38.762308 | Q10: =M10/O10 -> 50.391
B11: - Backoffice support (Junior-level) | C11: 1 | E11: 3000 | F11: =E11*0.08 -> 240 | G11: =E11*1/12 -> 250 | H11: =0.08*E11 -> 240 | I11: =0.17*SUM(E11:H11) -> 634.1 | J11: 200 | L11: 50 | M11: =SUM(D11:L11) -> 4614.1 | N11: =N$1/12 -> 173.33333 | O11: =O$1/12 -> 133.33333 | P11: =M11/N11 -> 26.619808 | Q11: =M11/O11 -> 34.60575
B12: - Data engineer (Medior-level) | C12: 1 | E12: 4500 | F12: =E12*0.08 -> 360 | G12: =E12*1/12 -> 375 | H12: =0.08*E12 -> 360 | I12: =0.17*SUM(E12:H12) -> 951.15 | J12: 200 | L12: 50 | M12: =SUM(D12:L12) -> 6796.15 | N12: =N$1/12 -> 173.33333 | O12: =O$1/12 -> 133.33333 | P12: =M12/N12 -> 39.208558 | Q12: =M12/O12 -> 50.971125
D13: =SUM(D4:D12) -> 20000 | E13: =SUM(E4:E12) -> 39000 | F13: =SUM(F4:F12) -> 3120 | G13: =SUM(G4:G12) -> 4916.6667 | H13: =SUM(H4:H12) -> 3120 | I13: =SUM(I4:I12) -> 8243.3 | J13: =SUM(J4:J12) -> 6350 | K13: =SUM(K4:K12) -> 1150 | ... M13: =SUM(M4:M12) -> 86449.967
D15: 2026-01 | E15: 2026-02 | F15: 2026-03 | G15: 2026-04 | H15: 2026-05 | I15: 2026-06 | J15: 2026-07 | K15: 2026-08 | L15: 2026-09 | M15: 2026-10 | N15: 2026-11 | O15: 2026-12 | Q15: 2027-01 | R15: 2027-02 | S15: 2027-03 | T15: 2027-04 | U15: 2027-05 | V15: 2027-06 | W15: 2027-07 | X15: 2027-08 | Y15: 2027-09 | Z15: 2027-10 | AA15: 2027-11 | AB15: 2027-12 | AD15: 2027-01 | AE15: 2027-02 | AF15: 2027-03 | AG15: 2027-04 | AH15: 2027-05 | AI15: 2027-06 | AJ15: 2027-07 | AK15: 2027-08 | AL15: 2027-09 | AM15: 2027-10 | AN15: 2027-11 | AO15: 2027-12
B17: - CEO (C-level) | D17: 0.2 | E17: 0.2 | F17: 0.2 | G17: 0.2 | H17: 0.2 | I17: 0.2 | J17: 0.2 | K17: 0.2 | L17: 0.2 | M17: 0.2 | N17: 0.2 | O17: 0.2 | Q17: =RFF!Q20 -> 0.5 | R17: =RFF!R20 -> 0.5 | S17: =RFF!S20 -> 0.5 | T17: =RFF!T20 -> 0.6 | U17: =RFF!U20 -> 0.6 | V17: =RFF!V20 -> 0.6 | W17: =RFF!W20 -> 0.6 | X17: =RFF!X20 -> 0.6 | ... AB17: =RFF!AB20 -> 0.8 | AD17: =RFF!AD20 -> 1.4 | AE17: =RFF!AE20 -> 1.4 | AF17: =RFF!AF20 -> 1.4 | AG17: =RFF!AG20 -> 1.4 | AH17: =RFF!AH20 -> 1.4 | AI17: =RFF!AI20 -> 1.4 | AJ17: =RFF!AJ20 -> 1.4 | AK17: =RFF!AK20 -> 1.4 | ... AO17: =RFF!AO20 -> 1.6
B18: - CFO (C-level) | D18: 0.6 | E18: 0.6 | F18: 0.6 | G18: 0.6 | H18: 0.6 | I18: 0.6 | J18: 0.6 | K18: 0.6 | L18: 0.6 | M18: 0.6 | N18: 0.6 | O18: 0.6 | Q18: =RFF!Q21 -> 0.8 | R18: =RFF!R21 -> 0.8 | S18: =RFF!S21 -> 0.8 | T18: =RFF!T21 -> 1 | U18: =RFF!U21 -> 1.4 | V18: =RFF!V21 -> 1.4 | W18: =RFF!W21 -> 1.4 | X18: =RFF!X21 -> 1.4 | ... AB18: =RFF!AB21 -> 1.4 | AD18: =RFF!AD21 -> 2 | AE18: =RFF!AE21 -> 2 | AF18: =RFF!AF21 -> 2 | AG18: =RFF!AG21 -> 2.2 | AH18: =RFF!AH21 -> 2.2 | AI18: =RFF!AI21 -> 2.2 | AJ18: =RFF!AJ21 -> 2.2 | AK18: =RFF!AK21 -> 2.2 | ... AO18: =RFF!AO21 -> 2.6
B19: - CMO (Senior-level) | J19: 0.4 | K19: 0.4 | L19: 0.4 | M19: 0.4 | N19: 0.4 | O19: 0.4 | Q19: =RFF!Q22 -> 0.8 | R19: =RFF!R22 -> 0.8 | S19: =RFF!S22 -> 0.8 | T19: =RFF!T22 -> 1 | U19: =RFF!U22 -> 1.2 | V19: =RFF!V22 -> 1.2 | W19: =RFF!W22 -> 1.2 | X19: =RFF!X22 -> 1.2 | ... AB19: =RFF!AB22 -> 1.4 | AD19: =RFF!AD22 -> 2 | AE19: =RFF!AE22 -> 2 | AF19: =RFF!AF22 -> 2 | AG19: =RFF!AG22 -> 2.2 | AH19: =RFF!AH22 -> 2.2 | AI19: =RFF!AI22 -> 2.2 | AJ19: =RFF!AJ22 -> 2.2 | AK19: =RFF!AK22 -> 2.2 | ... AO19: =RFF!AO22 -> 2.6
B20: - CTO (Senior-level) | J20: 0.4 | K20: 0.4 | L20: 0.4 | M20: 0.4 | N20: 0.4 | O20: 0.4 | Q20: =RFF!Q23 -> 0.8 | R20: =RFF!R23 -> 0.8 | S20: =RFF!S23 -> 0.8 | T20: =RFF!T23 -> 1 | U20: =RFF!U23 -> 1.2 | V20: =RFF!V23 -> 1.2 | W20: =RFF!W23 -> 1.2 | X20: =RFF!X23 -> 1.2 | ... AB20: =RFF!AB23 -> 1.4 | AD20: =RFF!AD23 -> 2 | AE20: =RFF!AE23 -> 2 | AF20: =RFF!AF23 -> 2 | AG20: =RFF!AG23 -> 2.4 | AH20: =RFF!AH23 -> 2.4 | AI20: =RFF!AI23 -> 2.4 | AJ20: =RFF!AJ23 -> 2.4 | AK20: =RFF!AK23 -> 2.4 | ... AO20: =RFF!AO23 -> 2.6
B21: - HR partner (Senior-level) | J21: 0.4 | K21: 0.4 | L21: 0.4 | M21: 0.4 | N21: 0.4 | O21: 0.4 | Q21: =RFF!Q24 -> 0.8 | R21: =RFF!R24 -> 0.8 | S21: =RFF!S24 -> 0.8 | T21: =RFF!T24 -> 1.4 | U21: =RFF!U24 -> 1.4 | V21: =RFF!V24 -> 1.4 | W21: =RFF!W24 -> 1.4 | X21: =RFF!X24 -> 1.4 | ... AB21: =RFF!AB24 -> 1.4 | AD21: =RFF!AD24 -> 2 | AE21: =RFF!AE24 -> 2 | AF21: =RFF!AF24 -> 2 | AG21: =RFF!AG24 -> 2.4 | AH21: =RFF!AH24 -> 2.4 | AI21: =RFF!AI24 -> 2.4 | AJ21: =RFF!AJ24 -> 2.4 | AK21: =RFF!AK24 -> 2.4 | ... AO21: =RFF!AO24 -> 2.6
B22: - Finance admin (Sedior-level) | D22: 0.4 | E22: 0.4 | F22: 0.4 | G22: 0.4 | H22: 0.4 | I22: 0.4 | J22: 1.4 | K22: 1.4 | L22: 1.4 | M22: 1.4 | N22: 1.4 | O22: 1.4 | Q22: =RFF!Q25 -> 1 | R22: =RFF!R25 -> 1 | S22: =RFF!S25 -> 1 | T22: =RFF!T25 -> 1.4 | U22: =RFF!U25 -> 1.4 | V22: =RFF!V25 -> 1.4 | W22: =RFF!W25 -> 1.4 | X22: =RFF!X25 -> 1.4 | ... AB22: =RFF!AB25 -> 1.4 | AD22: =RFF!AD25 -> 2 | AE22: =RFF!AE25 -> 2 | AF22: =RFF!AF25 -> 2 | AG22: =RFF!AG25 -> 2.4 | AH22: =RFF!AH25 -> 2.4 | AI22: =RFF!AI25 -> 2.4 | AJ22: =RFF!AJ25 -> 2.4 | AK22: =RFF!AK25 -> 2.4 | ... AO22: =RFF!AO25 -> 2.6
B23: - HR admin (Medior-level) | Q23: =RFF!Q26 -> 0 | R23: =RFF!R26 -> 0 | S23: =RFF!S26 -> 0 | T23: =RFF!T26 -> 0 | U23: =RFF!U26 -> 0 | V23: =RFF!V26 -> 0 | W23: =RFF!W26 -> 0 | X23: =RFF!X26 -> 0 | ... AB23: =RFF!AB26 -> 0 | AD23: =RFF!AD26 -> 0 | AE23: =RFF!AE26 -> 0 | AF23: =RFF!AF26 -> 0 | AG23: =RFF!AG26 -> 0 | AH23: =RFF!AH26 -> 0 | AI23: =RFF!AI26 -> 0 | AJ23: =RFF!AJ26 -> 0 | AK23: =RFF!AK26 -> 0 | ... AO23: =RFF!AO26 -> 0
B24: - Backoffice support (Junior-level) | J24: 0.4 | K24: 0.4 | L24: 1 | M24: 1 | N24: 1 | O24: 1 | Q24: =RFF!Q27 -> 1.6 | R24: =RFF!R27 -> 1.6 | S24: =RFF!S27 -> 1.6 | T24: =RFF!T27 -> 2 | U24: =RFF!U27 -> 2.4 | V24: =RFF!V27 -> 2.4 | W24: =RFF!W27 -> 2.4 | X24: =RFF!X27 -> 2.4 | ... AB24: =RFF!AB27 -> 3 | AD24: =RFF!AD27 -> 4 | AE24: =RFF!AE27 -> 4 | AF24: =RFF!AF27 -> 4 | AG24: =RFF!AG27 -> 4.4 | AH24: =RFF!AH27 -> 4.4 | AI24: =RFF!AI27 -> 4.4 | AJ24: =RFF!AJ27 -> 4.4 | AK24: =RFF!AK27 -> 4.4 | ... AO24: =RFF!AO27 -> 4.6
B25: - Data engineer (Medior-level) | J25: 0.4 | K25: 0.4 | L25: 0.4 | M25: 0.4 | N25: 0.4 | O25: 0.4 | Q25: =RFF!Q28 -> 0.4 | R25: =RFF!R28 -> 0.4 | S25: =RFF!S28 -> 0.4 | T25: =RFF!T28 -> 0.4 | U25: =RFF!U28 -> 0.4 | V25: =RFF!V28 -> 0.4 | W25: =RFF!W28 -> 0.4 | X25: =RFF!X28 -> 0.4 | ... AB25: =RFF!AB28 -> 0.4 | AD25: =RFF!AD28 -> 0.4 | AE25: =RFF!AE28 -> 0.4 | AF25: =RFF!AF28 -> 0.4 | AG25: =RFF!AG28 -> 0.4 | AH25: =RFF!AH28 -> 0.4 | AI25: =RFF!AI28 -> 0.4 | AJ25: =RFF!AJ28 -> 0.4 | AK25: =RFF!AK28 -> 0.4 | ... AO25: =RFF!AO28 -> 0.4
B28: Personeelskosten | D28: =SUM(D29:D38) -> 13933.127 | E28: =SUM(E29:E38) -> 13933.127 | F28: =SUM(F29:F38) -> 13933.127 | G28: =SUM(G29:G38) -> 13933.127 | H28: =SUM(H29:H38) -> 13933.127 | I28: =SUM(I29:I38) -> 13933.127 | J28: =SUM(J29:J38) -> 42912.217 | K28: =SUM(K29:K38) -> 42912.217 | ... O28: =SUM(O29:O38) -> 45738.997 | Q28: =SUM(Q29:Q38) -> 65524.052 | R28: =SUM(R29:R38) -> 65524.052 | S28: =SUM(S29:S38) -> 65524.052 | T28: =SUM(T29:T38) -> 85998.682 | U28: =SUM(U29:U38) -> 98121.553 | V28: =SUM(V29:V38) -> 98121.553 | W28: =SUM(W29:W38) -> 98121.553 | X28: =SUM(X29:X38) -> 98121.553 | ... AB28: =SUM(AB29:AB38) -> 108781.78 | AD28: =SUM(AD29:AD38) -> 155920.19 | AE28: =SUM(AE29:AE38) -> 155920.19 | AF28: =SUM(AF29:AF38) -> 155920.19 | AG28: =SUM(AG29:AG38) -> 176098.01 | AH28: =SUM(AH29:AH38) -> 176098.01 | AI28: =SUM(AI29:AI38) -> 176098.01 | AJ28: =SUM(AJ29:AJ38) -> 176098.01 | AK28: =SUM(AK29:AK38) -> 176098.01 | ... AO28: =SUM(AO29:AO38) -> 196257.2
B29: Brutosalarissen | D29: =SUMPRODUCT(D$17:D$25,$E4:$E12) -> 2600 | E29: =SUMPRODUCT(E$17:E$25,$E4:$E12) -> 2600 | F29: =SUMPRODUCT(F$17:F$25,$E4:$E12) -> 2600 | G29: =SUMPRODUCT(G$17:G$25,$E4:$E12) -> 2600 | H29: =SUMPRODUCT(H$17:H$25,$E4:$E12) -> 2600 | I29: =SUMPRODUCT(I$17:I$25,$E4:$E12) -> 2600 | J29: =SUMPRODUCT(J$17:J$25,$E4:$E12) -> 20500 | K29: =SUMPRODUCT(K$17:K$25,$E4:$E12) -> 20500 | ... O29: =SUMPRODUCT(O$17:O$25,$E4:$E12) -> 22300 | Q29: =SUMPRODUCT(Q$17:Q$25,$E4:$E12)*1.03 -> 30797 | R29: =SUMPRODUCT(R$17:R$25,$E4:$E12)*1.03 -> 30797 | S29: =SUMPRODUCT(S$17:S$25,$E4:$E12)*1.03 -> 30797 | T29: =SUMPRODUCT(T$17:T$25,$E4:$E12)*1.03 -> 41097 | U29: =SUMPRODUCT(U$17:U$25,$E4:$E12)*1.03 -> 45629 | V29: =SUMPRODUCT(V$17:V$25,$E4:$E12)*1.03 -> 45629 | W29: =SUMPRODUCT(W$17:W$25,$E4:$E12)*1.03 -> 45629 | X29: =SUMPRODUCT(X$17:X$25,$E4:$E12)*1.03 -> 45629 | ... AB29: =SUMPRODUCT(AB$17:AB$25,$E4:$E12)*1.03 -> 50779 | AD29: =SUMPRODUCT(AD$17:AD$25,$E4:$E12)*1.03 -> 70864 | AE29: =SUMPRODUCT(AE$17:AE$25,$E4:$E12)*1.03 -> 70864 | AF29: =SUMPRODUCT(AF$17:AF$25,$E4:$E12)*1.03 -> 70864 | AG29: =SUMPRODUCT(AG$17:AG$25,$E4:$E12)*1.03 -> 81782 | AH29: =SUMPRODUCT(AH$17:AH$25,$E4:$E12)*1.03 -> 81782 | AI29: =SUMPRODUCT(AI$17:AI$25,$E4:$E12)*1.03 -> 81782 | AJ29: =SUMPRODUCT(AJ$17:AJ$25,$E4:$E12)*1.03 -> 81782 | AK29: =SUMPRODUCT(AK$17:AK$25,$E4:$E12)*1.03 -> 81782 | ... AO29: =SUMPRODUCT(AO$17:AO$25,$E4:$E12)*1.03 -> 89713
B30: Vakantiegeld | D30: =SUMPRODUCT(D$17:D$25,$F4:$F12) -> 208 | E30: =SUMPRODUCT(E$17:E$25,$F4:$F12) -> 208 | F30: =SUMPRODUCT(F$17:F$25,$F4:$F12) -> 208 | G30: =SUMPRODUCT(G$17:G$25,$F4:$F12) -> 208 | H30: =SUMPRODUCT(H$17:H$25,$F4:$F12) -> 208 | I30: =SUMPRODUCT(I$17:I$25,$F4:$F12) -> 208 | J30: =SUMPRODUCT(J$17:J$25,$F4:$F12) -> 1640 | K30: =SUMPRODUCT(K$17:K$25,$F4:$F12) -> 1640 | ... O30: =SUMPRODUCT(O$17:O$25,$F4:$F12) -> 1784 | Q30: =SUMPRODUCT(Q$17:Q$25,$F4:$F12)*1.03 -> 2463.76 | R30: =SUMPRODUCT(R$17:R$25,$F4:$F12)*1.03 -> 2463.76 | S30: =SUMPRODUCT(S$17:S$25,$F4:$F12)*1.03 -> 2463.76 | T30: =SUMPRODUCT(T$17:T$25,$F4:$F12)*1.03 -> 3287.76 | U30: =SUMPRODUCT(U$17:U$25,$F4:$F12)*1.03 -> 3650.32 | V30: =SUMPRODUCT(V$17:V$25,$F4:$F12)*1.03 -> 3650.32 | W30: =SUMPRODUCT(W$17:W$25,$F4:$F12)*1.03 -> 3650.32 | X30: =SUMPRODUCT(X$17:X$25,$F4:$F12)*1.03 -> 3650.32 | ... AB30: =SUMPRODUCT(AB$17:AB$25,$F4:$F12)*1.03 -> 4062.32 | AD30: =SUMPRODUCT(AD$17:AD$25,$F4:$F12)*1.03 -> 5669.12 | AE30: =SUMPRODUCT(AE$17:AE$25,$F4:$F12)*1.03 -> 5669.12 | AF30: =SUMPRODUCT(AF$17:AF$25,$F4:$F12)*1.03 -> 5669.12 | AG30: =SUMPRODUCT(AG$17:AG$25,$F4:$F12)*1.03 -> 6542.56 | AH30: =SUMPRODUCT(AH$17:AH$25,$F4:$F12)*1.03 -> 6542.56 | AI30: =SUMPRODUCT(AI$17:AI$25,$F4:$F12)*1.03 -> 6542.56 | AJ30: =SUMPRODUCT(AJ$17:AJ$25,$F4:$F12)*1.03 -> 6542.56 | AK30: =SUMPRODUCT(AK$17:AK$25,$F4:$F12)*1.03 -> 6542.56 | ... AO30: =SUMPRODUCT(AO$17:AO$25,$F4:$F12)*1.03 -> 7177.04
B31: Bonussen | D31: =SUMPRODUCT(D$17:D$25,$G4:$G12) -> 883.33333 | E31: =SUMPRODUCT(E$17:E$25,$G4:$G12) -> 883.33333 | F31: =SUMPRODUCT(F$17:F$25,$G4:$G12) -> 883.33333 | G31: =SUMPRODUCT(G$17:G$25,$G4:$G12) -> 883.33333 | H31: =SUMPRODUCT(H$17:H$25,$G4:$G12) -> 883.33333 | I31: =SUMPRODUCT(I$17:I$25,$G4:$G12) -> 883.33333 | J31: =SUMPRODUCT(J$17:J$25,$G4:$G12) -> 2375 | K31: =SUMPRODUCT(K$17:K$25,$G4:$G12) -> 2375 | ... O31: =SUMPRODUCT(O$17:O$25,$G4:$G12) -> 2525 | Q31: =SUMPRODUCT(Q$17:Q$25,$G4:$G12)*1.03 -> 3682.25 | R31: =SUMPRODUCT(R$17:R$25,$G4:$G12)*1.03 -> 3682.25 | S31: =SUMPRODUCT(S$17:S$25,$G4:$G12)*1.03 -> 3682.25 | T31: =SUMPRODUCT(T$17:T$25,$G4:$G12)*1.03 -> 4798.0833 | U31: =SUMPRODUCT(U$17:U$25,$G4:$G12)*1.03 -> 5519.0833 | V31: =SUMPRODUCT(V$17:V$25,$G4:$G12)*1.03 -> 5519.0833 | W31: =SUMPRODUCT(W$17:W$25,$G4:$G12)*1.03 -> 5519.0833 | X31: =SUMPRODUCT(X$17:X$25,$G4:$G12)*1.03 -> 5519.0833 | ... AB31: =SUMPRODUCT(AB$17:AB$25,$G4:$G12)*1.03 -> 6119.9167 | AD31: =SUMPRODUCT(AD$17:AD$25,$G4:$G12)*1.03 -> 8823.6667 | AE31: =SUMPRODUCT(AE$17:AE$25,$G4:$G12)*1.03 -> 8823.6667 | AF31: =SUMPRODUCT(AF$17:AF$25,$G4:$G12)*1.03 -> 8823.6667 | AG31: =SUMPRODUCT(AG$17:AG$25,$G4:$G12)*1.03 -> 9905.1667 | AH31: =SUMPRODUCT(AH$17:AH$25,$G4:$G12)*1.03 -> 9905.1667 | AI31: =SUMPRODUCT(AI$17:AI$25,$G4:$G12)*1.03 -> 9905.1667 | AJ31: =SUMPRODUCT(AJ$17:AJ$25,$G4:$G12)*1.03 -> 9905.1667 | AK31: =SUMPRODUCT(AK$17:AK$25,$G4:$G12)*1.03 -> 9905.1667 | ... AO31: =SUMPRODUCT(AO$17:AO$25,$G4:$G12)*1.03 -> 11081.083
B32: Pensioen | D32: =SUMPRODUCT(D$17:D$25,$H4:$H12) -> 208 | E32: =SUMPRODUCT(E$17:E$25,$H4:$H12) -> 208 | F32: =SUMPRODUCT(F$17:F$25,$H4:$H12) -> 208 | G32: =SUMPRODUCT(G$17:G$25,$H4:$H12) -> 208 | H32: =SUMPRODUCT(H$17:H$25,$H4:$H12) -> 208 | I32: =SUMPRODUCT(I$17:I$25,$H4:$H12) -> 208 | J32: =SUMPRODUCT(J$17:J$25,$H4:$H12) -> 1640 | K32: =SUMPRODUCT(K$17:K$25,$H4:$H12) -> 1640 | ... O32: =SUMPRODUCT(O$17:O$25,$H4:$H12) -> 1784 | Q32: =SUMPRODUCT(Q$17:Q$25,$H4:$H12)*1.03 -> 2463.76 | R32: =SUMPRODUCT(R$17:R$25,$H4:$H12)*1.03 -> 2463.76 | S32: =SUMPRODUCT(S$17:S$25,$H4:$H12)*1.03 -> 2463.76 | T32: =SUMPRODUCT(T$17:T$25,$H4:$H12)*1.03 -> 3287.76 | U32: =SUMPRODUCT(U$17:U$25,$H4:$H12)*1.03 -> 3650.32 | V32: =SUMPRODUCT(V$17:V$25,$H4:$H12)*1.03 -> 3650.32 | W32: =SUMPRODUCT(W$17:W$25,$H4:$H12)*1.03 -> 3650.32 | X32: =SUMPRODUCT(X$17:X$25,$H4:$H12)*1.03 -> 3650.32 | ... AB32: =SUMPRODUCT(AB$17:AB$25,$H4:$H12)*1.03 -> 4062.32 | AD32: =SUMPRODUCT(AD$17:AD$25,$H4:$H12)*1.03 -> 5669.12 | AE32: =SUMPRODUCT(AE$17:AE$25,$H4:$H12)*1.03 -> 5669.12 | AF32: =SUMPRODUCT(AF$17:AF$25,$H4:$H12)*1.03 -> 5669.12 | AG32: =SUMPRODUCT(AG$17:AG$25,$H4:$H12)*1.03 -> 6542.56 | AH32: =SUMPRODUCT(AH$17:AH$25,$H4:$H12)*1.03 -> 6542.56 | AI32: =SUMPRODUCT(AI$17:AI$25,$H4:$H12)*1.03 -> 6542.56 | AJ32: =SUMPRODUCT(AJ$17:AJ$25,$H4:$H12)*1.03 -> 6542.56 | AK32: =SUMPRODUCT(AK$17:AK$25,$H4:$H12)*1.03 -> 6542.56 | ... AO32: =SUMPRODUCT(AO$17:AO$25,$H4:$H12)*1.03 -> 7177.04
B33: Soc. Lasten | D33: =SUMPRODUCT(D$17:D$25,$I4:$I12) -> 549.55333 | E33: =SUMPRODUCT(E$17:E$25,$I4:$I12) -> 549.55333 | F33: =SUMPRODUCT(F$17:F$25,$I4:$I12) -> 549.55333 | G33: =SUMPRODUCT(G$17:G$25,$I4:$I12) -> 549.55333 | H33: =SUMPRODUCT(H$17:H$25,$I4:$I12) -> 549.55333 | I33: =SUMPRODUCT(I$17:I$25,$I4:$I12) -> 549.55333 | J33: =SUMPRODUCT(J$17:J$25,$I4:$I12) -> 4333.0167 | K33: =SUMPRODUCT(K$17:K$25,$I4:$I12) -> 4333.0167 | ... O33: =SUMPRODUCT(O$17:O$25,$I4:$I12) -> 4713.4767 | Q33: =SUMPRODUCT(Q$17:Q$25,$I4:$I12)*1.03 -> 6509.4592 | R33: =SUMPRODUCT(R$17:R$25,$I4:$I12)*1.03 -> 6509.4592 | S33: =SUMPRODUCT(S$17:S$25,$I4:$I12)*1.03 -> 6509.4592 | T33: =SUMPRODUCT(T$17:T$25,$I4:$I12)*1.03 -> 8686.5359 | U33: =SUMPRODUCT(U$17:U$25,$I4:$I12)*1.03 -> 9644.4496 | V33: =SUMPRODUCT(V$17:V$25,$I4:$I12)*1.03 -> 9644.4496 | W33: =SUMPRODUCT(W$17:W$25,$I4:$I12)*1.03 -> 9644.4496 | X33: =SUMPRODUCT(X$17:X$25,$I4:$I12)*1.03 -> 9644.4496 | ... AB33: =SUMPRODUCT(AB$17:AB$25,$I4:$I12)*1.03 -> 10732.988 | AD33: =SUMPRODUCT(AD$17:AD$25,$I4:$I12)*1.03 -> 14978.287 | AE33: =SUMPRODUCT(AE$17:AE$25,$I4:$I12)*1.03 -> 14978.287 | AF33: =SUMPRODUCT(AF$17:AF$25,$I4:$I12)*1.03 -> 14978.287 | AG33: =SUMPRODUCT(AG$17:AG$25,$I4:$I12)*1.03 -> 17285.989 | AH33: =SUMPRODUCT(AH$17:AH$25,$I4:$I12)*1.03 -> 17285.989 | AI33: =SUMPRODUCT(AI$17:AI$25,$I4:$I12)*1.03 -> 17285.989 | AJ33: =SUMPRODUCT(AJ$17:AJ$25,$I4:$I12)*1.03 -> 17285.989 | AK33: =SUMPRODUCT(AK$17:AK$25,$I4:$I12)*1.03 -> 17285.989 | ... AO33: =SUMPRODUCT(AO$17:AO$25,$I4:$I12)*1.03 -> 18962.338
B34: Vergoedingen | D34: =SUMPRODUCT(D$17:D$25,$L4:$L12) -> 100 | E34: =SUMPRODUCT(E$17:E$25,$L4:$L12) -> 100 | F34: =SUMPRODUCT(F$17:F$25,$L4:$L12) -> 100 | G34: =SUMPRODUCT(G$17:G$25,$L4:$L12) -> 100 | H34: =SUMPRODUCT(H$17:H$25,$L4:$L12) -> 100 | I34: =SUMPRODUCT(I$17:I$25,$L4:$L12) -> 100 | J34: =SUMPRODUCT(J$17:J$25,$L4:$L12) -> 250 | K34: =SUMPRODUCT(K$17:K$25,$L4:$L12) -> 250 | ... O34: =SUMPRODUCT(O$17:O$25,$L4:$L12) -> 280 | Q34: =SUMPRODUCT(Q$17:Q$25,$L4:$L12) -> 400 | R34: =SUMPRODUCT(R$17:R$25,$L4:$L12) -> 400 | S34: =SUMPRODUCT(S$17:S$25,$L4:$L12) -> 400 | T34: =SUMPRODUCT(T$17:T$25,$L4:$L12) -> 520 | U34: =SUMPRODUCT(U$17:U$25,$L4:$L12) -> 600 | V34: =SUMPRODUCT(V$17:V$25,$L4:$L12) -> 600 | W34: =SUMPRODUCT(W$17:W$25,$L4:$L12) -> 600 | X34: =SUMPRODUCT(X$17:X$25,$L4:$L12) -> 600 | ... AB34: =SUMPRODUCT(AB$17:AB$25,$L4:$L12) -> 670 | AD34: =SUMPRODUCT(AD$17:AD$25,$L4:$L12) -> 960 | AE34: =SUMPRODUCT(AE$17:AE$25,$L4:$L12) -> 960 | AF34: =SUMPRODUCT(AF$17:AF$25,$L4:$L12) -> 960 | AG34: =SUMPRODUCT(AG$17:AG$25,$L4:$L12) -> 1070 | AH34: =SUMPRODUCT(AH$17:AH$25,$L4:$L12) -> 1070 | AI34: =SUMPRODUCT(AI$17:AI$25,$L4:$L12) -> 1070 | AJ34: =SUMPRODUCT(AJ$17:AJ$25,$L4:$L12) -> 1070 | AK34: =SUMPRODUCT(AK$17:AK$25,$L4:$L12) -> 1070 | ... AO34: =SUMPRODUCT(AO$17:AO$25,$L4:$L12) -> 1190
B35: Overige personeelskosten (3%) | D35: =0.03*SUM(D29:D30) -> 84.24 | E35: =0.03*SUM(E29:E30) -> 84.24 | F35: =0.03*SUM(F29:F30) -> 84.24 | G35: =0.03*SUM(G29:G30) -> 84.24 | H35: =0.03*SUM(H29:H30) -> 84.24 | I35: =0.03*SUM(I29:I30) -> 84.24 | J35: =0.03*SUM(J29:J30) -> 664.2 | K35: =0.03*SUM(K29:K30) -> 664.2 | ... O35: =0.03*SUM(O29:O30) -> 722.52 | Q35: =0.03*SUM(Q29:Q30) -> 997.8228 | R35: =0.03*SUM(R29:R30) -> 997.8228 | S35: =0.03*SUM(S29:S30) -> 997.8228 | T35: =0.03*SUM(T29:T30) -> 1331.5428 | U35: =0.03*SUM(U29:U30) -> 1478.3796 | V35: =0.03*SUM(V29:V30) -> 1478.3796 | W35: =0.03*SUM(W29:W30) -> 1478.3796 | X35: =0.03*SUM(X29:X30) -> 1478.3796 | ... AB35: =0.03*SUM(AB29:AB30) -> 1645.2396 | AD35: =0.03*SUM(AD29:AD30) -> 2295.9936 | AE35: =0.03*SUM(AE29:AE30) -> 2295.9936 | AF35: =0.03*SUM(AF29:AF30) -> 2295.9936 | AG35: =0.03*SUM(AG29:AG30) -> 2649.7368 | AH35: =0.03*SUM(AH29:AH30) -> 2649.7368 | AI35: =0.03*SUM(AI29:AI30) -> 2649.7368 | AJ35: =0.03*SUM(AJ29:AJ30) -> 2649.7368 | AK35: =0.03*SUM(AK29:AK30) -> 2649.7368 | ... AO35: =0.03*SUM(AO29:AO30) -> 2906.7012
B36: Autokosten | D36: =SUMPRODUCT(D$17:D$25,$J4:$J12) -> 1080 | E36: =SUMPRODUCT(E$17:E$25,$J4:$J12) -> 1080 | F36: =SUMPRODUCT(F$17:F$25,$J4:$J12) -> 1080 | G36: =SUMPRODUCT(G$17:G$25,$J4:$J12) -> 1080 | H36: =SUMPRODUCT(H$17:H$25,$J4:$J12) -> 1080 | I36: =SUMPRODUCT(I$17:I$25,$J4:$J12) -> 1080 | J36: =SUMPRODUCT(J$17:J$25,$J4:$J12) -> 2960 | K36: =SUMPRODUCT(K$17:K$25,$J4:$J12) -> 2960 | ... O36: =SUMPRODUCT(O$17:O$25,$J4:$J12) -> 3080 | Q36: =SUMPRODUCT(Q$17:Q$25,$J4:$J12) -> 4440 | R36: =SUMPRODUCT(R$17:R$25,$J4:$J12) -> 4440 | S36: =SUMPRODUCT(S$17:S$25,$J4:$J12) -> 4440 | T36: =SUMPRODUCT(T$17:T$25,$J4:$J12) -> 5950 | U36: =SUMPRODUCT(U$17:U$25,$J4:$J12) -> 6770 | V36: =SUMPRODUCT(V$17:V$25,$J4:$J12) -> 6770 | W36: =SUMPRODUCT(W$17:W$25,$J4:$J12) -> 6770 | X36: =SUMPRODUCT(X$17:X$25,$J4:$J12) -> 6770 | ... AB36: =SUMPRODUCT(AB$17:AB$25,$J4:$J12) -> 7430 | AD36: =SUMPRODUCT(AD$17:AD$25,$J4:$J12) -> 10780 | AE36: =SUMPRODUCT(AE$17:AE$25,$J4:$J12) -> 10780 | AF36: =SUMPRODUCT(AF$17:AF$25,$J4:$J12) -> 10780 | AG36: =SUMPRODUCT(AG$17:AG$25,$J4:$J12) -> 12190 | AH36: =SUMPRODUCT(AH$17:AH$25,$J4:$J12) -> 12190 | AI36: =SUMPRODUCT(AI$17:AI$25,$J4:$J12) -> 12190 | AJ36: =SUMPRODUCT(AJ$17:AJ$25,$J4:$J12) -> 12190 | AK36: =SUMPRODUCT(AK$17:AK$25,$J4:$J12) -> 12190 | ... AO36: =SUMPRODUCT(AO$17:AO$25,$J4:$J12) -> 13650
B37: Brandstof | D37: =SUMPRODUCT(D$17:D$25,$K4:$K12) -> 220 | E37: =SUMPRODUCT(E$17:E$25,$K4:$K12) -> 220 | F37: =SUMPRODUCT(F$17:F$25,$K4:$K12) -> 220 | G37: =SUMPRODUCT(G$17:G$25,$K4:$K12) -> 220 | H37: =SUMPRODUCT(H$17:H$25,$K4:$K12) -> 220 | I37: =SUMPRODUCT(I$17:I$25,$K4:$K12) -> 220 | J37: =SUMPRODUCT(J$17:J$25,$K4:$K12) -> 550 | K37: =SUMPRODUCT(K$17:K$25,$K4:$K12) -> 550 | ... O37: =SUMPRODUCT(O$17:O$25,$K4:$K12) -> 550 | Q37: =SUMPRODUCT(Q$17:Q$25,$K4:$K12) -> 770 | R37: =SUMPRODUCT(R$17:R$25,$K4:$K12) -> 770 | S37: =SUMPRODUCT(S$17:S$25,$K4:$K12) -> 770 | T37: =SUMPRODUCT(T$17:T$25,$K4:$K12) -> 1040 | U37: =SUMPRODUCT(U$17:U$25,$K4:$K12) -> 1180 | V37: =SUMPRODUCT(V$17:V$25,$K4:$K12) -> 1180 | W37: =SUMPRODUCT(W$17:W$25,$K4:$K12) -> 1180 | X37: =SUMPRODUCT(X$17:X$25,$K4:$K12) -> 1180 | ... AB37: =SUMPRODUCT(AB$17:AB$25,$K4:$K12) -> 1280 | AD37: =SUMPRODUCT(AD$17:AD$25,$K4:$K12) -> 1880 | AE37: =SUMPRODUCT(AE$17:AE$25,$K4:$K12) -> 1880 | AF37: =SUMPRODUCT(AF$17:AF$25,$K4:$K12) -> 1880 | AG37: =SUMPRODUCT(AG$17:AG$25,$K4:$K12) -> 2130 | AH37: =SUMPRODUCT(AH$17:AH$25,$K4:$K12) -> 2130 | AI37: =SUMPRODUCT(AI$17:AI$25,$K4:$K12) -> 2130 | AJ37: =SUMPRODUCT(AJ$17:AJ$25,$K4:$K12) -> 2130 | AK37: =SUMPRODUCT(AK$17:AK$25,$K4:$K12) -> 2130 | ... AO37: =SUMPRODUCT(AO$17:AO$25,$K4:$K12) -> 2400
B38: Managementfee | D38: =SUMPRODUCT(D$17:D$25,$D4:$D12) -> 8000 | E38: =SUMPRODUCT(E$17:E$25,$D4:$D12) -> 8000 | F38: =SUMPRODUCT(F$17:F$25,$D4:$D12) -> 8000 | G38: =SUMPRODUCT(G$17:G$25,$D4:$D12) -> 8000 | H38: =SUMPRODUCT(H$17:H$25,$D4:$D12) -> 8000 | I38: =SUMPRODUCT(I$17:I$25,$D4:$D12) -> 8000 | J38: =SUMPRODUCT(J$17:J$25,$D4:$D12) -> 8000 | K38: =SUMPRODUCT(K$17:K$25,$D4:$D12) -> 8000 | ... O38: =SUMPRODUCT(O$17:O$25,$D4:$D12) -> 8000 | Q38: =SUMPRODUCT(Q$17:Q$25,$D4:$D12) -> 13000 | R38: =SUMPRODUCT(R$17:R$25,$D4:$D12) -> 13000 | S38: =SUMPRODUCT(S$17:S$25,$D4:$D12) -> 13000 | T38: =SUMPRODUCT(T$17:T$25,$D4:$D12) -> 16000 | U38: =SUMPRODUCT(U$17:U$25,$D4:$D12) -> 20000 | V38: =SUMPRODUCT(V$17:V$25,$D4:$D12) -> 20000 | W38: =SUMPRODUCT(W$17:W$25,$D4:$D12) -> 20000 | X38: =SUMPRODUCT(X$17:X$25,$D4:$D12) -> 20000 | ... AB38: =SUMPRODUCT(AB$17:AB$25,$D4:$D12) -> 22000 | AD38: =SUMPRODUCT(AD$17:AD$25,$D4:$D12) -> 34000 | AE38: =SUMPRODUCT(AE$17:AE$25,$D4:$D12) -> 34000 | AF38: =SUMPRODUCT(AF$17:AF$25,$D4:$D12) -> 34000 | AG38: =SUMPRODUCT(AG$17:AG$25,$D4:$D12) -> 36000 | AH38: =SUMPRODUCT(AH$17:AH$25,$D4:$D12) -> 36000 | AI38: =SUMPRODUCT(AI$17:AI$25,$D4:$D12) -> 36000 | AJ38: =SUMPRODUCT(AJ$17:AJ$25,$D4:$D12) -> 36000 | AK38: =SUMPRODUCT(AK$17:AK$25,$D4:$D12) -> 36000 | ... AO38: =SUMPRODUCT(AO$17:AO$25,$D4:$D12) -> 42000
B41: Huisvesting | D41: =SUM(D42:D43) -> 2200 | E41: =SUM(E42:E43) -> 2200 | F41: =SUM(F42:F43) -> 2200 | G41: =SUM(G42:G43) -> 2200 | H41: =SUM(H42:H43) -> 2200 | I41: =SUM(I42:I43) -> 2200 | J41: =SUM(J42:J43) -> 3850 | K41: =SUM(K42:K43) -> 3850 | ... O41: =SUM(O42:O43) -> 3850 | Q41: =SUM(Q42:Q43) -> 3965.5 | R41: =SUM(R42:R43) -> 3965.5 | S41: =SUM(S42:S43) -> 3965.5 | T41: =SUM(T42:T43) -> 3965.5 | U41: =SUM(U42:U43) -> 3965.5 | V41: =SUM(V42:V43) -> 7700 | W41: =SUM(W42:W43) -> 7700 | X41: =SUM(X42:X43) -> 7700 | ... AB41: =SUM(AB42:AB43) -> 7700 | AD41: =SUM(AD42:AD43) -> 11231 | AE41: =SUM(AE42:AE43) -> 11231 | AF41: =SUM(AF42:AF43) -> 11231 | AG41: =SUM(AG42:AG43) -> 11231 | AH41: =SUM(AH42:AH43) -> 11231 | AI41: =SUM(AI42:AI43) -> 11231 | AJ41: =SUM(AJ42:AJ43) -> 11231 | AK41: =SUM(AK42:AK43) -> 11231 | ... AO41: =SUM(AO42:AO43) -> 11231
B42: - Huur | D42: 2000 | E42: 2000 | F42: 2000 | G42: 2000 | H42: 2000 | I42: 2000 | J42: =I42+1500 -> 3500 | K42: =J42 -> 3500 | L42: =K42 -> 3500 | M42: =L42 -> 3500 | N42: =M42 -> 3500 | O42: =N42 -> 3500 | Q42: =O42*1.03 -> 3605 | R42: =Q42 -> 3605 | S42: =R42 -> 3605 | T42: =S42 -> 3605 | U42: =T42 -> 3605 | V42: =7000 -> 7000 | W42: =V42 -> 7000 | X42: =W42 -> 7000 | Y42: =X42 -> 7000 | Z42: =Y42 -> 7000 | AA42: =Z42 -> 7000 | AB42: =AA42 -> 7000 | AD42: =AB42*1.03+3000 -> 10210 | AE42: =AD42 -> 10210 | AF42: =AE42 -> 10210 | AG42: =AF42 -> 10210 | AH42: =AG42 -> 10210 | AI42: =AH42 -> 10210 | AJ42: =AI42 -> 10210 | AK42: =AJ42 -> 10210 | AL42: =AK42 -> 10210 | ... AO42: =AN42 -> 10210
B43: - Overige huisvesting | D43: =D42*0.1 -> 200 | E43: =E42*0.1 -> 200 | F43: =F42*0.1 -> 200 | G43: =G42*0.1 -> 200 | H43: =H42*0.1 -> 200 | I43: =I42*0.1 -> 200 | J43: =J42*0.1 -> 350 | K43: =K42*0.1 -> 350 | ... O43: =O42*0.1 -> 350 | Q43: =Q42*0.1 -> 360.5 | R43: =R42*0.1 -> 360.5 | S43: =S42*0.1 -> 360.5 | T43: =T42*0.1 -> 360.5 | U43: =U42*0.1 -> 360.5 | V43: =V42*0.1 -> 700 | W43: =W42*0.1 -> 700 | X43: =X42*0.1 -> 700 | ... AB43: =AB42*0.1 -> 700 | AD43: =AD42*0.1 -> 1021 | AE43: =AE42*0.1 -> 1021 | AF43: =AF42*0.1 -> 1021 | AG43: =AG42*0.1 -> 1021 | AH43: =AH42*0.1 -> 1021 | AI43: =AI42*0.1 -> 1021 | AJ43: =AJ42*0.1 -> 1021 | AK43: =AK42*0.1 -> 1021 | ... AO43: =AO42*0.1 -> 1021
B45: Algemene kosten | D45: =SUM(D46:D50) -> 1475 | E45: =SUM(E46:E50) -> 1475 | F45: =SUM(F46:F50) -> 1475 | G45: =SUM(G46:G50) -> 1475 | H45: =SUM(H46:H50) -> 1475 | I45: =SUM(I46:I50) -> 1475 | J45: =SUM(J46:J50) -> 1475 | K45: =SUM(K46:K50) -> 1475 | ... O45: =SUM(O46:O50) -> 1475 | Q45: =SUM(Q46:Q50) -> 3038.5 | R45: =SUM(R46:R50) -> 3038.5 | S45: =SUM(S46:S50) -> 3038.5 | T45: =SUM(T46:T50) -> 3038.5 | U45: =SUM(U46:U50) -> 3038.5 | V45: =SUM(V46:V50) -> 3038.5 | W45: =SUM(W46:W50) -> 3038.5 | X45: =SUM(X46:X50) -> 3038.5 | ... AB45: =SUM(AB46:AB50) -> 3038.5 | AD45: =SUM(AD46:AD50) -> 6259.31 | AE45: =SUM(AE46:AE50) -> 6259.31 | AF45: =SUM(AF46:AF50) -> 6259.31 | AG45: =SUM(AG46:AG50) -> 6259.31 | AH45: =SUM(AH46:AH50) -> 6259.31 | AI45: =SUM(AI46:AI50) -> 6259.31 | AJ45: =SUM(AJ46:AJ50) -> 6259.31 | AK45: =SUM(AK46:AK50) -> 6259.31 | ... AO45: =SUM(AO46:AO50) -> 6259.31
B46: - Verzekeringen | D46: =6000/12 -> 500 | E46: =6000/12 -> 500 | F46: =6000/12 -> 500 | G46: =6000/12 -> 500 | H46: =6000/12 -> 500 | I46: =6000/12 -> 500 | J46: =6000/12 -> 500 | K46: =6000/12 -> 500 | ... O46: =6000/12 -> 500 | Q46: =O46*1.03*2 -> 1030 | R46: =Q46 -> 1030 | S46: =R46 -> 1030 | T46: =S46 -> 1030 | U46: =T46 -> 1030 | V46: =U46 -> 1030 | W46: =V46 -> 1030 | X46: =W46 -> 1030 | Y46: =X46 -> 1030 | ... AB46: =AA46 -> 1030 | AD46: =AB46*1.03*2 -> 2121.8 | AE46: =AD46 -> 2121.8 | AF46: =AE46 -> 2121.8 | AG46: =AF46 -> 2121.8 | AH46: =AG46 -> 2121.8 | AI46: =AH46 -> 2121.8 | AJ46: =AI46 -> 2121.8 | AK46: =AJ46 -> 2121.8 | AL46: =AK46 -> 2121.8 | ... AO46: =AN46 -> 2121.8
B47: - Accountantskosten | D47: =3600/12 -> 300 | E47: =3600/12 -> 300 | F47: =3600/12 -> 300 | G47: =3600/12 -> 300 | H47: =3600/12 -> 300 | I47: =3600/12 -> 300 | J47: =3600/12 -> 300 | K47: =3600/12 -> 300 | ... O47: =3600/12 -> 300 | Q47: =O47*1.03*2 -> 618 | R47: =Q47 -> 618 | S47: =R47 -> 618 | T47: =S47 -> 618 | U47: =T47 -> 618 | V47: =U47 -> 618 | W47: =V47 -> 618 | X47: =W47 -> 618 | Y47: =X47 -> 618 | ... AB47: =AA47 -> 618 | AD47: =AB47*1.03*2 -> 1273.08 | AE47: =AD47 -> 1273.08 | AF47: =AE47 -> 1273.08 | AG47: =AF47 -> 1273.08 | AH47: =AG47 -> 1273.08 | AI47: =AH47 -> 1273.08 | AJ47: =AI47 -> 1273.08 | AK47: =AJ47 -> 1273.08 | AL47: =AK47 -> 1273.08 | ... AO47: =AN47 -> 1273.08
B48: - Juridische kosten | D48: =3600/12 -> 300 | E48: =3600/12 -> 300 | F48: =3600/12 -> 300 | G48: =3600/12 -> 300 | H48: =3600/12 -> 300 | I48: =3600/12 -> 300 | J48: =3600/12 -> 300 | K48: =3600/12 -> 300 | ... O48: =3600/12 -> 300 | Q48: =O48*1.03*2 -> 618 | R48: =Q48 -> 618 | S48: =R48 -> 618 | T48: =S48 -> 618 | U48: =T48 -> 618 | V48: =U48 -> 618 | W48: =V48 -> 618 | X48: =W48 -> 618 | Y48: =X48 -> 618 | ... AB48: =AA48 -> 618 | AD48: =AB48*1.03*2 -> 1273.08 | AE48: =AD48 -> 1273.08 | AF48: =AE48 -> 1273.08 | AG48: =AF48 -> 1273.08 | AH48: =AG48 -> 1273.08 | AI48: =AH48 -> 1273.08 | AJ48: =AI48 -> 1273.08 | AK48: =AJ48 -> 1273.08 | AL48: =AK48 -> 1273.08 | ... AO48: =AN48 -> 1273.08
B49: - Telefonie/Internet | D49: 100 | E49: 100 | F49: 100 | G49: 100 | H49: 100 | I49: 100 | J49: 100 | K49: 100 | L49: 100 | M49: 100 | N49: 100 | O49: 100 | Q49: =O49*1.03*2 -> 206 | R49: =Q49 -> 206 | S49: =R49 -> 206 | T49: =S49 -> 206 | U49: =T49 -> 206 | V49: =U49 -> 206 | W49: =V49 -> 206 | X49: =W49 -> 206 | Y49: =X49 -> 206 | ... AB49: =AA49 -> 206 | AD49: =AB49*1.03*2 -> 424.36 | AE49: =AD49 -> 424.36 | AF49: =AE49 -> 424.36 | AG49: =AF49 -> 424.36 | AH49: =AG49 -> 424.36 | AI49: =AH49 -> 424.36 | AJ49: =AI49 -> 424.36 | AK49: =AJ49 -> 424.36 | AL49: =AK49 -> 424.36 | ... AO49: =AN49 -> 424.36
B50: - Overige algemene kosten (25%) | D50: =0.25*SUM(D46:D48) -> 275 | E50: =0.25*SUM(E46:E48) -> 275 | F50: =0.25*SUM(F46:F48) -> 275 | G50: =0.25*SUM(G46:G48) -> 275 | H50: =0.25*SUM(H46:H48) -> 275 | I50: =0.25*SUM(I46:I48) -> 275 | J50: =0.25*SUM(J46:J48) -> 275 | K50: =0.25*SUM(K46:K48) -> 275 | ... O50: =0.25*SUM(O46:O48) -> 275 | Q50: =0.25*SUM(Q46:Q48) -> 566.5 | R50: =0.25*SUM(R46:R48) -> 566.5 | S50: =0.25*SUM(S46:S48) -> 566.5 | T50: =0.25*SUM(T46:T48) -> 566.5 | U50: =0.25*SUM(U46:U48) -> 566.5 | V50: =0.25*SUM(V46:V48) -> 566.5 | W50: =0.25*SUM(W46:W48) -> 566.5 | X50: =0.25*SUM(X46:X48) -> 566.5 | ... AB50: =0.25*SUM(AB46:AB48) -> 566.5 | AD50: =0.25*SUM(AD46:AD48) -> 1166.99 | AE50: =0.25*SUM(AE46:AE48) -> 1166.99 | AF50: =0.25*SUM(AF46:AF48) -> 1166.99 | AG50: =0.25*SUM(AG46:AG48) -> 1166.99 | AH50: =0.25*SUM(AH46:AH48) -> 1166.99 | AI50: =0.25*SUM(AI46:AI48) -> 1166.99 | AJ50: =0.25*SUM(AJ46:AJ48) -> 1166.99 | AK50: =0.25*SUM(AK46:AK48) -> 1166.99 | ... AO50: =0.25*SUM(AO46:AO48) -> 1166.99
B52: Marketing | D52: =SUM(D53:D59) -> 1521.6667 | E52: =SUM(E53:E59) -> 1521.6667 | F52: =SUM(F53:F59) -> 1521.6667 | G52: =SUM(G53:G59) -> 1521.6667 | H52: =SUM(H53:H59) -> 1521.6667 | I52: =SUM(I53:I59) -> 1521.6667 | J52: =SUM(J53:J59) -> 1521.6667 | K52: =SUM(K53:K59) -> 1521.6667 | ... O52: =SUM(O53:O59) -> 1521.6667 | Q52: =SUM(Q53:Q59) -> 3134.6333 | R52: =SUM(R53:R59) -> 3134.6333 | S52: =SUM(S53:S59) -> 3134.6333 | T52: =SUM(T53:T59) -> 3134.6333 | U52: =SUM(U53:U59) -> 3134.6333 | V52: =SUM(V53:V59) -> 3134.6333 | W52: =SUM(W53:W59) -> 3134.6333 | X52: =SUM(X53:X59) -> 3134.6333 | ... AB52: =SUM(AB53:AB59) -> 3134.6333 | AD52: =SUM(AD53:AD59) -> 7157.5387 | AE52: =SUM(AE53:AE59) -> 7157.5387 | AF52: =SUM(AF53:AF59) -> 7157.5387 | AG52: =SUM(AG53:AG59) -> 7157.5387 | AH52: =SUM(AH53:AH59) -> 7157.5387 | AI52: =SUM(AI53:AI59) -> 7157.5387 | AJ52: =SUM(AJ53:AJ59) -> 7157.5387 | AK52: =SUM(AK53:AK59) -> 7157.5387 | ... AO52: =SUM(AO53:AO59) -> 7157.5387
B53: - Website | D53: =200 -> 200 | E53: =200 -> 200 | F53: =200 -> 200 | G53: =200 -> 200 | H53: =200 -> 200 | I53: =200 -> 200 | J53: =200 -> 200 | K53: =200 -> 200 | ... O53: =200 -> 200 | Q53: =O53*1.03*2 -> 412 | R53: =Q53 -> 412 | S53: =R53 -> 412 | T53: =S53 -> 412 | U53: =T53 -> 412 | V53: =U53 -> 412 | W53: =V53 -> 412 | X53: =W53 -> 412 | Y53: =X53 -> 412 | ... AB53: =AA53 -> 412 | AD53: =AB53*1.03*2 -> 848.72 | AE53: =AD53 -> 848.72 | AF53: =AE53 -> 848.72 | AG53: =AF53 -> 848.72 | AH53: =AG53 -> 848.72 | AI53: =AH53 -> 848.72 | AJ53: =AI53 -> 848.72 | AK53: =AJ53 -> 848.72 | AL53: =AK53 -> 848.72 | ... AO53: =AN53 -> 848.72
B54: - Events | D54: =10000/12 -> 833.33333 | E54: =10000/12 -> 833.33333 | F54: =10000/12 -> 833.33333 | G54: =10000/12 -> 833.33333 | H54: =10000/12 -> 833.33333 | I54: =10000/12 -> 833.33333 | J54: =10000/12 -> 833.33333 | K54: =10000/12 -> 833.33333 | ... O54: =10000/12 -> 833.33333 | Q54: =O54*1.03*2 -> 1716.6667 | R54: =Q54 -> 1716.6667 | S54: =R54 -> 1716.6667 | T54: =S54 -> 1716.6667 | U54: =T54 -> 1716.6667 | V54: =U54 -> 1716.6667 | W54: =V54 -> 1716.6667 | X54: =W54 -> 1716.6667 | Y54: =X54 -> 1716.6667 | ... AB54: =AA54 -> 1716.6667 | AD54: =AB54*1.03*2 -> 3536.3333 | AE54: =AD54 -> 3536.3333 | AF54: =AE54 -> 3536.3333 | AG54: =AF54 -> 3536.3333 | AH54: =AG54 -> 3536.3333 | AI54: =AH54 -> 3536.3333 | AJ54: =AI54 -> 3536.3333 | AK54: =AJ54 -> 3536.3333 | AL54: =AK54 -> 3536.3333 | ... AO54: =AN54 -> 3536.3333
B55: - Advertentie | D55: =250 -> 250 | E55: =250 -> 250 | F55: =250 -> 250 | G55: =250 -> 250 | H55: =250 -> 250 | I55: =250 -> 250 | J55: =250 -> 250 | K55: =250 -> 250 | ... O55: =250 -> 250 | Q55: =O55*1.03*2 -> 515 | R55: =Q55 -> 515 | S55: =R55 -> 515 | T55: =S55 -> 515 | U55: =T55 -> 515 | V55: =U55 -> 515 | W55: =V55 -> 515 | X55: =W55 -> 515 | Y55: =X55 -> 515 | ... AB55: =AA55 -> 515 | AD55: =AB55*1.03*3 -> 1591.35 | AE55: =AD55 -> 1591.35 | AF55: =AE55 -> 1591.35 | AG55: =AF55 -> 1591.35 | AH55: =AG55 -> 1591.35 | AI55: =AH55 -> 1591.35 | AJ55: =AI55 -> 1591.35 | AK55: =AJ55 -> 1591.35 | AL55: =AK55 -> 1591.35 | ... AO55: =AN55 -> 1591.35
B56: - Relatiegeschenken | D56: =50 -> 50 | E56: =50 -> 50 | F56: =50 -> 50 | G56: =50 -> 50 | H56: =50 -> 50 | I56: =50 -> 50 | J56: =50 -> 50 | K56: =50 -> 50 | ... O56: =50 -> 50 | Q56: =O56*1.03*2 -> 103 | R56: =Q56 -> 103 | S56: =R56 -> 103 | T56: =S56 -> 103 | U56: =T56 -> 103 | V56: =U56 -> 103 | W56: =V56 -> 103 | X56: =W56 -> 103 | Y56: =X56 -> 103 | ... AB56: =AA56 -> 103 | AD56: =AB56*1.03*3 -> 318.27 | AE56: =AD56 -> 318.27 | AF56: =AE56 -> 318.27 | AG56: =AF56 -> 318.27 | AH56: =AG56 -> 318.27 | AI56: =AH56 -> 318.27 | AJ56: =AI56 -> 318.27 | AK56: =AJ56 -> 318.27 | AL56: =AK56 -> 318.27 | ... AO56: =AN56 -> 318.27
B57: - Online campagnes | D57: 50 | E57: 50 | F57: 50 | G57: 50 | H57: 50 | I57: 50 | J57: 50 | K57: 50 | L57: 50 | M57: 50 | N57: 50 | O57: 50 | Q57: =O57*1.03*2 -> 103 | R57: =Q57 -> 103 | S57: =R57 -> 103 | T57: =S57 -> 103 | U57: =T57 -> 103 | V57: =U57 -> 103 | W57: =V57 -> 103 | X57: =W57 -> 103 | Y57: =X57 -> 103 | ... AB57: =AA57 -> 103 | AD57: =AB57*1.03*2 -> 212.18 | AE57: =AD57 -> 212.18 | AF57: =AE57 -> 212.18 | AG57: =AF57 -> 212.18 | AH57: =AG57 -> 212.18 | AI57: =AH57 -> 212.18 | AJ57: =AI57 -> 212.18 | AK57: =AJ57 -> 212.18 | AL57: =AK57 -> 212.18 | ... AO57: =AN57 -> 212.18
B58: - Offline campagnes
B59: - Overige marketing (10%) | D59: =0.1*SUM(D53:D58) -> 138.33333 | E59: =0.1*SUM(E53:E58) -> 138.33333 | F59: =0.1*SUM(F53:F58) -> 138.33333 | G59: =0.1*SUM(G53:G58) -> 138.33333 | H59: =0.1*SUM(H53:H58) -> 138.33333 | I59: =0.1*SUM(I53:I58) -> 138.33333 | J59: =0.1*SUM(J53:J58) -> 138.33333 | K59: =0.1*SUM(K53:K58) -> 138.33333 | ... O59: =0.1*SUM(O53:O58) -> 138.33333 | Q59: =0.1*SUM(Q53:Q58) -> 284.96667 | R59: =0.1*SUM(R53:R58) -> 284.96667 | S59: =0.1*SUM(S53:S58) -> 284.96667 | T59: =0.1*SUM(T53:T58) -> 284.96667 | U59: =0.1*SUM(U53:U58) -> 284.96667 | V59: =0.1*SUM(V53:V58) -> 284.96667 | W59: =0.1*SUM(W53:W58) -> 284.96667 | X59: =0.1*SUM(X53:X58) -> 284.96667 | ... AB59: =0.1*SUM(AB53:AB58) -> 284.96667 | AD59: =0.1*SUM(AD53:AD58) -> 650.68533 | AE59: =0.1*SUM(AE53:AE58) -> 650.68533 | AF59: =0.1*SUM(AF53:AF58) -> 650.68533 | AG59: =0.1*SUM(AG53:AG58) -> 650.68533 | AH59: =0.1*SUM(AH53:AH58) -> 650.68533 | AI59: =0.1*SUM(AI53:AI58) -> 650.68533 | AJ59: =0.1*SUM(AJ53:AJ58) -> 650.68533 | AK59: =0.1*SUM(AK53:AK58) -> 650.68533 | ... AO59: =0.1*SUM(AO53:AO58) -> 650.68533
B61: Automatisering | D61: =SUM(D62:D70) -> 1650 | E61: =SUM(E62:E70) -> 1650 | F61: =SUM(F62:F70) -> 1650 | G61: =SUM(G62:G70) -> 1650 | H61: =SUM(H62:H70) -> 1650 | I61: =SUM(I62:I70) -> 1650 | J61: =SUM(J62:J70) -> 1980 | K61: =SUM(K62:K70) -> 1980 | ... O61: =SUM(O62:O70) -> 2046 | Q61: =SUM(Q62:Q70) -> 2590.665 | R61: =SUM(R62:R70) -> 2590.665 | S61: =SUM(S62:S70) -> 2590.665 | T61: =SUM(T62:T70) -> 2821.665 | U61: =SUM(U62:U70) -> 2953.665 | V61: =SUM(V62:V70) -> 2953.665 | W61: =SUM(W62:W70) -> 2953.665 | X61: =SUM(X62:X70) -> 2953.665 | ... AB61: =SUM(AB62:AB70) -> 3085.665 | AD61: =SUM(AD62:AD70) -> 3642.3249 | AE61: =SUM(AE62:AE70) -> 3642.3249 | AF61: =SUM(AF62:AF70) -> 3642.3249 | AG61: =SUM(AG62:AG70) -> 3862.3249 | AH61: =SUM(AH62:AH70) -> 3862.3249 | AI61: =SUM(AI62:AI70) -> 3862.3249 | AJ61: =SUM(AJ62:AJ70) -> 3862.3249 | AK61: =SUM(AK62:AK70) -> 3862.3249 | ... AO61: =SUM(AO62:AO70) -> 4060.3249
B62: - AFAS omgeving | C62: 1 | D62: =C62*300 -> 300 | E62: 300 | F62: 300 | G62: 300 | H62: 300 | I62: 300 | J62: 300 | K62: 300 | L62: 300 | M62: 300 | N62: 300 | O62: 300 | Q62: =O62*1.03 -> 309 | R62: =Q62 -> 309 | S62: =R62 -> 309 | T62: =S62 -> 309 | U62: =T62 -> 309 | V62: =U62 -> 309 | W62: =V62 -> 309 | X62: =W62 -> 309 | Y62: =X62 -> 309 | ... AB62: =AA62 -> 309 | AD62: =AB62*1.03 -> 318.27 | AE62: =AD62 -> 318.27 | AF62: =AE62 -> 318.27 | AG62: =AF62 -> 318.27 | AH62: =AG62 -> 318.27 | AI62: =AH62 -> 318.27 | AJ62: =AI62 -> 318.27 | AK62: =AJ62 -> 318.27 | AL62: =AK62 -> 318.27 | ... AO62: =AN62 -> 318.27
B63: - AFAS licenties | C63: 9 | D63: =C63*25 -> 225 | E63: =D63 -> 225 | F63: =E63 -> 225 | G63: =F63 -> 225 | H63: =G63 -> 225 | I63: =H63 -> 225 | J63: =I63 -> 225 | K63: =J63 -> 225 | L63: =K63 -> 225 | ... O63: =N63 -> 225 | Q63: =20*25 -> 500 | R63: =Q63 -> 500 | S63: =R63 -> 500 | T63: =S63 -> 500 | U63: =T63 -> 500 | V63: =U63 -> 500 | W63: =V63 -> 500 | X63: =W63 -> 500 | Y63: =X63 -> 500 | ... AB63: =AA63 -> 500 | AD63: =AB63*1.03 -> 515 | AE63: =AD63 -> 515 | AF63: =AE63 -> 515 | AG63: =AF63 -> 515 | AH63: =AG63 -> 515 | AI63: =AH63 -> 515 | AJ63: =AI63 -> 515 | AK63: =AJ63 -> 515 | AL63: =AK63 -> 515 | ... AO63: =AN63 -> 515
B64: - Hubspot omgeving | C64: 1 | D64: =C64*85 -> 85 | E64: =D64 -> 85 | F64: =E64 -> 85 | G64: =F64 -> 85 | H64: =G64 -> 85 | I64: =H64 -> 85 | J64: =I64 -> 85 | K64: =J64 -> 85 | L64: =K64 -> 85 | ... O64: =N64 -> 85 | Q64: =O64*1.03 -> 87.55 | R64: =Q64 -> 87.55 | S64: =R64 -> 87.55 | T64: =S64 -> 87.55 | U64: =T64 -> 87.55 | V64: =U64 -> 87.55 | W64: =V64 -> 87.55 | X64: =W64 -> 87.55 | Y64: =X64 -> 87.55 | ... AB64: =AA64 -> 87.55 | AD64: =AB64*1.03 -> 90.1765 | AE64: =AD64 -> 90.1765 | AF64: =AE64 -> 90.1765 | AG64: =AF64 -> 90.1765 | AH64: =AG64 -> 90.1765 | AI64: =AH64 -> 90.1765 | AJ64: =AI64 -> 90.1765 | AK64: =AJ64 -> 90.1765 | AL64: =AK64 -> 90.1765 | ... AO64: =AN64 -> 90.1765
B65: - Hubspot licenties | C65: 2 | D65: =C65*85 -> 170 | E65: =D65 -> 170 | F65: =E65 -> 170 | G65: =F65 -> 170 | H65: =G65 -> 170 | I65: =H65 -> 170 | J65: =I65 -> 170 | K65: =J65 -> 170 | L65: =K65 -> 170 | ... O65: =N65 -> 170 | Q65: =O65*1.03 -> 175.1 | R65: =Q65 -> 175.1 | S65: =R65 -> 175.1 | T65: =S65 -> 175.1 | U65: =T65 -> 175.1 | V65: =U65 -> 175.1 | W65: =V65 -> 175.1 | X65: =W65 -> 175.1 | Y65: =X65 -> 175.1 | ... AB65: =AA65 -> 175.1 | AD65: =AB65*1.03 -> 180.353 | AE65: =AD65 -> 180.353 | AF65: =AE65 -> 180.353 | AG65: =AF65 -> 180.353 | AH65: =AG65 -> 180.353 | AI65: =AH65 -> 180.353 | AJ65: =AI65 -> 180.353 | AK65: =AJ65 -> 180.353 | AL65: =AK65 -> 180.353 | ... AO65: =AN65 -> 180.353
B66: - Hubspot marketing | C66: 1 | D66: =C66*150 -> 150 | E66: =D66 -> 150 | F66: =E66 -> 150 | G66: =F66 -> 150 | H66: =G66 -> 150 | I66: =H66 -> 150 | J66: =I66 -> 150 | K66: =J66 -> 150 | L66: =K66 -> 150 | ... O66: =N66 -> 150 | Q66: =O66*1.03 -> 154.5 | R66: =Q66 -> 154.5 | S66: =R66 -> 154.5 | T66: =S66 -> 154.5 | U66: =T66 -> 154.5 | V66: =U66 -> 154.5 | W66: =V66 -> 154.5 | X66: =W66 -> 154.5 | Y66: =X66 -> 154.5 | ... AB66: =AA66 -> 154.5 | AD66: =AB66*1.03 -> 159.135 | AE66: =AD66 -> 159.135 | AF66: =AE66 -> 159.135 | AG66: =AF66 -> 159.135 | AH66: =AG66 -> 159.135 | AI66: =AH66 -> 159.135 | AJ66: =AI66 -> 159.135 | AK66: =AJ66 -> 159.135 | AL66: =AK66 -> 159.135 | ... AO66: =AN66 -> 159.135
B67: - Overige marketing tooling | D67: 200 | E67: 200 | F67: 200 | G67: 200 | H67: 200 | I67: 200 | J67: 200 | K67: 200 | L67: 200 | M67: 200 | N67: 200 | O67: 200 | Q67: =O67*1.03 -> 206 | R67: =Q67 -> 206 | S67: =R67 -> 206 | T67: =S67 -> 206 | U67: =T67 -> 206 | V67: =U67 -> 206 | W67: =V67 -> 206 | X67: =W67 -> 206 | Y67: =X67 -> 206 | ... AB67: =AA67 -> 206 | AD67: =AB67*1.03 -> 212.18 | AE67: =AD67 -> 212.18 | AF67: =AE67 -> 212.18 | AG67: =AF67 -> 212.18 | AH67: =AG67 -> 212.18 | AI67: =AH67 -> 212.18 | AJ67: =AI67 -> 212.18 | AK67: =AJ67 -> 212.18 | AL67: =AK67 -> 212.18 | ... AO67: =AN67 -> 212.18
B68: - API koppelingen | D68: 100 | E68: 100 | F68: 100 | G68: 100 | H68: 100 | I68: 100 | J68: 100 | K68: 100 | L68: 100 | M68: 100 | N68: 100 | O68: 100 | Q68: =O68*1.03 -> 103 | R68: =Q68 -> 103 | S68: =R68 -> 103 | T68: =S68 -> 103 | U68: =T68 -> 103 | V68: =U68 -> 103 | W68: =V68 -> 103 | X68: =W68 -> 103 | Y68: =X68 -> 103 | ... AB68: =AA68 -> 103 | AD68: =AB68*1.03 -> 106.09 | AE68: =AD68 -> 106.09 | AF68: =AE68 -> 106.09 | AG68: =AF68 -> 106.09 | AH68: =AG68 -> 106.09 | AI68: =AH68 -> 106.09 | AJ68: =AI68 -> 106.09 | AK68: =AJ68 -> 106.09 | AL68: =AK68 -> 106.09 | ... AO68: =AN68 -> 106.09
B69: - IT beheer | D69: =SUM(D17:D25)*100+150 -> 270 | E69: =SUM(E17:E25)*100+150 -> 270 | F69: =SUM(F17:F25)*100+150 -> 270 | G69: =SUM(G17:G25)*100+150 -> 270 | H69: =SUM(H17:H25)*100+150 -> 270 | I69: =SUM(I17:I25)*100+150 -> 270 | J69: =SUM(J17:J25)*100+150 -> 570 | K69: =SUM(K17:K25)*100+150 -> 570 | ... O69: =SUM(O17:O25)*100+150 -> 630 | Q69: =SUM(Q17:Q25)*100+150 -> 820 | R69: =SUM(R17:R25)*100+150 -> 820 | S69: =SUM(S17:S25)*100+150 -> 820 | T69: =SUM(T17:T25)*100+150 -> 1030 | U69: =SUM(U17:U25)*100+150 -> 1150 | V69: =SUM(V17:V25)*100+150 -> 1150 | W69: =SUM(W17:W25)*100+150 -> 1150 | X69: =SUM(X17:X25)*100+150 -> 1150 | ... AB69: =SUM(AB17:AB25)*100+150 -> 1270 | AD69: =SUM(AD17:AD25)*100+150 -> 1730 | AE69: =SUM(AE17:AE25)*100+150 -> 1730 | AF69: =SUM(AF17:AF25)*100+150 -> 1730 | AG69: =SUM(AG17:AG25)*100+150 -> 1930 | AH69: =SUM(AH17:AH25)*100+150 -> 1930 | AI69: =SUM(AI17:AI25)*100+150 -> 1930 | AJ69: =SUM(AJ17:AJ25)*100+150 -> 1930 | AK69: =SUM(AK17:AK25)*100+150 -> 1930 | ... AO69: =SUM(AO17:AO25)*100+150 -> 2110
B70: - Overige automatisering (10%) | D70: =0.1*SUM(D62:D69) -> 150 | E70: =0.1*SUM(E62:E69) -> 150 | F70: =0.1*SUM(F62:F69) -> 150 | G70: =0.1*SUM(G62:G69) -> 150 | H70: =0.1*SUM(H62:H69) -> 150 | I70: =0.1*SUM(I62:I69) -> 150 | J70: =0.1*SUM(J62:J69) -> 180 | K70: =0.1*SUM(K62:K69) -> 180 | ... O70: =0.1*SUM(O62:O69) -> 186 | Q70: =0.1*SUM(Q62:Q69) -> 235.515 | R70: =0.1*SUM(R62:R69) -> 235.515 | S70: =0.1*SUM(S62:S69) -> 235.515 | T70: =0.1*SUM(T62:T69) -> 256.515 | U70: =0.1*SUM(U62:U69) -> 268.515 | V70: =0.1*SUM(V62:V69) -> 268.515 | W70: =0.1*SUM(W62:W69) -> 268.515 | X70: =0.1*SUM(X62:X69) -> 268.515 | ... AB70: =0.1*SUM(AB62:AB69) -> 280.515 | AD70: =0.1*SUM(AD62:AD69) -> 331.12045 | AE70: =0.1*SUM(AE62:AE69) -> 331.12045 | AF70: =0.1*SUM(AF62:AF69) -> 331.12045 | AG70: =0.1*SUM(AG62:AG69) -> 351.12045 | AH70: =0.1*SUM(AH62:AH69) -> 351.12045 | AI70: =0.1*SUM(AI62:AI69) -> 351.12045 | AJ70: =0.1*SUM(AJ62:AJ69) -> 351.12045 | AK70: =0.1*SUM(AK62:AK69) -> 351.12045 | ... AO70: =0.1*SUM(AO62:AO69) -> 369.12045

Sheet Blad1
I1: Eenmalig | J1: Maand
B2: Deelneming | C2: Omzet | D2: FTE | E2: Adviesfee | F2: Uren | G2: Eigen medewerkers | H2: AFAS+Hubspot | I2: Implementatiekosten AFAS+Hubspot | J2: Maandkosten | K2: Pakket
B3: IT-Connectie | C3: 3700000 | D3: 13 | E3: 4180 | F3: 4700 | H3: =350+360 -> 710 | I3: 26615 | J3: =SUM(E3:H3) -> 9590 | K3: Foundation+
B4: Covolt | C4: 3200000 | D4: 25 | E4: =5275 -> 5275 | F4: 19722 | H4: =521+124 -> 645 | I4: =1750*3+15200 -> 20450 | J4: =SUM(E4:H4) -> 25642 | K4: Growth+
B5: WDL Kredietfondsen | C5: 3400000 | D5: 11 | E5: 5775 | F5: =4000 -> 4000 | H5: 606 | I5: 20000 | J5: =SUM(E5:H5) -> 10381 | K5: Foundation+
B6: Blenddata | C6: 2100000 | D6: 19 | E6: 3620 | F6: 4000 | H6: =1125+130+150 -> 1405 | I6: 5000 | J6: =SUM(E6:H6) -> 9025 | K6: Foundation
B7: Baeken | C7: 2800000 | D7: 30 | E7: 2000 | F7: 3000 | G7: =3200*1.08*1.2 -> 4147.2 | H7: 1200 | I7: 13000 | J7: =SUM(E7:H7) -> 10347.2 | K7: Foundation
